Workbook

Sheet Instructivo
C1: INSTITUTO HONDUREÑO DE SEGURIDAD SOCIAL
C2: INSTRUCTIVO PARA EL LLENADO DE LA MATRIZ DE RIESGOS
B4: I. INTRODUCCIÓN
B5: La presente guía se ha elaborado para facilitar y orientar al personal de la Unidad de Riesgos, enlaces de riesgos operacionales ubicados en las diferentes dependencias del IHSS, y demás personal en la identificación, evaluación y registro de riesgos del IHSS, con base en los procesos y procedimientos institucionales, así como los que surgen en las diferentes operaciones, transacciones y actividades que se desarrollan.
B6: Se pretende describir los principales riesgos que pueden presentarse en los diferentes procesos y/o procedimientos operativos de cada uno de los regímenes del IHSS y áreas de la administración central.
B7: Cada Gerente, Subgerente o Jefe debe administrar los principales procesos y procedimientos operativos que se ejecutan en las áreas que dirigen, de manera periódica debe mantener comunicación cercana con el Departamento de Organizaciones y Métodos con el propósito de conocer el portafolio de procesos y procedimientos correspondientes.
B8: Es importante destacar que los procesos y procedimientos deben estar actualizados, es decir que considere los cambios tecnológicos, legales, normativos y otros factores internos o externos que pueden afectarlos.
B10: II. OBJETIVO
B11: Diseñar las diferentes consideraciones que faciliten a la Unidad de Gestión de Riesgos, diferentes áreas y enlaces de riesgos operacionales autorizados, la identificación, evaluación y medición de los diferentes riesgos operativos, tecnológicos y legales, con un llenado adecuado del formato de matriz de riesgos oficial; incluyendo la forma de documentar controles preventivos, detectivos y correctivos y la mecánica de cálculo automático del Valor del Riesgo Residual.
B13: III. CONCEPTOS BÁSICOS SOBRE RIESGOS Y GENERALIDADES DEL FORMATO DE LA MATRIZ DE RIESGOS DEL IHSS
B14: Se entiende por riesgo, la posibilidad de que un evento ocurra que tendría un impacto negativo en la consecución de los objetivos (de la persona, empresa o institución); y, por control, las políticas, normas, procedimientos, instructivos y otras acciones para prevenir, detectar o corregir riesgos.
B15: En el proceso de gestión de los riesgos, es necesaria la intervención de TODOS los empleados del IHSS que participan de las diferentes fases de los procesos, ya que conocen su funcionamiento y deben orientar el desarrollo de dicha gestión.
B16: La plantilla del formato de matriz de riesgos cuentas con diferentes columnas de información los cuales deben llenarse, por esta razón el personal de la Unidad de Gestión de Riesgos, enlaces de riesgos operacional u otro personal debe tener en cuenta las siguientes generalidades:
B18: 1. La plantilla consta de cuatro hojas:
C19: a) Instructivo (Instrucciones sobre el llenado de la matriz de riesgos)
C20: b) Matriz Consolidada (registro por riesgo).
C21: c) Otras tablas (Definiciones de controles por riesgo).
C22: d) Listas (tablas de respaldo para validaciones y listas desplegables).
B24: 2. Convenciones de captura de acuerdo al color de las columnas (leyenda):
C25: Celdas en color blanco: Ingreso manual.
C26: Celdas en color oro claro: Listas desplegables (valores predefinidos)
C27: Celdas en color verde claro: Cálculo automático, estas celdas no se pueden modificar.
C28: Celdas en color azul claro: Uso exclusivo para riesgos de tipo tecnológico.
B30: 3. En la Matriz Consolidada, el campo “Riesgo Residual” reproducirá exactamente la misma redacción del “Riesgo Inherente”, conforme a la pauta ya establecida en el Manual. El cálculo asociado se refleja únicamente en el campo “Valor del Riesgo Residual”.
B33: IV. INSUMOS O ENTRADAS:
B34: Los principales insumos para la gestión de riesgos son los objetivos institucionales vigentes, procesos y procedimientos, normativas aplicables, evidencias de operación de controles y registros de incidentes.
B36: V. DOCUMENTOS DE REFERENCIA:
C37: Manual de Gestión Integral de Riesgos del IHSS
C38: Reporte de eventos de riesgos
C39: Procedimiento de Monitoreo de Controles
B41: VI. DESCRIPCIÓN E INSTRUCCIONES PARA EL LLENADO DE LOS CAMPOS DE LA MATRIZ:
B42: Para facilitar el llenado del formato de matriz de riesgos se establecen diferentes instrucciones y pasos a seguir para aplicarse y facilitar la evaluación de los riesgos. La Matriz de Riesgos está compuesta por distintos campos de información, es importante señalar que, para el caso de las matrices de riesgos tecnológicos el formato de matrices de riesgos contara con 3 columnas adicionales a las que se describen en este apartado estas son: amenazas, vulnerabilidades y los activos de información. A continuación, se describe la información correspondiente a cada columna:
B44: No.: | C44: Todos los riesgos deben enumerarse desde 1 hasta la cantidad de riesgos que identifique cada uno de los Regímenes, áreas administrativas a nivel central, región norte y otras regiones donde el IHSS presenta servicios. (ejemplo, 1,2,3,4,5, 6...1000 etc.).
B45: Código del Riesgo: | C45: Llenado automático. Se codifica siguiendo la convención institucional por tipo de riesgo, área/régimen y número secuencial. Ejemplo: RO-GTIC-01, RO-GTIC-02
B46: Tipo de Riesgo: | C46: Selección manual. Seleccionar el tipo de riesgo: Operativo, Legal o Tecnológico.
B47: Proceso / Procedimiento: | C47: Escribir el proceso o procedimiento que se ve afectado por el riesgo que se evalúa. Se debe considerar contar con las políticas, procesos y procedimientos aplicables al área actualizados.
B48: Objetivos estratégicos: | C48: De acuerdo al PEI se debe Especificar el Objetivo estratégico institucional que se ve afectado por el riesgo identificado.
B49: Riesgo Inherente: | C49: Se escribe el nombre del riesgo. Estos se identificarán y evaluarán de sus principales procesos/ procedimientos con respecto a: • Aquellos relacionados a operaciones no autorizadas, extravíos de bienes, uso indebido de facultades y poderes, operaciones no reveladas entre otras. • Errores o fallas relacionadas a los servicios, modelos, otorgamiento de beneficios a derecho habientes, pensionados, jubilados, así como errores en; contratos y en el registro de datos u operaciones. • Errores contables, errores en procesos, información o datos incompletos o inexistentes. Se escribe el nombre del riesgo. Estos se identificarán y evaluarán de sus principales procesos/ procedimientos con respecto a: • Aquellos relacionados a operaciones no autorizadas, extravíos de bienes, uso indebido de facultades y poderes, operaciones no reveladas entre otras. • Errores o fallas relacionadas a los servicios, modelos, otorgamiento de beneficios a derecho habientes, pensionados, jubilados, así como errores en; contratos y en el registro de datos u operaciones. • Errores contables, errores en procesos, información o datos incompletos o inexistentes • Incumplimiento de plazos o responsabilidades regulatorias, normativas, contractuales o legales. • Debilidades en la Seguridad de los Sistemas de Información de los regímenes. • Daños o debilidades en la protección de loa activos físicos de los regímenes y áreas de la administración central. • Registros incorrectos en operaciones de los patronos, derechohabientes y los proveedores. • Fallas en; hardware, en software, medios de almacenamiento, telecomunicaciones y energía. • Divulgación de información, practicas improcedentes, servicios defectuosos. • Mantenimiento oportuno para reanudar las interrupciones provocadas respecto al funcionamiento de sistemas, hardware que permitan la continuidad de los servicios prestados a los derechohabientes en los diferentes regímenes. • Probables Incumplimiento con los elementos del control interno institucional y normativa de la CNBS, así como de otras leyes y reglamentación aplicables. • Debilidades o deficiencias en los principales procesos de las áreas con mayor exposición al riesgo • Otros Riesgos Operacionales que afecten los objetivos estratégicos de los regímenes y áreas de la administración Central del IHSS.
C50: En materia tecnológica aquellos riesgos relacionados a las posibilidades de escenarios relacionados a: • Vulneración de los sistemas de información, ataques informáticos o ciberataques, robo de información, uso de claves de accesos y niveles de autorización de manera inadecuada. • Códigos dañinos, errores humanos, denegación de servicios, interrupción de servicios, intrusiones externas, acceso no autorizado a la información, modificación y borrado de la información, incumplimientos a políticas de seguridad entre otros escenarios de riesgos posibles.
C51: En materia Legal lo riesgos relacionados a escenarios respecto a: • Litigios con proveedores, demandas de tipo laboral, otros escenarios de demandas.
C52: Tomar en consideración las actividades críticas identificadas en las de sus principales procesos. Es importante tomar en cuenta el entorno interno y externo donde opera cada Régimen o área administrativa sea a nivel central o de otras regiones donde el IHSS presta servicios a sus derechohabientes o beneficiarios. Cada Director, Gerente, Subgerente, Jefe de Unidad o personal de apoyo debe considerar el riesgo al que esta expuestas los edificios o instalaciones físicas relacionados con los eventos de riesgos y su cercanía a zonas costeras, ríos, fallas geológicas, gasolineras, por otro lado, tomar en cuenta situaciones internas propios de los edificios que pueden detonar riesgos de interrupción de actividades por alguna debilidad que pueda presentar los mismos si este fuera el caso.
B53: Evaluación: | C53: Está compuesta por los siguientes 3 apartados: • Descripción: se debe detallar el riesgo identificado, justificando la existencia del riesgo, Planteamiento de visión de futuro acerca de la situación del riesgo, es importante que se pueda consultar reportes del sistema de información, log, consultas al sistema, otros registros, que facilite la descripción de la situación o la experiencia del personal del área en la que se está evaluando el riesgo.
C54: • Causas: describir los factores, situaciones o condiciones que originaron el riesgo identificado. Algunos ejemplos de causas que pueden ocasionar riesgos pueden ser: controles inexistentes, falta de supervisión u omisión de revisión o validaciones, ausencia de segregación de deberes, controles no operando o sin funcionamiento, mal diseño de procesos o ineficientes, eventos externos, documentos inadecuados o inexistentes, errores en procesos de conciliación, errores de cálculo, falta de capacitación, negligencia, ausencia de monitoreo de requisitos legales o regulatorios, cambios regulatorios no implementados oportunamente o pasados por alto o no tomados en cuenta, carencia de comunicación interdepartamental o entre las áreas, inexistencia de canales de denuncia, cultura que tolera riesgos, conflictos de interés, carencia de capacitación continuada con el código de ética del IHSS, Tercerización de servicios con falta de supervisión, monitoreo o carencia de evaluación de desempeño periódico. Incumplimiento de parte de proveedores no gestionados, contratos outsourcing no actualizados o con evaluación de desempeño, alta concentración de proveedores o proveedor único. Aquí solo se muestras algunos ejemplos, sin embargo, el riesgo operativo por proceso identificado indicara las principales causas posibles de manera puntual.
C55: • Efectos: describir las consecuencias o impactos que puede generar la materialización del riesgo. Algunos ejemplos son: Pérdidas financieras, daños a la reputación, multas y sanciones, interrupción del negocio y sus principales servicios o operaciones, desconfianza del público en general, interrupción de la cadena de suministro, interrupción o retraso en la distribución de medicamentos, seguridad de los sistemas comprometida, exposición de datos de derechohabientes, empleados, patronos o proveedores, deficientes desempeño operativo o estratégico, daños a la infraestructura, Interrupción en la captación de ingresos, incremento de costos operativos, incremento por gastos por litigios, incremento de costos por defensa legal, perdidas de inversiones en tecnología, imagen pública negativa, pérdida de confianza del derecho habiente, investigaciones regulatorias, incremento de costos de remediación y corrección, paralización operativa, afectación de la cadena de suministros. Incapacidad para cumplir con plazos y compromisos, perdida de datos críticos, caída de sistemas clave, exposición a ciberataque futuros, obsolescencia tecnológica, mayor rotación de personal, conflictos de interés o internos. • Todo lo anterior solamente son algunos ejemplos, sin embargo, la causa y efecto puntual de riesgos será determinado por el dueño del proceso y los que operan los controles con el soporte del Jefe inmediato y el enlace de riesgo operacional.
B56: Frecuencia (probabilidad): | C56: Toma valores del 1 al 5 y se selecciona de la lista aprobada, de acuerdo a la siguiente tabla:
B69: Impacto: | C69: Toma valores del 1 al 5 y se selecciona de la lista aprobada, de acuerdo a la siguiente tabla:
B95: Valor del Riesgo Inherente: | C95: Se calcula de forma automática como: Valor del Riesgo Inherente = Frecuencia + Impacto – 1
B96: Nivel del Riesgo Inherente: | C96: Campo que se actualiza de forma automática. Se determina conforme a la siguiente tabla:
B112: Responsable o dueño del riesgo: | C112: Escribir e indicar el área o régimen responsable.
B113: Régimen afectado: | C113: Seleccionar el régimen que se ve afectado por el riesgo evaluado.
B114: Transversalidad o interrelación con otros riesgos: | C114: Completar según corresponda con los riesgos que se relaciona.
B115: Amenazas: | C115: Exclusiva para riesgos de tipo tecnológico. Especificar los eventos, acciones o incidentes potenciales que podrían afectar la confidencialidad, integridad o disponibilidad de los activos de la información
B116: Vulnerabilidades: | C116: Exclusiva para riesgos de tipo tecnológico. Anotar las debilidades, fallos o carencias en los activos, procesos o controles que pueden ser aprovechadas por una amenaza para materializar un riesgo
B117: Activos de Información: | C117: Exclusiva para riesgos de tipo tecnológico. Identificar y describir los recursos de información, tecnológicos o de infraestructura que requieren protección (ejemplo: sistemas, bases de datos, redes, equipos, aplicaciones, personal o conocimiento
B119: VII. REGISTRO DE CONTROLES POR TIPO
C120: Para cada riesgo, documentar los controles existentes por tipo para la mitigación de los riesgos identificados, estos tipos de controles son:
B121: Preventivo: | C121: Control Interno utilizado para evitar que eventos no deseados, errores y otras ocurrencias.
B122: Detectivo: | C122: Diseñados para detectar y reportar cuando los errores, omisiones, usos no autorizados o registros ocurren.
B123: Correctivo: | C123: Diseñados para corregir errores, omisiones y usos no autorizados una vez que son detectados.
B124: Descripción (por cada tipo de control): | C124: Se detalla el control con el que se cuenta en el área para gestionar el riesgo que se ha identificado, cabe señalar que cuando haya varios controles del mismo tipo: describir todos los controles en esta columna y seleccionar un único nivel de la escala que refleje su efecto combinado sobre el riesgo. Cuando no existan controles de un tipo para el riesgo, en la descripción se consignará “No hay”.
B125: Escala de efectividad: | C125: Se debe seleccionar de acuerdo al tipo de control que se esté evaluando, se selecciona de la lista despegable; misma que se encuentra conformada de la siguiente manera:
B126: Inexistente: | C126: Se utiliza cuando no hay controles del tipo correspondiente; la descripción consignará “No hay”.
B127: Inefectivo: | C127: Existe control, pero no funciona o no mitiga.
B128: Razonable: | C128: Existen debilidades en el diseño e implementación de control y requieren modificaciones importantes para su mejoramiento, o están parcialmente de acuerdo con normativa, no están socializados e implementados. Los controles reducen la probabilidad e impacto de en un 30%.
B129: Parcialmente efectivo: | C129: Se realizan actividades de control que permiten mitigar el riesgo de manera parcial, están aprobados y socializados, pero no están totalmente implementados. Los controles reducen la probabilidad e impacto en un 50%.
B130: Moderado: | C130: Se realizan actividades de control que permiten administrar o mitigar los riesgos, existen situaciones que los controles no mitigan los riesgos en un nivel bajo respecto a las causas de su probabilidad de ocurrencia, sin embargo, los controles reducen la probabilidad e impacto en un 85%.
B131: Alta efectividad: | C131: Se realizan actividades control que permiten mitigar o administrar los riesgos y sus causas, los controles reducen la probabilidad e impacto en un 90%.
B132: Nivel de efectividad de controles: | C132: El campo es llenado de forma automática una vez seleccionada la escala. Este campo toma valores de 0 al 5 según lo definido en Procedimiento de Controles de Riesgos.
... B134: Nivel de Automatización de los Controles: | C134: Se seleccionará de la lista desplegable entre Automatizado, Semi-automatizado o Manual.
B141: VIII. EFECTIVIDAD TOTAL PONDERADA Y CÁLCULO DEL RESIDUAL
B142: Efectividad Total Ponderada de los Controles (ETP): Se calcula automáticamente con la expresión: ETP= 0.70 x EP + 0.15 x ED + 0.15 x EC, donde EP, ED y EC son los porcentajes de efectividad de los controles preventivo, detectivo y correctivo registrados en la fila del riesgo.
B143: Las ponderaciones no se redistribuyen cuando un tipo de control no exista; en ese caso su % corresponderá a 0% por haber seleccionado la Escala Inexistente.
B144: Riesgo Residual: Este campo se llena de forma automática. Se consigna el mismo texto del campo Riesgo Inherente.
B145: Frecuencia Residual (FR): Se calcula de forma automática como un valor entero entre 1 y la Frecuencia inherente, representando la frecuencia del riesgo después del efecto de los controles. FR=(1-ETP) x Frecuencia (*)
B146: Impacto Residual (FR): Se calcula de forma automática como un valor entero entre 1 y el Impacto inherente, representando el impacto del riesgo después del efecto de los controles. IR=(1-ETP) x Impacto (*)
B147: Valor del Riesgo Residual: Se calcula automáticamente: Valor del Riesgo Residual = Valor del Riesgo Inherente x (1- ETP). Adicionalmente, por construcción de las reglas de redondeo y asignación, se cumple la identidad: VRR = FR+IR-1
B148: El Valor del Riesgo Residual no podrá ser inferior a 1; si el cálculo arroja un valor menor, se registrará el valor de 1 como mínimo interno establecido.
B149: El Nivel del Riesgo Residual se determina automáticamente según el manual de Gestión Integral de Riesgos.
B151: (*): Para mantener la igualdad entre el Valor del Riesgo Residual por construcción y el Valor del Riesgo Residual Redondeado de la Matriz que va acorde con la metodología de riesgos y considerando la parte decimal de la Frecuencia e Impacto Residual, así como el mínimo normativo de 1 para cada valor (FR, IR, VRR), más el efecto de la ETP, estos valores (Frecuencia e Impacto Residual) se ajustan tomando estas consideraciones. Revisar la nota técnica adjunta para un mayor detalle de dicha formulación.
B153: IX. RESPUESTA AL RIESGO
B154: La respuesta se selecciona entre las cuatro categorías institucionales: Reducir, Aceptar, Transferir o Evitar, de acuerdo con el Manual.
... B158: 2. Todo control que se describa deberá contar con evidencia disponible para verificación posterior.

Sheet Matriz Consolidada
A1: No. | B1: Código de Riesgo | C1: Área | D1: Área Consolidada | E1: Tipo de Riesgo | F1: Procedimiento | G1: Objetivo(s) Estratégico(s) | H1: Riesgo Inherente | I1: Evaluación | J1: Frecuencia | K1: Impacto | L1: Valor del Riesgo Inherente | M1: Nivel de Riesgo Inherente | N1: Responsable o dueño del riesgo | O1: Régimen afectado | P1: Transversalidad o Interrelación con otros Riesgos | Q1: Amenazas (Solo para riesgos de GTIC) | R1: Vulnerabilidades (Solo para riesgos de GTIC) | S1: Activos de Información (Solo para riesgos de GTIC) | T1: Descripción de Control(es) Preventivo(s) | U1: Escala de efectividad de control(es) preventivo(s) | V1: Nivel de efectividad de control(es) preventivo(s) | W1: % efectividad de control(es) preventivo(s) | X1: Descripción de Control(es) Detectivo(s) | Y1: Escala de efectividad de control(es) detectivo(s) | Z1: Nivel de efectividad de control(es) detectivo(s) | AA1: % efectividad de control detectivo | AB1: Descripción de Control(es) Correctivo(s) | AC1: Escala de efectividad de control(es) correctivo(s) | AD1: Nivel de efectividad de control(es) correctivo(s) | AE1: % efectividad de control correctivo | AF1: Nivel de Automatización de los Controles | AG1: Efectividad Total Ponderada de los Controles | AH1: Riesgo Residual | AI1: Frecuencia Residual | AJ1: Impacto Residual | AK1: Valor del Riesgo Residual | AL1: Nivel del Riesgo Residual | AM1: Respuesta al riesgo | AN1: Plan de Mitigación/Acciones Correctivas | AO1: No. Acciones de Mitigación | AP1: Actividades | AQ1: Cantidad de Actividades | AR1: Monitoreo/ Seguimiento | AS1: Responsables | AT1: Fecha inicio | AU1: Fecha final | AV1: Recursos | AW1: Presupuesto | AX1: Frecuencia Residual (AUX) | AY1: Impacto Residual (AUX) | AZ1: Suma Residual redondeada (AUX) | BA1: F_base (AUX) | BB1: I_base (AUX) | BC1: Tope F (AUX) | BD1: Tope I (AUX) | BE1: Capacidad F (AUX) | BF1: Capacidad I (AUX) | BG1: Resto (AUX) | BH1: Prefiere I (AUX) | BI1: Inc_I (AUX) | BJ1: Inc_F (AUX) | BK1: Valor del Riesgo Residual (AUX) | BL1: Verificación | BM1: VRR 2 | BN1: Verificar VRR 2 | BO1: Verificar Frec | BP1: Verificar Impact | BQ1: VRI-VRR | BR1: Señales de Alerta | BS1: Estado del Riesgo | BT1: Estado del Control Preventivo | BU1: Evaluación de la Efectividad del Control Preventivo | BV1: Evidencia(s) del Control Preventivo | BW1: Estado del Control Detectivo | BX1: Evaluación de la Efectividad del Control Detectivo | BY1: Evidencia(s) del Control Detectivo | BZ1: Estado del Control Correctivo | CA1: Evaluación de la Efectividad del Control Correctivo | CB1: Evidencia(s) del Control Correctivo | CC1: Observaciones del Área | CD1: Observaciones UGR
A2: 1 | B2: ROTR-AFIL-1 | C2: Afiliacion | E2: Otros Riesgos | F2: Afiliacion | H2: Creación y activación de registros en el sistema correspondientes a identidades falsas, suplantadas o personas que no cumplen criterios normativos, contractuales o internos para su afiliacion. | I2: Descripción: Posibilidad de que el IHSS registre o afilie personas naturales o jurídicas inexistentes, suplantadas o que no cumplen los requisitos de elegibilidad establecidos, debido a deficiencias en los procesos de verificación de identidad, validación documental o controles de admisión. Causas: Ausencia de validación biométrica o verificación en fuentes oficiales, procesos manuales sin doble validación, colusión interna, documentación falsificada no detectada. Efecto: Pérdidas económicas por fraude / Afectación de imagen por vinculación con identidades ficticias / | J2: 3 | K2: 5 | L2: =IF((Matriz_Riesgos[[#This Row],[Frecuencia]]+Matriz_Riesgos[[#This Row],[Impacto]]-1)=-1,"",Matriz_Riesgos[[#This Row],[Frecuencia]]+Matriz_Riesgos[[#This Row],[Impacto]]-1) -> 7 | M2: =IFERROR(VLOOKUP(Matriz_Riesgos[[#This Row],[Valor del Riesgo Inherente]],t_nivel_riesgo[],2,FALSE), "") -> Riesgo Alto | N2: Control patronal/Planilla preelaborada/Afiliacion | O2: Todos | P2: Fraude, LAFT, Operativo, incumplimiento regulatorio | T2: 1.- Verificacion de identidad del afiliado y el patrono mediante consulta a bases oficiales gubernamentales y registros institucionales para confirmar autenticidad, vigencia y consistencia de la informacion. 2.- Validacion biometrica, firma electronica o mecanismos de autenticacion digital, para confirmar correspondencia entre el solicitante y la identidad registrada. 3. Parametrización obligatoria de requisitos de elegibilidad, es decir configuracion de reglas automaticas en el sistema que impidan registrar afiliaciones que no cumplan con los requisitos normativos, documentales, salariales o de relacion laboral. El sistema debe bloquear registros incompletos, inconsistentes o fuera de parametros. 4. Segregación de funciones entre registro y aprobación, es decir: Separacion de responsabilidades entre captura, validacion y aprobacion de afiliaciones. El suistema debe impedir autoaprobaciones y mantiene trazabilidad de usuarios, cambios y autorizaciones | U2: Alta Efectividad | V2: =IFERROR(VLOOKUP(Matriz_Riesgos[[#This Row],[Escala de efectividad de control(es) preventivo(s)]],t_efectividad[],2,FALSE),"") -> 5 | W2: =IFERROR(VLOOKUP(Matriz_Riesgos[[#This Row],[Escala de efectividad de control(es) preventivo(s)]],t_efectividad[],3,FALSE),"") -> 0.9 | X2: 1. Monitoreo de afiliaciones inusuales. Es decir, generacion periodica de reportes para identificar patrones atipicos: multiples afiliaciones vinculadas a un mismo patrono, altas masivas, salarios inconsistentes o duplicidad documental. 2. Muestreo periodico de afiliaciones aprobadas para validacion documental, elegibilidad y cumplimiento de procedimientos. 3. Alertas automaticas por inconsistencias: Parametrizacion de alertas para detectar documentos duplicados, identidades repetidas, patronos inactivos o afiliaciones fuera de rango salarial permitido. | Y2: Alta Efectividad | Z2: =IFERROR(VLOOKUP(Matriz_Riesgos[[#This Row],[Escala de efectividad de control(es) detectivo(s)]],t_efectividad[],2,FALSE),"") -> 5 | AA2: =IFERROR(VLOOKUP(Matriz_Riesgos[[#This Row],[Escala de efectividad de control(es) detectivo(s)]],t_efectividad[],3,FALSE),"") -> 0.9 | AB2: 1. Inhabilitacion temporal de afiliaciones detectadas con inconsistencias hasta completar validacion. 2. Investigación interna y escalamiento. Remision de casos sospechosos a Auditoria Interna o instancia disciplinaria correspondiente. 3. Depuracion periodica de registros. revision y saneamiento de afiliaciones duplicadas, inactivas o irregulares detectadas en controles posteriores. | AC2: Alta Efectividad | AD2: =IFERROR(VLOOKUP(Matriz_Riesgos[[#This Row],[Escala de efectividad de control(es) correctivo(s)]],t_efectividad[],2,FALSE),"") -> 5 | AE2: =IFERROR(VLOOKUP(Matriz_Riesgos[[#This Row],[Escala de efectividad de control(es) correctivo(s)]],t_efectividad[],3,FALSE),"") -> 0.9 | AF2: Semiautomatizado | AG2: =IF(AND(T2="",X2="",AB2=""),"",('Otras Tablas'!$B$3*IF(W2="",0,W2)+'Otras Tablas'!$B$4*IF(AA2="",0,AA2)+'Otras Tablas'!$B$5*IF(AE2="",0,AE2))) | AH2: =IF(Matriz_Riesgos[[#This Row],[Riesgo Inherente]]="","",Matriz_Riesgos[[#This Row],[Riesgo Inherente]]) -> Creación y activación de registros en el sistema correspondientes a identidades falsas, suplantadas o personas que no cumplen criterios normativos, contractuales o internos para su afiliacion. | AI2: =IFERROR(IF(OR(Matriz_Riesgos[[#This Row],[Frecuencia]]="",Matriz_Riesgos[[#This Row],[Impacto]]="",Matriz_Riesgos[[#This Row],[Valor del Riesgo Inherente]]="",Matriz_Riesgos[[#This Row],[Valor del Riesgo Residual]]=""),"",IF(Matriz_Riesgos[[#This Row],[Valor del Riesgo Inherente]]=Matriz_Riesgos[[#This Row],[Valor del Riesgo Residual]],Matriz_Riesgos[[#This Row],[Frecuencia]],MIN(Matriz_Riesgos[[#This Row],[Tope F (AUX)]], Matriz_Riesgos[[#This Row],[F_base (AUX)]]+Matriz_Riesgos[[#This Row],[Inc_F (AUX)]]))),"") -> 1 | AJ2: =IFERROR(IF(OR(Matriz_Riesgos[[#This Row],[Frecuencia]]="",Matriz_Riesgos[[#This Row],[Impacto]]="",Matriz_Riesgos[[#This Row],[Valor del Riesgo Inherente]]="",Matriz_Riesgos[[#This Row],[Valor del Riesgo Residual]]=""),"",IF(Matriz_Riesgos[[#This Row],[Valor del Riesgo Inherente]]=Matriz_Riesgos[[#This Row],[Valor del Riesgo Residual]],Matriz_Riesgos[[#This Row],[Impacto]],MIN(Matriz_Riesgos[[#This Row],[Tope I (AUX)]], Matriz_Riesgos[[#This Row],[I_base (AUX)]]+Matriz_Riesgos[[#This Row],[Inc_I (AUX)]]))),"") -> 1 | AK2: =IFERROR(ROUND(MAX(1,Matriz_Riesgos[[#This Row],[Valor del Riesgo Inherente]]*(1 - Matriz_Riesgos[[#This Row],[Efectividad Total Ponderada de los Controles]])),0), "") -> 1 | AL2: =IFERROR(VLOOKUP(Matriz_Riesgos[[#This Row],[Valor del Riesgo Residual]],t_nivel_riesgo[],2,FALSE),"") -> Riesgo no significativo | AM2: Evitar | AN2: 1. Fortalecer validaciones automaticas de elegibilidad 2. Implementar controles de segregacion de funciones 3. Mejorar mecanismos de verificacion documental 4. Fortalecer monitoreo de afiliaciones inusuales 5. Realizar depuracion periodica de registros 6. Formalizar procedimientos de excepciones 7. Reforzar trazabilidad y auditoria 8. Capacitar al personal involucrado | AO2: 8 | AP2: 1.1 Parametrizar validaciones obligatorias 1.2. Incorporar bloqueos automaticos por inconsistencias 1.3. Validar duplicidad documental e identidad 2.1 Revisar perfiles de usuario 2.2 Eliminar permisos incompatibles 2.3 Configurar restricciones de autoaprobacion 2.4 Actualizar matrices de accesos 3.1 Estandarizar check lis documental 3.2 Capacitar al personal sobre documentos falsificados y señales de alerta 4.1 Diseñar reportes automatizados 4.2 identificar patrones atipicos 4.3 Realizar revisiones periodicas 5.1 Revisar afiliaciones duplicadas o inconsistentes 5.2 Confirmar vigencia de patronos 5.3 Corregir registros observados 6.1 Definir criterios de excepcion 6.2 Establecer niveles de autorizacion 6.3 Documentar y monitorear excepciones aprobadas 7.1 Activar bitacoras completas 7.2 Conservart historial de cambios y aprobaciones 8.1 Capacitaciones sobre LAFT, Señales de Alerta, etica y responsabilidad es de Control Interno | AQ2: 21 | AR2: 1. Revision mensual de afiliaciones aprobadas por excepcion 2. Revision mensual de Logs y Bitacoras 3. Muestreo trimestral de expedientes de afiliacion 4. Evaluacion anual de efectividad de controles | AS2: 1. Afiliacion / TI 2. Afiliacion / TI/ RRHH 3. Afiliacion / Legal / Cumplimiento 4. Cumplimiento /Auditoria / TI 5. Afiliacion / Auditoria 6. Cumplimiento / Afiliacion 7. TI / Auditoria 8. Cumplimiento / RRHH | AX2: =IFERROR((1-Matriz_Riesgos[[#This Row],[Efectividad Total Ponderada de los Controles]])*Matriz_Riesgos[[#This Row],[Frecuencia]],"") -> 0.3 | AY2: =IFERROR((1-Matriz_Riesgos[[#This Row],[Efectividad Total Ponderada de los Controles]])*Matriz_Riesgos[[#This Row],[Impacto]],"") -> 0.5 | AZ2: =IFERROR(Matriz_Riesgos[[#This Row],[Valor del Riesgo Residual]] + 1, "") -> 2 | BA2: =IFERROR(MAX(1, ROUNDDOWN(Matriz_Riesgos[[#This Row],[Frecuencia Residual (AUX)]],0)),"") -> 1 | BB2: =IFERROR(MAX(1, ROUNDDOWN(Matriz_Riesgos[[#This Row],[Impacto Residual (AUX)]],0)),"") -> 1 | BC2: =IF(Matriz_Riesgos[[#This Row],[Frecuencia]]="","",Matriz_Riesgos[[#This Row],[Frecuencia]]) -> 3 | BD2: =IF(Matriz_Riesgos[[#This Row],[Impacto]]="","",Matriz_Riesgos[[#This Row],[Impacto]]) -> 5 | BE2: =IF(OR(Matriz_Riesgos[[#This Row],[Tope F (AUX)]]="",Matriz_Riesgos[[#This Row],[F_base (AUX)]]=""),"",MAX(0,Matriz_Riesgos[[#This Row],[Tope F (AUX)]]-Matriz_Riesgos[[#This Row],[F_base (AUX)]])) -> 2 | BF2: =IF(OR(Matriz_Riesgos[[#This Row],[Tope I (AUX)]]="",Matriz_Riesgos[[#This Row],[I_base (AUX)]]=""),"",MAX(0,Matriz_Riesgos[[#This Row],[Tope I (AUX)]]-Matriz_Riesgos[[#This Row],[I_base (AUX)]])) -> 4 | BG2: =IF(OR(Matriz_Riesgos[[#This Row],[Suma Residual redondeada (AUX)]]="",Matriz_Riesgos[[#This Row],[F_base (AUX)]]="",Matriz_Riesgos[[#This Row],[I_base (AUX)]]=""),"",MAX(0,Matriz_Riesgos[[#This Row],[Suma Residual redondeada (AUX)]]-(Matriz_Riesgos[[#This Row],[F_base (AUX)]]+Matriz_Riesgos[[#This Row],[I_base (AUX)]]))) -> 0 | BH2: =IF(OR(Matriz_Riesgos[[#This Row],[Impacto Residual (AUX)]]="",Matriz_Riesgos[[#This Row],[Frecuencia Residual (AUX)]]=""),"",IF(MOD(Matriz_Riesgos[[#This Row],[Impacto Residual (AUX)]],1) > MOD(Matriz_Riesgos[[#This Row],[Frecuencia Residual (AUX)]],1),1,IF(MOD(Matriz_Riesgos[[#This Row],[Impacto Residual (AUX)]],1) = MOD(Matriz_Riesgos[[#This Row],[Frecuencia Residual (AUX)]],1),1,0))) -> 1 | BI2: =IF(OR(Matriz_Riesgos[[#This Row],[Resto (AUX)]]="",Matriz_Riesgos[[#This Row],[Capacidad I (AUX)]]="",Matriz_Riesgos[[#This Row],[Capacidad F (AUX)]]=""),"",IF(Matriz_Riesgos[[#This Row],[Resto (AUX)]]=0, 0,IF(Matriz_Riesgos[[#This Row],[Resto (AUX)]]=1,MIN(Matriz_Riesgos[[#This Row],[Capacidad I (AUX)]], IF(OR(Matriz_Riesgos[[#This Row],[Prefiere I (AUX)]]=1,Matriz_Riesgos[[#This Row],[Capacidad F (AUX)]]=0),1,0)),MIN(Matriz_Riesgos[[#This Row],[Capacidad I (AUX)]],IF(Matriz_Riesgos[[#This Row],[Prefiere I (AUX)]]=1,1 + IF(Matriz_Riesgos[[#This Row],[Capacidad F (AUX)]]>0,0,1),IF(Matriz_Riesgos[[#This Row],[Capacidad F (AUX)]]>0,1,2)))))) -> 0 | BJ2: =IF(OR(Matriz_Riesgos[[#This Row],[Resto (AUX)]]="",Matriz_Riesgos[[#This Row],[Capacidad F (AUX)]]="",Matriz_Riesgos[[#This Row],[Inc_I (AUX)]]=""),"",MIN(Matriz_Riesgos[[#This Row],[Capacidad F (AUX)]], MAX(0,Matriz_Riesgos[[#This Row],[Resto (AUX)]]-Matriz_Riesgos[[#This Row],[Inc_I (AUX)]]))) -> 0 | BK2: =IFERROR(MAX(ROUND(Matriz_Riesgos[[#This Row],[Frecuencia Residual (AUX)]]+Matriz_Riesgos[[#This Row],[Impacto Residual (AUX)]]-1+Matriz_Riesgos[[#This Row],[Efectividad Total Ponderada de los Controles]],0),1),"") -> 1 | BL2: =IFERROR(Matriz_Riesgos[[#This Row],[Valor del Riesgo Residual]]-Matriz_Riesgos[[#This Row],[Valor del Riesgo Residual (AUX)]],"") -> 0 | BM2: =IFERROR(Matriz_Riesgos[[#This Row],[Frecuencia Residual]]+Matriz_Riesgos[[#This Row],[Impacto Residual]]-1,"") -> 1 | BN2: =IFERROR(Matriz_Riesgos[[#This Row],[Valor del Riesgo Residual]]-Matriz_Riesgos[[#This Row],[VRR 2]],"") -> 0 | BO2: =IFERROR(Matriz_Riesgos[[#This Row],[Frecuencia]]-Matriz_Riesgos[[#This Row],[Frecuencia Residual]],"") -> 2 | BP2: =IFERROR(Matriz_Riesgos[[#This Row],[Impacto]]-Matriz_Riesgos[[#This Row],[Impacto Residual]],"") -> 4 | BQ2: =IFERROR(Matriz_Riesgos[[#This Row],[Valor del Riesgo Inherente]]-Matriz_Riesgos[[#This Row],[Valor del Riesgo Residual]],"") -> 6 | BR2: 1. Afiliaciones masivas atipicas 2. Patronos sin actividad verificable 3. Duplicidad documental 4. Excepciones recurrentes 5. Coincidencias de datos entre afiliados 6. Autoaprobaciones o intervencion repetitiva de funcionarios
A3: 2 | B3: ROTR-AFIL-2 | C3: Afiliacion | E3: Otros Riesgos | F3: Afiliacion | H3: Emisión de autorización o prestación efectiva de un servicio de salud a una persona que, no figura como afiliado al sistema o tiene afiliacion suspendida | I3: Descripción: Posibilidad de que el IHSS autorice y/o preste servicios médicos a personas que no se encuentren afiliadas, que hayan perdido su condición de afiliación o que no cumplan los requisitos legales y contractuales para acceder a los servicios, debido a fallas en los controles de validación de derechos, Causas: Sistemas desactualizados o sin integración, errores manuales del personal de admisiones, suplantación de identidad, falta de capacitación del personal, Parametrización incorrecta en el sistema de admisiones. Efecto: Pago de servicios no recuperables, investigaciones administrativas, redes organizadas para uso indebido de servicios | J3: 4 | K3: 4 | L3: =IF((Matriz_Riesgos[[#This Row],[Frecuencia]]+Matriz_Riesgos[[#This Row],[Impacto]]-1)=-1,"",Matriz_Riesgos[[#This Row],[Frecuencia]]+Matriz_Riesgos[[#This Row],[Impacto]]-1) -> 7 | M3: =IFERROR(VLOOKUP(Matriz_Riesgos[[#This Row],[Valor del Riesgo Inherente]],t_nivel_riesgo[],2,FALSE), "") -> Riesgo Alto | N3: Control patronal/Planilla preelaborada | O3: EM | P3: Fraude, riesgo operativo y financiero | T3: 1.- Validación automática y obligatoria del estado de afiliación previo a la emisión de autorizaciones y prestación de servicios. 2.- Integración entre los sistemas de afiliación, recaudación y atención médica para garantizar información actualizada en tiempo real. 3.- Restricción de acceso al sistema para impedir la generación manual de autorizaciones sin validación previa. 4.- Implementación de perfiles y segregación de funciones para el personal autorizado. 5.- Capacitación periódica al personal administrativo y asistencial sobre procedimientos de verificación de afiliación. 6.- Establecimiento de políticas y procedimientos formales para validación de derechos y cobertura. 7.- Uso de mecanismos de autenticación del afiliado mediante documento de identidad y validación biométrica cuando aplique. | U3: Alta Efectividad | V3: =IFERROR(VLOOKUP(Matriz_Riesgos[[#This Row],[Escala de efectividad de control(es) preventivo(s)]],t_efectividad[],2,FALSE),"") -> 5 | W3: =IFERROR(VLOOKUP(Matriz_Riesgos[[#This Row],[Escala de efectividad de control(es) preventivo(s)]],t_efectividad[],3,FALSE),"") -> 0.9 | X3: 1. Generación de reportes periódicos de autorizaciones emitidas a afiliados suspendidos o inexistentes. 2.- Conciliaciones mensuales entre base de afiliados activos y servicios prestados. 3.- Monitoreo de excepciones y alertas automáticas sobre inconsistencias en afiliación. 4.- Auditorías internas sobre expedientes médicos y autorizaciones emitidas. 5.- Revisión aleatoria de atenciones médicas otorgadas en periodos críticos o fuera de parámetros normales. 6.- Seguimiento de usuarios con alto volumen de anulaciones o modificaciones de autorizaciones. | Y3: Alta Efectividad | Z3: =IFERROR(VLOOKUP(Matriz_Riesgos[[#This Row],[Escala de efectividad de control(es) detectivo(s)]],t_efectividad[],2,FALSE),"") -> 5 | AA3: =IFERROR(VLOOKUP(Matriz_Riesgos[[#This Row],[Escala de efectividad de control(es) detectivo(s)]],t_efectividad[],3,FALSE),"") -> 0.9 | AB3: 1. Suspensión inmediata de accesos o permisos a usuarios involucrados en irregularidades. 2. Anulación de autorizaciones emitidas indebidamente cuando proceda. 3. Recuperación administrativa o legal de valores pagados indebidamente. 4. Investigación interna de casos detectados y documentación de hallazgos. 5. Aplicación de medidas disciplinarias conforme normativa institucional. 6. Actualización de procedimientos y controles derivados de incidentes identificados. | AC3: Alta Efectividad | AD3: =IFERROR(VLOOKUP(Matriz_Riesgos[[#This Row],[Escala de efectividad de control(es) correctivo(s)]],t_efectividad[],2,FALSE),"") -> 5 | AE3: =IFERROR(VLOOKUP(Matriz_Riesgos[[#This Row],[Escala de efectividad de control(es) correctivo(s)]],t_efectividad[],3,FALSE),"") -> 0.9 | AF3: Semiautomatizado | AG3: =IF(AND(T3="",X3="",AB3=""),"",('Otras Tablas'!$B$3*IF(W3="",0,W3)+'Otras Tablas'!$B$4*IF(AA3="",0,AA3)+'Otras Tablas'!$B$5*IF(AE3="",0,AE3))) | AH3: =IF(Matriz_Riesgos[[#This Row],[Riesgo Inherente]]="","",Matriz_Riesgos[[#This Row],[Riesgo Inherente]]) -> Emisión de autorización o prestación efectiva de un servicio de salud a una persona que, no figura como afiliado al sistema o tiene afiliacion suspendida | AI3: =IFERROR(IF(OR(Matriz_Riesgos[[#This Row],[Frecuencia]]="",Matriz_Riesgos[[#This Row],[Impacto]]="",Matriz_Riesgos[[#This Row],[Valor del Riesgo Inherente]]="",Matriz_Riesgos[[#This Row],[Valor del Riesgo Residual]]=""),"",IF(Matriz_Riesgos[[#This Row],[Valor del Riesgo Inherente]]=Matriz_Riesgos[[#This Row],[Valor del Riesgo Residual]],Matriz_Riesgos[[#This Row],[Frecuencia]],MIN(Matriz_Riesgos[[#This Row],[Tope F (AUX)]], Matriz_Riesgos[[#This Row],[F_base (AUX)]]+Matriz_Riesgos[[#This Row],[Inc_F (AUX)]]))),"") -> 1 | AJ3: =IFERROR(IF(OR(Matriz_Riesgos[[#This Row],[Frecuencia]]="",Matriz_Riesgos[[#This Row],[Impacto]]="",Matriz_Riesgos[[#This Row],[Valor del Riesgo Inherente]]="",Matriz_Riesgos[[#This Row],[Valor del Riesgo Residual]]=""),"",IF(Matriz_Riesgos[[#This Row],[Valor del Riesgo Inherente]]=Matriz_Riesgos[[#This Row],[Valor del Riesgo Residual]],Matriz_Riesgos[[#This Row],[Impacto]],MIN(Matriz_Riesgos[[#This Row],[Tope I (AUX)]], Matriz_Riesgos[[#This Row],[I_base (AUX)]]+Matriz_Riesgos[[#This Row],[Inc_I (AUX)]]))),"") -> 1 | AK3: =IFERROR(ROUND(MAX(1,Matriz_Riesgos[[#This Row],[Valor del Riesgo Inherente]]*(1 - Matriz_Riesgos[[#This Row],[Efectividad Total Ponderada de los Controles]])),0), "") -> 1 | AL3: =IFERROR(VLOOKUP(Matriz_Riesgos[[#This Row],[Valor del Riesgo Residual]],t_nivel_riesgo[],2,FALSE),"") -> Riesgo no significativo | AM3: Evitar | AN3: 1. Implementar controles automáticos de bloqueo ante inconsistencias de afiliación. 2. Realizar auditorías periódicas sobre autorizaciones y servicios otorgados. 3. Reforzar programas de capacitación y concientización del personal. 4. Actualizar matrices de acceso y perfiles de usuarios. 5. Establecer indicadores de monitoreo y seguimiento de incidentes LAFT asociados al proceso. 6. Implementar revisiones periódicas de calidad de datos de afiliación. | AP3: 1. Ejecutar validaciones automáticas diarias de afiliación activa. 2. Elaborar reportes mensuales de incidencias detectadas. 3. Realizar cruces de información entre afiliación, recaudación y servicios médicos. 4. Capacitar trimestralmente al personal involucrado. 5. Documentar y dar seguimiento a incidentes detectados. 6. Revisar y actualizar procedimientos operativos cada seis meses. 7. Aplicar pruebas de funcionamiento de controles tecnológicos. 8. Presentar resultados de monitoreo al comité de cumplimiento o riesgo institucional. | AX3: =IFERROR((1-Matriz_Riesgos[[#This Row],[Efectividad Total Ponderada de los Controles]])*Matriz_Riesgos[[#This Row],[Frecuencia]],"") -> 0.4 | AY3: =IFERROR((1-Matriz_Riesgos[[#This Row],[Efectividad Total Ponderada de los Controles]])*Matriz_Riesgos[[#This Row],[Impacto]],"") -> 0.4 | AZ3: =IFERROR(Matriz_Riesgos[[#This Row],[Valor del Riesgo Residual]] + 1, "") -> 2 | BA3: =IFERROR(MAX(1, ROUNDDOWN(Matriz_Riesgos[[#This Row],[Frecuencia Residual (AUX)]],0)),"") -> 1 | BB3: =IFERROR(MAX(1, ROUNDDOWN(Matriz_Riesgos[[#This Row],[Impacto Residual (AUX)]],0)),"") -> 1 | BC3: =IF(Matriz_Riesgos[[#This Row],[Frecuencia]]="","",Matriz_Riesgos[[#This Row],[Frecuencia]]) -> 4 | BD3: =IF(Matriz_Riesgos[[#This Row],[Impacto]]="","",Matriz_Riesgos[[#This Row],[Impacto]]) -> 4 | BE3: =IF(OR(Matriz_Riesgos[[#This Row],[Tope F (AUX)]]="",Matriz_Riesgos[[#This Row],[F_base (AUX)]]=""),"",MAX(0,Matriz_Riesgos[[#This Row],[Tope F (AUX)]]-Matriz_Riesgos[[#This Row],[F_base (AUX)]])) -> 3 | BF3: =IF(OR(Matriz_Riesgos[[#This Row],[Tope I (AUX)]]="",Matriz_Riesgos[[#This Row],[I_base (AUX)]]=""),"",MAX(0,Matriz_Riesgos[[#This Row],[Tope I (AUX)]]-Matriz_Riesgos[[#This Row],[I_base (AUX)]])) -> 3 | BG3: =IF(OR(Matriz_Riesgos[[#This Row],[Suma Residual redondeada (AUX)]]="",Matriz_Riesgos[[#This Row],[F_base (AUX)]]="",Matriz_Riesgos[[#This Row],[I_base (AUX)]]=""),"",MAX(0,Matriz_Riesgos[[#This Row],[Suma Residual redondeada (AUX)]]-(Matriz_Riesgos[[#This Row],[F_base (AUX)]]+Matriz_Riesgos[[#This Row],[I_base (AUX)]]))) -> 0 | BH3: =IF(OR(Matriz_Riesgos[[#This Row],[Impacto Residual (AUX)]]="",Matriz_Riesgos[[#This Row],[Frecuencia Residual (AUX)]]=""),"",IF(MOD(Matriz_Riesgos[[#This Row],[Impacto Residual (AUX)]],1) > MOD(Matriz_Riesgos[[#This Row],[Frecuencia Residual (AUX)]],1),1,IF(MOD(Matriz_Riesgos[[#This Row],[Impacto Residual (AUX)]],1) = MOD(Matriz_Riesgos[[#This Row],[Frecuencia Residual (AUX)]],1),1,0))) -> 1 | BI3: =IF(OR(Matriz_Riesgos[[#This Row],[Resto (AUX)]]="",Matriz_Riesgos[[#This Row],[Capacidad I (AUX)]]="",Matriz_Riesgos[[#This Row],[Capacidad F (AUX)]]=""),"",IF(Matriz_Riesgos[[#This Row],[Resto (AUX)]]=0, 0,IF(Matriz_Riesgos[[#This Row],[Resto (AUX)]]=1,MIN(Matriz_Riesgos[[#This Row],[Capacidad I (AUX)]], IF(OR(Matriz_Riesgos[[#This Row],[Prefiere I (AUX)]]=1,Matriz_Riesgos[[#This Row],[Capacidad F (AUX)]]=0),1,0)),MIN(Matriz_Riesgos[[#This Row],[Capacidad I (AUX)]],IF(Matriz_Riesgos[[#This Row],[Prefiere I (AUX)]]=1,1 + IF(Matriz_Riesgos[[#This Row],[Capacidad F (AUX)]]>0,0,1),IF(Matriz_Riesgos[[#This Row],[Capacidad F (AUX)]]>0,1,2)))))) -> 0 | BJ3: =IF(OR(Matriz_Riesgos[[#This Row],[Resto (AUX)]]="",Matriz_Riesgos[[#This Row],[Capacidad F (AUX)]]="",Matriz_Riesgos[[#This Row],[Inc_I (AUX)]]=""),"",MIN(Matriz_Riesgos[[#This Row],[Capacidad F (AUX)]], MAX(0,Matriz_Riesgos[[#This Row],[Resto (AUX)]]-Matriz_Riesgos[[#This Row],[Inc_I (AUX)]]))) -> 0 | BK3: =IFERROR(MAX(ROUND(Matriz_Riesgos[[#This Row],[Frecuencia Residual (AUX)]]+Matriz_Riesgos[[#This Row],[Impacto Residual (AUX)]]-1+Matriz_Riesgos[[#This Row],[Efectividad Total Ponderada de los Controles]],0),1),"") -> 1 | BL3: =IFERROR(Matriz_Riesgos[[#This Row],[Valor del Riesgo Residual]]-Matriz_Riesgos[[#This Row],[Valor del Riesgo Residual (AUX)]],"") -> 0 | BM3: =IFERROR(Matriz_Riesgos[[#This Row],[Frecuencia Residual]]+Matriz_Riesgos[[#This Row],[Impacto Residual]]-1,"") -> 1 | BN3: =IFERROR(Matriz_Riesgos[[#This Row],[Valor del Riesgo Residual]]-Matriz_Riesgos[[#This Row],[VRR 2]],"") -> 0 | BO3: =IFERROR(Matriz_Riesgos[[#This Row],[Frecuencia]]-Matriz_Riesgos[[#This Row],[Frecuencia Residual]],"") -> 3 | BP3: =IFERROR(Matriz_Riesgos[[#This Row],[Impacto]]-Matriz_Riesgos[[#This Row],[Impacto Residual]],"") -> 3 | BQ3: =IFERROR(Matriz_Riesgos[[#This Row],[Valor del Riesgo Inherente]]-Matriz_Riesgos[[#This Row],[Valor del Riesgo Residual]],"") -> 6 | BR3: 1. Emisión recurrente de autorizaciones manuales o fuera del flujo normal. 2. Prestación de servicios a personas con afiliación suspendida, inexistente o inconsistente. 3. Incremento inusual de anulaciones o correcciones de autorizaciones. 4. Usuarios internos que realizan modificaciones frecuentes en registros de afiliación. 5. Diferencias entre la base de afiliados activos y los servicios facturados. 6. Reclamos o denuncias relacionados con uso indebido de cobertura médica. 7. Accesos al sistema fuera de horarios habituales o desde ubicaciones no autorizadas. 8. Uso reiterado de credenciales por distintos usuarios.
A4: 3 | B4: ROTR-PENS-3 | C4: Pensiones | E4: Otros Riesgos | F4: Reconocimiento de Pensiones | H4: Aprobación y reconocimiento de una prestación pensional a una persona que no cumple los requisitos legales | I4: Descripción: Posibilidad de que el IHSS reconozca y otorgue una pensión con base en información falsa, adulterada o incompleta respecto a semanas cotizadas, historia laboral, edad, estado civil, invalidez u otros requisitos legales, debido a deficiencias en los procesos de validación y verificación documental Causas: Procesos manuales sin doble revisión técnica, colusión entre funcionarios y solicitantes, falsificación documental no detectada. Efecto: Alto impacto financiero y reputacional, procesos disciplinarios contra funcionarios | J4: 3 | K4: 5 | L4: =IF((Matriz_Riesgos[[#This Row],[Frecuencia]]+Matriz_Riesgos[[#This Row],[Impacto]]-1)=-1,"",Matriz_Riesgos[[#This Row],[Frecuencia]]+Matriz_Riesgos[[#This Row],[Impacto]]-1) -> 7 | M4: =IFERROR(VLOOKUP(Matriz_Riesgos[[#This Row],[Valor del Riesgo Inherente]],t_nivel_riesgo[],2,FALSE), "") -> Riesgo Alto | N4: Pensiones | O4: IVM | P4: Fraude, LAFT, incumplimiento regulatorio. Riesgo operativo, Riesgo reputacional, corrupcion, tecnologico | T4: 1. Validación biométrica del solicitante 2. Implementación de controles de acceso y trazabilidad sobre expedientes físicos y electrónicos. 3. Verificación de autenticidad de documentos mediante consultas a registros oficiales, bases de datos institucionales y fuentes independientes. 4. Aplicación de procesos de debida diligencia para verificar la identidad del solicitante, beneficiarios y apoderados, cuando corresponda. 5. Segregación de funciones entre las áreas responsables de recepción, análisis, validación, recomendación y aprobación de prestaciones. 6. Capacitación periódica al personal sobre prevención de fraude, corrupción, LAFT y detección de documentación falsa o alterada. 7. | U4: Inexistente | V4: =IFERROR(VLOOKUP(U4,Listas!$A$30:$C$35,2,FALSE),"") | W4: =IFERROR(VLOOKUP(U4,Listas!$A$30:$C$35,3,FALSE),"") | X4: 1. Indicador de pensiones revocadas (cuántas pensiones que ya habían sido reconocidas, posteriormente fueron anuladas, revocadas o dejadas sin efecto por detectar inconsistencias, errores o fraude). 2.- Análisis de patrones inusuales en reconocimientos 3. Revisiones de calidad y validaciones independientes sobre expedientes previamente aprobados. 4. Auditorías periódicas de expedientes pensionales y beneficios otorgados. 5. Generación de reportes de alertas sobre modificaciones posteriores a la aprobación de beneficios. 6. Revisiones aleatorias de expedientes por parte de las áreas de control interno, cumplimiento o auditoría 7. Monitoreo de usuarios con accesos privilegiados o intervenciones inusuales sobre expedientes de prestaciones. | Y4: Inexistente | Z4: =IFERROR(VLOOKUP(Y4,Listas!$A$30:$C$35,2,FALSE),"") | AA4: =IFERROR(VLOOKUP(Y4,Listas!$A$30:$C$35,3,FALSE),"") | AB4: 1.- Suspensión preventiva del trámite o del beneficio cuando se identifiquen inconsistencias relevantes o indicios de fraude. 2. Recuperación de pagos efectuados indebidamente conforme al marco legal aplicable. 3. Aplicación de medidas disciplinarias cuando se determine participación o negligencia de funcionarios. 4. Fortalecimiento de controles y procedimientos asociados al hallazgo identificado. 5. Comunicación y reporte a las autoridades competentes cuando existan indicios de fraude, corrupción, falsificación documental, lavado de activos u otros ilícitos. | AC4: Inexistente | AD4: =IFERROR(VLOOKUP(AC4,Listas!$A$30:$C$35,2,FALSE),"") | AE4: =IFERROR(VLOOKUP(AC4,Listas!$A$30:$C$35,3,FALSE),"") | AG4: =IF(AND(T4="",X4="",AB4=""),"",('Otras Tablas'!$B$3*IF(W4="",0,W4)+'Otras Tablas'!$B$4*IF(AA4="",0,AA4)+'Otras Tablas'!$B$5*IF(AE4="",0,AE4))) | AH4: =IF(Matriz_Riesgos[[#This Row],[Riesgo Inherente]]="","",Matriz_Riesgos[[#This Row],[Riesgo Inherente]]) -> Aprobación y reconocimiento de una prestación pensional a una persona que no cumple los requisitos legales | AI4: =IFERROR(IF(OR(Matriz_Riesgos[[#This Row],[Frecuencia]]="",Matriz_Riesgos[[#This Row],[Impacto]]="",Matriz_Riesgos[[#This Row],[Valor del Riesgo Inherente]]="",Matriz_Riesgos[[#This Row],[Valor del Riesgo Residual]]=""),"",IF(Matriz_Riesgos[[#This Row],[Valor del Riesgo Inherente]]=Matriz_Riesgos[[#This Row],[Valor del Riesgo Residual]],Matriz_Riesgos[[#This Row],[Frecuencia]],MIN(Matriz_Riesgos[[#This Row],[Tope F (AUX)]], Matriz_Riesgos[[#This Row],[F_base (AUX)]]+Matriz_Riesgos[[#This Row],[Inc_F (AUX)]]))),"") | AJ4: =IFERROR(IF(OR(Matriz_Riesgos[[#This Row],[Frecuencia]]="",Matriz_Riesgos[[#This Row],[Impacto]]="",Matriz_Riesgos[[#This Row],[Valor del Riesgo Inherente]]="",Matriz_Riesgos[[#This Row],[Valor del Riesgo Residual]]=""),"",IF(Matriz_Riesgos[[#This Row],[Valor del Riesgo Inherente]]=Matriz_Riesgos[[#This Row],[Valor del Riesgo Residual]],Matriz_Riesgos[[#This Row],[Impacto]],MIN(Matriz_Riesgos[[#This Row],[Tope I (AUX)]], Matriz_Riesgos[[#This Row],[I_base (AUX)]]+Matriz_Riesgos[[#This Row],[Inc_I (AUX)]]))),"") | AK4: =IFERROR(ROUND(MAX(1,Matriz_Riesgos[[#This Row],[Valor del Riesgo Inherente]]*(1 - Matriz_Riesgos[[#This Row],[Efectividad Total Ponderada de los Controles]])),0), "") | AL4: =IFERROR(VLOOKUP(Matriz_Riesgos[[#This Row],[Valor del Riesgo Residual]],t_nivel_riesgo[],2,FALSE),"") | AM4: Evitar | AN4: 1. Revisar y fortalecer los procedimientos de evaluación y aprobación de prestaciones. 2. Incrementar la frecuencia de auditorías sobre expedientes de alto riesgo. 3. Establecer mecanismos de doble revisión para casos complejos o excepcionales. 4. Actualizar periódicamente los criterios de segmentación y perfiles de riesgo. 5. Desarrollar programas continuos de capacitación y concienciación para el personal involucrado. 6. Implementar indicadores de gestión y alertas tempranas para identificar desviaciones en los procesos de aprobación. | AO4: 6 | AP4: 1. Verificación documental y legal de requisitos 2. Validación de identidad y autenticidad documental 3. Consulta en listas restrictivas y PEP 4. Revisión independiente de expedientes seleccionados 5. Auditoría de prestaciones aprobadas 6. Capacitación en fraude, LAFT y control interno 7. Actualización de procedimientos y controles 8. Seguimiento de hallazgos y planes de acción | AQ4: 8 | AX4: =IFERROR((1-Matriz_Riesgos[[#This Row],[Efectividad Total Ponderada de los Controles]])*Matriz_Riesgos[[#This Row],[Frecuencia]],"") | AY4: =IFERROR((1-Matriz_Riesgos[[#This Row],[Efectividad Total Ponderada de los Controles]])*Matriz_Riesgos[[#This Row],[Impacto]],"") | AZ4: =IFERROR(Matriz_Riesgos[[#This Row],[Valor del Riesgo Residual]] + 1, "") | BA4: =IFERROR(MAX(1, ROUNDDOWN(Matriz_Riesgos[[#This Row],[Frecuencia Residual (AUX)]],0)),"") | BB4: =IFERROR(MAX(1, ROUNDDOWN(Matriz_Riesgos[[#This Row],[Impacto Residual (AUX)]],0)),"") | BC4: =IF(Matriz_Riesgos[[#This Row],[Frecuencia]]="","",Matriz_Riesgos[[#This Row],[Frecuencia]]) -> 3 | BD4: =IF(Matriz_Riesgos[[#This Row],[Impacto]]="","",Matriz_Riesgos[[#This Row],[Impacto]]) -> 5 | BE4: =IF(OR(Matriz_Riesgos[[#This Row],[Tope F (AUX)]]="",Matriz_Riesgos[[#This Row],[F_base (AUX)]]=""),"",MAX(0,Matriz_Riesgos[[#This Row],[Tope F (AUX)]]-Matriz_Riesgos[[#This Row],[F_base (AUX)]])) | BF4: =IF(OR(Matriz_Riesgos[[#This Row],[Tope I (AUX)]]="",Matriz_Riesgos[[#This Row],[I_base (AUX)]]=""),"",MAX(0,Matriz_Riesgos[[#This Row],[Tope I (AUX)]]-Matriz_Riesgos[[#This Row],[I_base (AUX)]])) | BG4: =IF(OR(Matriz_Riesgos[[#This Row],[Suma Residual redondeada (AUX)]]="",Matriz_Riesgos[[#This Row],[F_base (AUX)]]="",Matriz_Riesgos[[#This Row],[I_base (AUX)]]=""),"",MAX(0,Matriz_Riesgos[[#This Row],[Suma Residual redondeada (AUX)]]-(Matriz_Riesgos[[#This Row],[F_base (AUX)]]+Matriz_Riesgos[[#This Row],[I_base (AUX)]]))) | BH4: =IF(OR(Matriz_Riesgos[[#This Row],[Impacto Residual (AUX)]]="",Matriz_Riesgos[[#This Row],[Frecuencia Residual (AUX)]]=""),"",IF(MOD(Matriz_Riesgos[[#This Row],[Impacto Residual (AUX)]],1) > MOD(Matriz_Riesgos[[#This Row],[Frecuencia Residual (AUX)]],1),1,IF(MOD(Matriz_Riesgos[[#This Row],[Impacto Residual (AUX)]],1) = MOD(Matriz_Riesgos[[#This Row],[Frecuencia Residual (AUX)]],1),1,0))) | BI4: =IF(OR(Matriz_Riesgos[[#This Row],[Resto (AUX)]]="",Matriz_Riesgos[[#This Row],[Capacidad I (AUX)]]="",Matriz_Riesgos[[#This Row],[Capacidad F (AUX)]]=""),"",IF(Matriz_Riesgos[[#This Row],[Resto (AUX)]]=0, 0,IF(Matriz_Riesgos[[#This Row],[Resto (AUX)]]=1,MIN(Matriz_Riesgos[[#This Row],[Capacidad I (AUX)]], IF(OR(Matriz_Riesgos[[#This Row],[Prefiere I (AUX)]]=1,Matriz_Riesgos[[#This Row],[Capacidad F (AUX)]]=0),1,0)),MIN(Matriz_Riesgos[[#This Row],[Capacidad I (AUX)]],IF(Matriz_Riesgos[[#This Row],[Prefiere I (AUX)]]=1,1 + IF(Matriz_Riesgos[[#This Row],[Capacidad F (AUX)]]>0,0,1),IF(Matriz_Riesgos[[#This Row],[Capacidad F (AUX)]]>0,1,2)))))) | BJ4: =IF(OR(Matriz_Riesgos[[#This Row],[Resto (AUX)]]="",Matriz_Riesgos[[#This Row],[Capacidad F (AUX)]]="",Matriz_Riesgos[[#This Row],[Inc_I (AUX)]]=""),"",MIN(Matriz_Riesgos[[#This Row],[Capacidad F (AUX)]], MAX(0,Matriz_Riesgos[[#This Row],[Resto (AUX)]]-Matriz_Riesgos[[#This Row],[Inc_I (AUX)]]))) | BK4: =IFERROR(MAX(ROUND(Matriz_Riesgos[[#This Row],[Frecuencia Residual (AUX)]]+Matriz_Riesgos[[#This Row],[Impacto Residual (AUX)]]-1+Matriz_Riesgos[[#This Row],[Efectividad Total Ponderada de los Controles]],0),1),"") | BL4: =IFERROR(Matriz_Riesgos[[#This Row],[Valor del Riesgo Residual]]-Matriz_Riesgos[[#This Row],[Valor del Riesgo Residual (AUX)]],"") | BM4: =IFERROR(Matriz_Riesgos[[#This Row],[Frecuencia Residual]]+Matriz_Riesgos[[#This Row],[Impacto Residual]]-1,"") | BN4: =IFERROR(Matriz_Riesgos[[#This Row],[Valor del Riesgo Residual]]-Matriz_Riesgos[[#This Row],[VRR 2]],"") | BO4: =IFERROR(Matriz_Riesgos[[#This Row],[Frecuencia]]-Matriz_Riesgos[[#This Row],[Frecuencia Residual]],"") | BP4: =IFERROR(Matriz_Riesgos[[#This Row],[Impacto]]-Matriz_Riesgos[[#This Row],[Impacto Residual]],"") | BQ4: =IFERROR(Matriz_Riesgos[[#This Row],[Valor del Riesgo Inherente]]-Matriz_Riesgos[[#This Row],[Valor del Riesgo Residual]],"") | BR4: 1. Expedientes con documentación incompleta, inconsistente o alterada. 2. Incremento inusual de solicitudes provenientes de una misma fuente o gestor. 3. Modificaciones frecuentes de datos personales antes de la aprobación. 4. Presión indebida para acelerar procesos o evitar controles establecidos. 5. Coincidencias con listas restrictivas, sancionatorias o registros de investigación. 6. Falta de soporte documental suficiente para acreditar el derecho a la prestación. 7. Pagos o beneficios aprobados bajo esquemas de excepción sin la debida justificación y autorización.
A5: 4 | B5: ROTR-PENS-4 | C5: Pensiones | E5: Otros Riesgos | F5: Pago de Pensiones | H5: Pago de una o más cuotas de pension, posteriores a la fecha real de fallecimiento del pensionado, sin que el sistema del IHSS haya bloqueado oportunamente el beneficio | I5: Descripción: Posibilidad de que la entidad continúe efectuando el pago de mesadas pensionales después del fallecimiento del beneficiario, debido a fallas en la actualización de información vital, ausencia de cruces con bases oficiales o deficiencias en los controles de verificación periódica. Causas: No existe un proceso de cruce de base de datos del IHSS contra la del RNP (Defunciones), Retraso, por parte de los familiares, en el reporte del fallecimiento del pensionado, Debilidad en el proceso de supervivencia Cobro fraudulento por terceros (familiares o apoderados) Efecto: Perdida financiera, riesgo reputacional (mal manejo de fondos publicos) | J5: 3 | K5: 5 | L5: =IF((Matriz_Riesgos[[#This Row],[Frecuencia]]+Matriz_Riesgos[[#This Row],[Impacto]]-1)=-1,"",Matriz_Riesgos[[#This Row],[Frecuencia]]+Matriz_Riesgos[[#This Row],[Impacto]]-1) -> 7 | M5: =IFERROR(VLOOKUP(Matriz_Riesgos[[#This Row],[Valor del Riesgo Inherente]],t_nivel_riesgo[],2,FALSE), "") -> Riesgo Alto | N5: Pensiones | O5: IVM | P5: Fraude, LAFT, incumplimiento regulatorio. Riesgo operativo, Riesgo reputacional | T5: 1. Cruce automático y periódico con base de datos del RNP (defunciones) 2. Proceso de sobrevivencia digital (Huella) | X5: 1. Indicador de pagos posteriores a fecha de fallecimiento (detectadas / total pensiones x100). 2. Auditorías periódicas a pensionados de mayor edad 3. Reportes de inconsistencias bancarias (Planillas dejadas de cobrar) | AB5: 1.- Suspension de pago 2. Denuncia penal | AG5: =IF(AND(T5="",X5="",AB5=""),"",('Otras Tablas'!$B$3*IF(W5="",0,W5)+'Otras Tablas'!$B$4*IF(AA5="",0,AA5)+'Otras Tablas'!$B$5*IF(AE5="",0,AE5))) | AH5: =IF(Matriz_Riesgos[[#This Row],[Riesgo Inherente]]="","",Matriz_Riesgos[[#This Row],[Riesgo Inherente]]) -> Pago de una o más cuotas de pension, posteriores a la fecha real de fallecimiento del pensionado, sin que el sistema del IHSS haya bloqueado oportunamente el beneficio | AI5: =IFERROR(IF(OR(Matriz_Riesgos[[#This Row],[Frecuencia]]="",Matriz_Riesgos[[#This Row],[Impacto]]="",Matriz_Riesgos[[#This Row],[Valor del Riesgo Inherente]]="",Matriz_Riesgos[[#This Row],[Valor del Riesgo Residual]]=""),"",IF(Matriz_Riesgos[[#This Row],[Valor del Riesgo Inherente]]=Matriz_Riesgos[[#This Row],[Valor del Riesgo Residual]],Matriz_Riesgos[[#This Row],[Frecuencia]],MIN(Matriz_Riesgos[[#This Row],[Tope F (AUX)]], Matriz_Riesgos[[#This Row],[F_base (AUX)]]+Matriz_Riesgos[[#This Row],[Inc_F (AUX)]]))),"") -> 3 | AJ5: =IFERROR(IF(OR(Matriz_Riesgos[[#This Row],[Frecuencia]]="",Matriz_Riesgos[[#This Row],[Impacto]]="",Matriz_Riesgos[[#This Row],[Valor del Riesgo Inherente]]="",Matriz_Riesgos[[#This Row],[Valor del Riesgo Residual]]=""),"",IF(Matriz_Riesgos[[#This Row],[Valor del Riesgo Inherente]]=Matriz_Riesgos[[#This Row],[Valor del Riesgo Residual]],Matriz_Riesgos[[#This Row],[Impacto]],MIN(Matriz_Riesgos[[#This Row],[Tope I (AUX)]], Matriz_Riesgos[[#This Row],[I_base (AUX)]]+Matriz_Riesgos[[#This Row],[Inc_I (AUX)]]))),"") -> 5 | AK5: =IFERROR(ROUND(MAX(1,Matriz_Riesgos[[#This Row],[Valor del Riesgo Inherente]]*(1 - Matriz_Riesgos[[#This Row],[Efectividad Total Ponderada de los Controles]])),0), "") -> 7 | AL5: =IFERROR(VLOOKUP(Matriz_Riesgos[[#This Row],[Valor del Riesgo Residual]],t_nivel_riesgo[],2,FALSE),"") -> Riesgo Alto | AM5: Evitar | AX5: =IFERROR((1-Matriz_Riesgos[[#This Row],[Efectividad Total Ponderada de los Controles]])*Matriz_Riesgos[[#This Row],[Frecuencia]],"") -> 3 | AY5: =IFERROR((1-Matriz_Riesgos[[#This Row],[Efectividad Total Ponderada de los Controles]])*Matriz_Riesgos[[#This Row],[Impacto]],"") -> 5 | AZ5: =IFERROR(Matriz_Riesgos[[#This Row],[Valor del Riesgo Residual]] + 1, "") -> 8 | BA5: =IFERROR(MAX(1, ROUNDDOWN(Matriz_Riesgos[[#This Row],[Frecuencia Residual (AUX)]],0)),"") -> 3 | BB5: =IFERROR(MAX(1, ROUNDDOWN(Matriz_Riesgos[[#This Row],[Impacto Residual (AUX)]],0)),"") -> 5 | BC5: =IF(Matriz_Riesgos[[#This Row],[Frecuencia]]="","",Matriz_Riesgos[[#This Row],[Frecuencia]]) -> 3 | BD5: =IF(Matriz_Riesgos[[#This Row],[Impacto]]="","",Matriz_Riesgos[[#This Row],[Impacto]]) -> 5 | BE5: =IF(OR(Matriz_Riesgos[[#This Row],[Tope F (AUX)]]="",Matriz_Riesgos[[#This Row],[F_base (AUX)]]=""),"",MAX(0,Matriz_Riesgos[[#This Row],[Tope F (AUX)]]-Matriz_Riesgos[[#This Row],[F_base (AUX)]])) -> 0 | BF5: =IF(OR(Matriz_Riesgos[[#This Row],[Tope I (AUX)]]="",Matriz_Riesgos[[#This Row],[I_base (AUX)]]=""),"",MAX(0,Matriz_Riesgos[[#This Row],[Tope I (AUX)]]-Matriz_Riesgos[[#This Row],[I_base (AUX)]])) -> 0 | BG5: =IF(OR(Matriz_Riesgos[[#This Row],[Suma Residual redondeada (AUX)]]="",Matriz_Riesgos[[#This Row],[F_base (AUX)]]="",Matriz_Riesgos[[#This Row],[I_base (AUX)]]=""),"",MAX(0,Matriz_Riesgos[[#This Row],[Suma Residual redondeada (AUX)]]-(Matriz_Riesgos[[#This Row],[F_base (AUX)]]+Matriz_Riesgos[[#This Row],[I_base (AUX)]]))) -> 0 | BH5: =IF(OR(Matriz_Riesgos[[#This Row],[Impacto Residual (AUX)]]="",Matriz_Riesgos[[#This Row],[Frecuencia Residual (AUX)]]=""),"",IF(MOD(Matriz_Riesgos[[#This Row],[Impacto Residual (AUX)]],1) > MOD(Matriz_Riesgos[[#This Row],[Frecuencia Residual (AUX)]],1),1,IF(MOD(Matriz_Riesgos[[#This Row],[Impacto Residual (AUX)]],1) = MOD(Matriz_Riesgos[[#This Row],[Frecuencia Residual (AUX)]],1),1,0))) -> 1 | BI5: =IF(OR(Matriz_Riesgos[[#This Row],[Resto (AUX)]]="",Matriz_Riesgos[[#This Row],[Capacidad I (AUX)]]="",Matriz_Riesgos[[#This Row],[Capacidad F (AUX)]]=""),"",IF(Matriz_Riesgos[[#This Row],[Resto (AUX)]]=0, 0,IF(Matriz_Riesgos[[#This Row],[Resto (AUX)]]=1,MIN(Matriz_Riesgos[[#This Row],[Capacidad I (AUX)]], IF(OR(Matriz_Riesgos[[#This Row],[Prefiere I (AUX)]]=1,Matriz_Riesgos[[#This Row],[Capacidad F (AUX)]]=0),1,0)),MIN(Matriz_Riesgos[[#This Row],[Capacidad I (AUX)]],IF(Matriz_Riesgos[[#This Row],[Prefiere I (AUX)]]=1,1 + IF(Matriz_Riesgos[[#This Row],[Capacidad F (AUX)]]>0,0,1),IF(Matriz_Riesgos[[#This Row],[Capacidad F (AUX)]]>0,1,2)))))) -> 0 | BJ5: =IF(OR(Matriz_Riesgos[[#This Row],[Resto (AUX)]]="",Matriz_Riesgos[[#This Row],[Capacidad F (AUX)]]="",Matriz_Riesgos[[#This Row],[Inc_I (AUX)]]=""),"",MIN(Matriz_Riesgos[[#This Row],[Capacidad F (AUX)]], MAX(0,Matriz_Riesgos[[#This Row],[Resto (AUX)]]-Matriz_Riesgos[[#This Row],[Inc_I (AUX)]]))) -> 0 | BK5: =IFERROR(MAX(ROUND(Matriz_Riesgos[[#This Row],[Frecuencia Residual (AUX)]]+Matriz_Riesgos[[#This Row],[Impacto Residual (AUX)]]-1+Matriz_Riesgos[[#This Row],[Efectividad Total Ponderada de los Controles]],0),1),"") -> 7 | BL5: =IFERROR(Matriz_Riesgos[[#This Row],[Valor del Riesgo Residual]]-Matriz_Riesgos[[#This Row],[Valor del Riesgo Residual (AUX)]],"") -> 0 | BM5: =IFERROR(Matriz_Riesgos[[#This Row],[Frecuencia Residual]]+Matriz_Riesgos[[#This Row],[Impacto Residual]]-1,"") -> 7 | BN5: =IFERROR(Matriz_Riesgos[[#This Row],[Valor del Riesgo Residual]]-Matriz_Riesgos[[#This Row],[VRR 2]],"") -> 0 | BO5: =IFERROR(Matriz_Riesgos[[#This Row],[Frecuencia]]-Matriz_Riesgos[[#This Row],[Frecuencia Residual]],"") -> 0 | BP5: =IFERROR(Matriz_Riesgos[[#This Row],[Impacto]]-Matriz_Riesgos[[#This Row],[Impacto Residual]],"") -> 0 | BQ5: =IFERROR(Matriz_Riesgos[[#This Row],[Valor del Riesgo Inherente]]-Matriz_Riesgos[[#This Row],[Valor del Riesgo Residual]],"") -> 0
A6: 5 | B6: ROTR-SUBS-5 | C6: Subsidios | E6: Otros Riesgos | F6: Pago de subsidios RP | H6: Reconocimiento y pago de subsidios o pension por invalidez, derivados de un accidente laboral que no ocurrio, ocurrio fuera del ambito laboral o fue respaldado con información falsa. | I6: Descripción: Posibilidad de que se reporten y tramiten accidentes de trabajo inexistentes, simulados o alterados con el fin de obtener prestaciones económicas o asistenciales indebidas, debido a debilidades en los procesos de verificación, investigación y validación del origen del evento. Causas: Procesos manuales sin doble revisión técnica, Falta de investigación técnica del accidente, Colusión entre trabajador y empleador, Falsificación documental no detectada, Presión económica del trabajador. Efecto: Pago indebido de prestaciones economicas | J6: 3 | K6: 4 | L6: =IF((Matriz_Riesgos[[#This Row],[Frecuencia]]+Matriz_Riesgos[[#This Row],[Impacto]]-1)=-1,"",Matriz_Riesgos[[#This Row],[Frecuencia]]+Matriz_Riesgos[[#This Row],[Impacto]]-1) -> 6 | M6: =IFERROR(VLOOKUP(Matriz_Riesgos[[#This Row],[Valor del Riesgo Inherente]],t_nivel_riesgo[],2,FALSE), "") -> Riesgo Alto | N6: RP | O6: RP | P6: Fraude, operativo, financiero | T6: 1. Procedimiento formal de investigación del accidente, 2. Análisis técnico del lugar del accidente. 3. Revisión médica independiente 4. Declaración formal bajo juramento | X6: 1. Indicador de reincidencia por trabajador (Trabajador con mas de X accientes en el periodo / total de trabajadores accidentados) o empleador (No. De accidentes en la empresa / Numero de trabajadores afiliados). Esto como alerta para investigacion 2. Cruces de incapacidades recurrentes 3. Auditorías aleatorias de casos | AB6: 1. Reversión de pagos cuando proceda 2. Denuncia penal por fraude 3. Reporte a autoridad laboral competente (Empleador) | AG6: =IF(AND(T6="",X6="",AB6=""),"",('Otras Tablas'!$B$3*IF(W6="",0,W6)+'Otras Tablas'!$B$4*IF(AA6="",0,AA6)+'Otras Tablas'!$B$5*IF(AE6="",0,AE6))) | AH6: =IF(Matriz_Riesgos[[#This Row],[Riesgo Inherente]]="","",Matriz_Riesgos[[#This Row],[Riesgo Inherente]]) -> Reconocimiento y pago de subsidios o pension por invalidez, derivados de un accidente laboral que no ocurrio, ocurrio fuera del ambito laboral o fue respaldado con información falsa. | AI6: =IFERROR(IF(OR(Matriz_Riesgos[[#This Row],[Frecuencia]]="",Matriz_Riesgos[[#This Row],[Impacto]]="",Matriz_Riesgos[[#This Row],[Valor del Riesgo Inherente]]="",Matriz_Riesgos[[#This Row],[Valor del Riesgo Residual]]=""),"",IF(Matriz_Riesgos[[#This Row],[Valor del Riesgo Inherente]]=Matriz_Riesgos[[#This Row],[Valor del Riesgo Residual]],Matriz_Riesgos[[#This Row],[Frecuencia]],MIN(Matriz_Riesgos[[#This Row],[Tope F (AUX)]], Matriz_Riesgos[[#This Row],[F_base (AUX)]]+Matriz_Riesgos[[#This Row],[Inc_F (AUX)]]))),"") -> 3 | AJ6: =IFERROR(IF(OR(Matriz_Riesgos[[#This Row],[Frecuencia]]="",Matriz_Riesgos[[#This Row],[Impacto]]="",Matriz_Riesgos[[#This Row],[Valor del Riesgo Inherente]]="",Matriz_Riesgos[[#This Row],[Valor del Riesgo Residual]]=""),"",IF(Matriz_Riesgos[[#This Row],[Valor del Riesgo Inherente]]=Matriz_Riesgos[[#This Row],[Valor del Riesgo Residual]],Matriz_Riesgos[[#This Row],[Impacto]],MIN(Matriz_Riesgos[[#This Row],[Tope I (AUX)]], Matriz_Riesgos[[#This Row],[I_base (AUX)]]+Matriz_Riesgos[[#This Row],[Inc_I (AUX)]]))),"") -> 4 | AK6: =IFERROR(ROUND(MAX(1,Matriz_Riesgos[[#This Row],[Valor del Riesgo Inherente]]*(1 - Matriz_Riesgos[[#This Row],[Efectividad Total Ponderada de los Controles]])),0), "") -> 6 | AL6: =IFERROR(VLOOKUP(Matriz_Riesgos[[#This Row],[Valor del Riesgo Residual]],t_nivel_riesgo[],2,FALSE),"") -> Riesgo Alto | AM6: Evitar | AX6: =IFERROR((1-Matriz_Riesgos[[#This Row],[Efectividad Total Ponderada de los Controles]])*Matriz_Riesgos[[#This Row],[Frecuencia]],"") -> 3 | AY6: =IFERROR((1-Matriz_Riesgos[[#This Row],[Efectividad Total Ponderada de los Controles]])*Matriz_Riesgos[[#This Row],[Impacto]],"") -> 4 | AZ6: =IFERROR(Matriz_Riesgos[[#This Row],[Valor del Riesgo Residual]] + 1, "") -> 7 | BA6: =IFERROR(MAX(1, ROUNDDOWN(Matriz_Riesgos[[#This Row],[Frecuencia Residual (AUX)]],0)),"") -> 3 | BB6: =IFERROR(MAX(1, ROUNDDOWN(Matriz_Riesgos[[#This Row],[Impacto Residual (AUX)]],0)),"") -> 4 | BC6: =IF(Matriz_Riesgos[[#This Row],[Frecuencia]]="","",Matriz_Riesgos[[#This Row],[Frecuencia]]) -> 3 | BD6: =IF(Matriz_Riesgos[[#This Row],[Impacto]]="","",Matriz_Riesgos[[#This Row],[Impacto]]) -> 4 | BE6: =IF(OR(Matriz_Riesgos[[#This Row],[Tope F (AUX)]]="",Matriz_Riesgos[[#This Row],[F_base (AUX)]]=""),"",MAX(0,Matriz_Riesgos[[#This Row],[Tope F (AUX)]]-Matriz_Riesgos[[#This Row],[F_base (AUX)]])) -> 0 | BF6: =IF(OR(Matriz_Riesgos[[#This Row],[Tope I (AUX)]]="",Matriz_Riesgos[[#This Row],[I_base (AUX)]]=""),"",MAX(0,Matriz_Riesgos[[#This Row],[Tope I (AUX)]]-Matriz_Riesgos[[#This Row],[I_base (AUX)]])) -> 0 | BG6: =IF(OR(Matriz_Riesgos[[#This Row],[Suma Residual redondeada (AUX)]]="",Matriz_Riesgos[[#This Row],[F_base (AUX)]]="",Matriz_Riesgos[[#This Row],[I_base (AUX)]]=""),"",MAX(0,Matriz_Riesgos[[#This Row],[Suma Residual redondeada (AUX)]]-(Matriz_Riesgos[[#This Row],[F_base (AUX)]]+Matriz_Riesgos[[#This Row],[I_base (AUX)]]))) -> 0 | BH6: =IF(OR(Matriz_Riesgos[[#This Row],[Impacto Residual (AUX)]]="",Matriz_Riesgos[[#This Row],[Frecuencia Residual (AUX)]]=""),"",IF(MOD(Matriz_Riesgos[[#This Row],[Impacto Residual (AUX)]],1) > MOD(Matriz_Riesgos[[#This Row],[Frecuencia Residual (AUX)]],1),1,IF(MOD(Matriz_Riesgos[[#This Row],[Impacto Residual (AUX)]],1) = MOD(Matriz_Riesgos[[#This Row],[Frecuencia Residual (AUX)]],1),1,0))) -> 1 | BI6: =IF(OR(Matriz_Riesgos[[#This Row],[Resto (AUX)]]="",Matriz_Riesgos[[#This Row],[Capacidad I (AUX)]]="",Matriz_Riesgos[[#This Row],[Capacidad F (AUX)]]=""),"",IF(Matriz_Riesgos[[#This Row],[Resto (AUX)]]=0, 0,IF(Matriz_Riesgos[[#This Row],[Resto (AUX)]]=1,MIN(Matriz_Riesgos[[#This Row],[Capacidad I (AUX)]], IF(OR(Matriz_Riesgos[[#This Row],[Prefiere I (AUX)]]=1,Matriz_Riesgos[[#This Row],[Capacidad F (AUX)]]=0),1,0)),MIN(Matriz_Riesgos[[#This Row],[Capacidad I (AUX)]],IF(Matriz_Riesgos[[#This Row],[Prefiere I (AUX)]]=1,1 + IF(Matriz_Riesgos[[#This Row],[Capacidad F (AUX)]]>0,0,1),IF(Matriz_Riesgos[[#This Row],[Capacidad F (AUX)]]>0,1,2)))))) -> 0 | BJ6: =IF(OR(Matriz_Riesgos[[#This Row],[Resto (AUX)]]="",Matriz_Riesgos[[#This Row],[Capacidad F (AUX)]]="",Matriz_Riesgos[[#This Row],[Inc_I (AUX)]]=""),"",MIN(Matriz_Riesgos[[#This Row],[Capacidad F (AUX)]], MAX(0,Matriz_Riesgos[[#This Row],[Resto (AUX)]]-Matriz_Riesgos[[#This Row],[Inc_I (AUX)]]))) -> 0 | BK6: =IFERROR(MAX(ROUND(Matriz_Riesgos[[#This Row],[Frecuencia Residual (AUX)]]+Matriz_Riesgos[[#This Row],[Impacto Residual (AUX)]]-1+Matriz_Riesgos[[#This Row],[Efectividad Total Ponderada de los Controles]],0),1),"") -> 6 | BL6: =IFERROR(Matriz_Riesgos[[#This Row],[Valor del Riesgo Residual]]-Matriz_Riesgos[[#This Row],[Valor del Riesgo Residual (AUX)]],"") -> 0 | BM6: =IFERROR(Matriz_Riesgos[[#This Row],[Frecuencia Residual]]+Matriz_Riesgos[[#This Row],[Impacto Residual]]-1,"") -> 6 | BN6: =IFERROR(Matriz_Riesgos[[#This Row],[Valor del Riesgo Residual]]-Matriz_Riesgos[[#This Row],[VRR 2]],"") -> 0 | BO6: =IFERROR(Matriz_Riesgos[[#This Row],[Frecuencia]]-Matriz_Riesgos[[#This Row],[Frecuencia Residual]],"") -> 0 | BP6: =IFERROR(Matriz_Riesgos[[#This Row],[Impacto]]-Matriz_Riesgos[[#This Row],[Impacto Residual]],"") -> 0 | BQ6: =IFERROR(Matriz_Riesgos[[#This Row],[Valor del Riesgo Inherente]]-Matriz_Riesgos[[#This Row],[Valor del Riesgo Residual]],"") -> 0
A7: 6 | B7: ROTR-SUBS-6 | C7: Subsidios | E7: Otros Riesgos | F7: Prestaciones Economicas | H7: Aprobación y pago de incapacidades prolongadas que no cuenten con soporte medico adecuado, emitidas de manera reiterada por el mismo profesional o superan tiempos estándar para el diagnóstico reportado | I7: Descripción: Posibilidad de que se autoricen o paguen prórrogas de incapacidades médicas sin sustento clínico suficiente o sin cumplimiento de criterios técnicos y normativos, debido a deficiencias en los procesos de auditoría médica y control de proceso de subsidios. Causas: Falta de auditoría médica especializada, Ausencia de guías clínicas parametrizadas en el sistema. Colusión entre trabajador y profesional de salud. Debilidad en seguimiento de incapacidades prolongadas. Efecto: Pérdidas económicas, fraude, riesgo reputacional, aumento de carga operativa innecesaria | J7: 4 | K7: 4 | L7: =IF((Matriz_Riesgos[[#This Row],[Frecuencia]]+Matriz_Riesgos[[#This Row],[Impacto]]-1)=-1,"",Matriz_Riesgos[[#This Row],[Frecuencia]]+Matriz_Riesgos[[#This Row],[Impacto]]-1) -> 7 | M7: =IFERROR(VLOOKUP(Matriz_Riesgos[[#This Row],[Valor del Riesgo Inherente]],t_nivel_riesgo[],2,FALSE), "") -> Riesgo Alto | N7: EM | O7: EM | P7: Fraude, financiero, operativo, legal | T7: 1. Parametrización de días máximos por diagnóstico (según guías clínicas) 2. Auditoría médica obligatoria a partir de cierto número de días acumulados. 3. Segunda opinión médica independiente en incapacidades prolongadas. 4. Validación de coherencia entre diagnóstico y tiempo de incapacidad. | X7: 1. Indicador de incapacidades superiores al promedio sectorial. 2. eincidencia por trabajador o médico tratante. 3. Alertas automáticas por acumulación de días. 4. Análisis de incapacidades por empleador. | AB7: 1. Revisión técnica integral del caso. 2. Reporte a autoridad competente si se configura fraude. | AG7: =IF(AND(T7="",X7="",AB7=""),"",('Otras Tablas'!$B$3*IF(W7="",0,W7)+'Otras Tablas'!$B$4*IF(AA7="",0,AA7)+'Otras Tablas'!$B$5*IF(AE7="",0,AE7))) | AH7: =IF(Matriz_Riesgos[[#This Row],[Riesgo Inherente]]="","",Matriz_Riesgos[[#This Row],[Riesgo Inherente]]) -> Aprobación y pago de incapacidades prolongadas que no cuenten con soporte medico adecuado, emitidas de manera reiterada por el mismo profesional o superan tiempos estándar para el diagnóstico reportado | AI7: =IFERROR(IF(OR(Matriz_Riesgos[[#This Row],[Frecuencia]]="",Matriz_Riesgos[[#This Row],[Impacto]]="",Matriz_Riesgos[[#This Row],[Valor del Riesgo Inherente]]="",Matriz_Riesgos[[#This Row],[Valor del Riesgo Residual]]=""),"",IF(Matriz_Riesgos[[#This Row],[Valor del Riesgo Inherente]]=Matriz_Riesgos[[#This Row],[Valor del Riesgo Residual]],Matriz_Riesgos[[#This Row],[Frecuencia]],MIN(Matriz_Riesgos[[#This Row],[Tope F (AUX)]], Matriz_Riesgos[[#This Row],[F_base (AUX)]]+Matriz_Riesgos[[#This Row],[Inc_F (AUX)]]))),"") -> 4 | AJ7: =IFERROR(IF(OR(Matriz_Riesgos[[#This Row],[Frecuencia]]="",Matriz_Riesgos[[#This Row],[Impacto]]="",Matriz_Riesgos[[#This Row],[Valor del Riesgo Inherente]]="",Matriz_Riesgos[[#This Row],[Valor del Riesgo Residual]]=""),"",IF(Matriz_Riesgos[[#This Row],[Valor del Riesgo Inherente]]=Matriz_Riesgos[[#This Row],[Valor del Riesgo Residual]],Matriz_Riesgos[[#This Row],[Impacto]],MIN(Matriz_Riesgos[[#This Row],[Tope I (AUX)]], Matriz_Riesgos[[#This Row],[I_base (AUX)]]+Matriz_Riesgos[[#This Row],[Inc_I (AUX)]]))),"") -> 4 | AK7: =IFERROR(ROUND(MAX(1,Matriz_Riesgos[[#This Row],[Valor del Riesgo Inherente]]*(1 - Matriz_Riesgos[[#This Row],[Efectividad Total Ponderada de los Controles]])),0), "") -> 7 | AL7: =IFERROR(VLOOKUP(Matriz_Riesgos[[#This Row],[Valor del Riesgo Residual]],t_nivel_riesgo[],2,FALSE),"") -> Riesgo Alto | AM7: Evitar | AX7: =IFERROR((1-Matriz_Riesgos[[#This Row],[Efectividad Total Ponderada de los Controles]])*Matriz_Riesgos[[#This Row],[Frecuencia]],"") -> 4 | AY7: =IFERROR((1-Matriz_Riesgos[[#This Row],[Efectividad Total Ponderada de los Controles]])*Matriz_Riesgos[[#This Row],[Impacto]],"") -> 4 | AZ7: =IFERROR(Matriz_Riesgos[[#This Row],[Valor del Riesgo Residual]] + 1, "") -> 8 | BA7: =IFERROR(MAX(1, ROUNDDOWN(Matriz_Riesgos[[#This Row],[Frecuencia Residual (AUX)]],0)),"") -> 4 | BB7: =IFERROR(MAX(1, ROUNDDOWN(Matriz_Riesgos[[#This Row],[Impacto Residual (AUX)]],0)),"") -> 4 | BC7: =IF(Matriz_Riesgos[[#This Row],[Frecuencia]]="","",Matriz_Riesgos[[#This Row],[Frecuencia]]) -> 4 | BD7: =IF(Matriz_Riesgos[[#This Row],[Impacto]]="","",Matriz_Riesgos[[#This Row],[Impacto]]) -> 4 | BE7: =IF(OR(Matriz_Riesgos[[#This Row],[Tope F (AUX)]]="",Matriz_Riesgos[[#This Row],[F_base (AUX)]]=""),"",MAX(0,Matriz_Riesgos[[#This Row],[Tope F (AUX)]]-Matriz_Riesgos[[#This Row],[F_base (AUX)]])) -> 0 | BF7: =IF(OR(Matriz_Riesgos[[#This Row],[Tope I (AUX)]]="",Matriz_Riesgos[[#This Row],[I_base (AUX)]]=""),"",MAX(0,Matriz_Riesgos[[#This Row],[Tope I (AUX)]]-Matriz_Riesgos[[#This Row],[I_base (AUX)]])) -> 0 | BG7: =IF(OR(Matriz_Riesgos[[#This Row],[Suma Residual redondeada (AUX)]]="",Matriz_Riesgos[[#This Row],[F_base (AUX)]]="",Matriz_Riesgos[[#This Row],[I_base (AUX)]]=""),"",MAX(0,Matriz_Riesgos[[#This Row],[Suma Residual redondeada (AUX)]]-(Matriz_Riesgos[[#This Row],[F_base (AUX)]]+Matriz_Riesgos[[#This Row],[I_base (AUX)]]))) -> 0 | BH7: =IF(OR(Matriz_Riesgos[[#This Row],[Impacto Residual (AUX)]]="",Matriz_Riesgos[[#This Row],[Frecuencia Residual (AUX)]]=""),"",IF(MOD(Matriz_Riesgos[[#This Row],[Impacto Residual (AUX)]],1) > MOD(Matriz_Riesgos[[#This Row],[Frecuencia Residual (AUX)]],1),1,IF(MOD(Matriz_Riesgos[[#This Row],[Impacto Residual (AUX)]],1) = MOD(Matriz_Riesgos[[#This Row],[Frecuencia Residual (AUX)]],1),1,0))) -> 1 | BI7: =IF(OR(Matriz_Riesgos[[#This Row],[Resto (AUX)]]="",Matriz_Riesgos[[#This Row],[Capacidad I (AUX)]]="",Matriz_Riesgos[[#This Row],[Capacidad F (AUX)]]=""),"",IF(Matriz_Riesgos[[#This Row],[Resto (AUX)]]=0, 0,IF(Matriz_Riesgos[[#This Row],[Resto (AUX)]]=1,MIN(Matriz_Riesgos[[#This Row],[Capacidad I (AUX)]], IF(OR(Matriz_Riesgos[[#This Row],[Prefiere I (AUX)]]=1,Matriz_Riesgos[[#This Row],[Capacidad F (AUX)]]=0),1,0)),MIN(Matriz_Riesgos[[#This Row],[Capacidad I (AUX)]],IF(Matriz_Riesgos[[#This Row],[Prefiere I (AUX)]]=1,1 + IF(Matriz_Riesgos[[#This Row],[Capacidad F (AUX)]]>0,0,1),IF(Matriz_Riesgos[[#This Row],[Capacidad F (AUX)]]>0,1,2)))))) -> 0 | BJ7: =IF(OR(Matriz_Riesgos[[#This Row],[Resto (AUX)]]="",Matriz_Riesgos[[#This Row],[Capacidad F (AUX)]]="",Matriz_Riesgos[[#This Row],[Inc_I (AUX)]]=""),"",MIN(Matriz_Riesgos[[#This Row],[Capacidad F (AUX)]], MAX(0,Matriz_Riesgos[[#This Row],[Resto (AUX)]]-Matriz_Riesgos[[#This Row],[Inc_I (AUX)]]))) -> 0 | BK7: =IFERROR(MAX(ROUND(Matriz_Riesgos[[#This Row],[Frecuencia Residual (AUX)]]+Matriz_Riesgos[[#This Row],[Impacto Residual (AUX)]]-1+Matriz_Riesgos[[#This Row],[Efectividad Total Ponderada de los Controles]],0),1),"") -> 7 | BL7: =IFERROR(Matriz_Riesgos[[#This Row],[Valor del Riesgo Residual]]-Matriz_Riesgos[[#This Row],[Valor del Riesgo Residual (AUX)]],"") -> 0 | BM7: =IFERROR(Matriz_Riesgos[[#This Row],[Frecuencia Residual]]+Matriz_Riesgos[[#This Row],[Impacto Residual]]-1,"") -> 7 | BN7: =IFERROR(Matriz_Riesgos[[#This Row],[Valor del Riesgo Residual]]-Matriz_Riesgos[[#This Row],[VRR 2]],"") -> 0 | BO7: =IFERROR(Matriz_Riesgos[[#This Row],[Frecuencia]]-Matriz_Riesgos[[#This Row],[Frecuencia Residual]],"") -> 0 | BP7: =IFERROR(Matriz_Riesgos[[#This Row],[Impacto]]-Matriz_Riesgos[[#This Row],[Impacto Residual]],"") -> 0 | BQ7: =IFERROR(Matriz_Riesgos[[#This Row],[Valor del Riesgo Inherente]]-Matriz_Riesgos[[#This Row],[Valor del Riesgo Residual]],"") -> 0
A8: 7 | B8: ROTR-COMPRAS-7 | C8: Compras/Almacen/GAYF | E8: Otros Riesgos | F8: Compras de Medicmentos | H8: Pago de cuentas médicas o registros contables que incluyen medicamentos no dispensados al derechohabiente, entregados parcialmente pero facturados en su totalidad, sustituidos por otros de menor valor, registrados sin soporte de entrega o sin firma de recibido. | I8: Descripción: Posibilidad de que se facture, pague o registre la compra de medicamentos que no fueron efectivamente entregados al paciente o recibidos físicamente por el IHSS, debido a fallas en los controles de dispensación, conciliación y auditoría. Causas: Ausencia de conciliación entre facturación y dispensación, Falta de trazabilidad del medicamento (lote, código, serial), Procesos manuales en farmacia, Colusión entre funcionario y proveedor, Fallas en control de inventarios. Efecto: Pérdidas económicas, fraude, riesgo reputacional, aumento de carga operativa innecesaria (Reprocesos) | J8: 5 | K8: 5 | L8: =IF((Matriz_Riesgos[[#This Row],[Frecuencia]]+Matriz_Riesgos[[#This Row],[Impacto]]-1)=-1,"",Matriz_Riesgos[[#This Row],[Frecuencia]]+Matriz_Riesgos[[#This Row],[Impacto]]-1) -> 9 | M8: =IFERROR(VLOOKUP(Matriz_Riesgos[[#This Row],[Valor del Riesgo Inherente]],t_nivel_riesgo[],2,FALSE), "") -> Riesgo Intolerable | N8: EM | O8: EM | P8: Fraude, operativo, financiero y legal | T8: 1. Sistema de dispensación con registro digital obligatorio 2. Trazabilidad por código de barras o serie. 3. Conciliación automática entre orden médica, inventario y facturación. 4. Segregación de funciones (dispensación vs facturación). | X8: 1. Auditoría de cuentas médicas, mientras se esta prestando el servicio. 2. Indicador de diferencias entre inventario físico y contable. 3. Análisis de consumo atípico por regional, periferica o institucion prestadora de servicios subrogados. | AB8: 1. Recuperación de pagos indebidos. 2. Denuncia penal si hay apropiación indebida. | AG8: =IF(AND(T8="",X8="",AB8=""),"",('Otras Tablas'!$B$3*IF(W8="",0,W8)+'Otras Tablas'!$B$4*IF(AA8="",0,AA8)+'Otras Tablas'!$B$5*IF(AE8="",0,AE8))) | AH8: =IF(Matriz_Riesgos[[#This Row],[Riesgo Inherente]]="","",Matriz_Riesgos[[#This Row],[Riesgo Inherente]]) -> Pago de cuentas médicas o registros contables que incluyen medicamentos no dispensados al derechohabiente, entregados parcialmente pero facturados en su totalidad, sustituidos por otros de menor valor, registrados sin soporte de entrega o sin firma de recibido. | AI8: =IFERROR(IF(OR(Matriz_Riesgos[[#This Row],[Frecuencia]]="",Matriz_Riesgos[[#This Row],[Impacto]]="",Matriz_Riesgos[[#This Row],[Valor del Riesgo Inherente]]="",Matriz_Riesgos[[#This Row],[Valor del Riesgo Residual]]=""),"",IF(Matriz_Riesgos[[#This Row],[Valor del Riesgo Inherente]]=Matriz_Riesgos[[#This Row],[Valor del Riesgo Residual]],Matriz_Riesgos[[#This Row],[Frecuencia]],MIN(Matriz_Riesgos[[#This Row],[Tope F (AUX)]], Matriz_Riesgos[[#This Row],[F_base (AUX)]]+Matriz_Riesgos[[#This Row],[Inc_F (AUX)]]))),"") -> 5 | AJ8: =IFERROR(IF(OR(Matriz_Riesgos[[#This Row],[Frecuencia]]="",Matriz_Riesgos[[#This Row],[Impacto]]="",Matriz_Riesgos[[#This Row],[Valor del Riesgo Inherente]]="",Matriz_Riesgos[[#This Row],[Valor del Riesgo Residual]]=""),"",IF(Matriz_Riesgos[[#This Row],[Valor del Riesgo Inherente]]=Matriz_Riesgos[[#This Row],[Valor del Riesgo Residual]],Matriz_Riesgos[[#This Row],[Impacto]],MIN(Matriz_Riesgos[[#This Row],[Tope I (AUX)]], Matriz_Riesgos[[#This Row],[I_base (AUX)]]+Matriz_Riesgos[[#This Row],[Inc_I (AUX)]]))),"") -> 5 | AK8: =IFERROR(ROUND(MAX(1,Matriz_Riesgos[[#This Row],[Valor del Riesgo Inherente]]*(1 - Matriz_Riesgos[[#This Row],[Efectividad Total Ponderada de los Controles]])),0), "") -> 9 | AL8: =IFERROR(VLOOKUP(Matriz_Riesgos[[#This Row],[Valor del Riesgo Residual]],t_nivel_riesgo[],2,FALSE),"") -> Riesgo Intolerable | AM8: Evitar | AX8: =IFERROR((1-Matriz_Riesgos[[#This Row],[Efectividad Total Ponderada de los Controles]])*Matriz_Riesgos[[#This Row],[Frecuencia]],"") -> 5 | AY8: =IFERROR((1-Matriz_Riesgos[[#This Row],[Efectividad Total Ponderada de los Controles]])*Matriz_Riesgos[[#This Row],[Impacto]],"") -> 5 | AZ8: =IFERROR(Matriz_Riesgos[[#This Row],[Valor del Riesgo Residual]] + 1, "") -> 10 | BA8: =IFERROR(MAX(1, ROUNDDOWN(Matriz_Riesgos[[#This Row],[Frecuencia Residual (AUX)]],0)),"") -> 5 | BB8: =IFERROR(MAX(1, ROUNDDOWN(Matriz_Riesgos[[#This Row],[Impacto Residual (AUX)]],0)),"") -> 5 | BC8: =IF(Matriz_Riesgos[[#This Row],[Frecuencia]]="","",Matriz_Riesgos[[#This Row],[Frecuencia]]) -> 5 | BD8: =IF(Matriz_Riesgos[[#This Row],[Impacto]]="","",Matriz_Riesgos[[#This Row],[Impacto]]) -> 5 | BE8: =IF(OR(Matriz_Riesgos[[#This Row],[Tope F (AUX)]]="",Matriz_Riesgos[[#This Row],[F_base (AUX)]]=""),"",MAX(0,Matriz_Riesgos[[#This Row],[Tope F (AUX)]]-Matriz_Riesgos[[#This Row],[F_base (AUX)]])) -> 0 | BF8: =IF(OR(Matriz_Riesgos[[#This Row],[Tope I (AUX)]]="",Matriz_Riesgos[[#This Row],[I_base (AUX)]]=""),"",MAX(0,Matriz_Riesgos[[#This Row],[Tope I (AUX)]]-Matriz_Riesgos[[#This Row],[I_base (AUX)]])) -> 0 | BG8: =IF(OR(Matriz_Riesgos[[#This Row],[Suma Residual redondeada (AUX)]]="",Matriz_Riesgos[[#This Row],[F_base (AUX)]]="",Matriz_Riesgos[[#This Row],[I_base (AUX)]]=""),"",MAX(0,Matriz_Riesgos[[#This Row],[Suma Residual redondeada (AUX)]]-(Matriz_Riesgos[[#This Row],[F_base (AUX)]]+Matriz_Riesgos[[#This Row],[I_base (AUX)]]))) -> 0 | BH8: =IF(OR(Matriz_Riesgos[[#This Row],[Impacto Residual (AUX)]]="",Matriz_Riesgos[[#This Row],[Frecuencia Residual (AUX)]]=""),"",IF(MOD(Matriz_Riesgos[[#This Row],[Impacto Residual (AUX)]],1) > MOD(Matriz_Riesgos[[#This Row],[Frecuencia Residual (AUX)]],1),1,IF(MOD(Matriz_Riesgos[[#This Row],[Impacto Residual (AUX)]],1) = MOD(Matriz_Riesgos[[#This Row],[Frecuencia Residual (AUX)]],1),1,0))) -> 1 | BI8: =IF(OR(Matriz_Riesgos[[#This Row],[Resto (AUX)]]="",Matriz_Riesgos[[#This Row],[Capacidad I (AUX)]]="",Matriz_Riesgos[[#This Row],[Capacidad F (AUX)]]=""),"",IF(Matriz_Riesgos[[#This Row],[Resto (AUX)]]=0, 0,IF(Matriz_Riesgos[[#This Row],[Resto (AUX)]]=1,MIN(Matriz_Riesgos[[#This Row],[Capacidad I (AUX)]], IF(OR(Matriz_Riesgos[[#This Row],[Prefiere I (AUX)]]=1,Matriz_Riesgos[[#This Row],[Capacidad F (AUX)]]=0),1,0)),MIN(Matriz_Riesgos[[#This Row],[Capacidad I (AUX)]],IF(Matriz_Riesgos[[#This Row],[Prefiere I (AUX)]]=1,1 + IF(Matriz_Riesgos[[#This Row],[Capacidad F (AUX)]]>0,0,1),IF(Matriz_Riesgos[[#This Row],[Capacidad F (AUX)]]>0,1,2)))))) -> 0 | BJ8: =IF(OR(Matriz_Riesgos[[#This Row],[Resto (AUX)]]="",Matriz_Riesgos[[#This Row],[Capacidad F (AUX)]]="",Matriz_Riesgos[[#This Row],[Inc_I (AUX)]]=""),"",MIN(Matriz_Riesgos[[#This Row],[Capacidad F (AUX)]], MAX(0,Matriz_Riesgos[[#This Row],[Resto (AUX)]]-Matriz_Riesgos[[#This Row],[Inc_I (AUX)]]))) -> 0 | BK8: =IFERROR(MAX(ROUND(Matriz_Riesgos[[#This Row],[Frecuencia Residual (AUX)]]+Matriz_Riesgos[[#This Row],[Impacto Residual (AUX)]]-1+Matriz_Riesgos[[#This Row],[Efectividad Total Ponderada de los Controles]],0),1),"") -> 9 | BL8: =IFERROR(Matriz_Riesgos[[#This Row],[Valor del Riesgo Residual]]-Matriz_Riesgos[[#This Row],[Valor del Riesgo Residual (AUX)]],"") -> 0 | BM8: =IFERROR(Matriz_Riesgos[[#This Row],[Frecuencia Residual]]+Matriz_Riesgos[[#This Row],[Impacto Residual]]-1,"") -> 9 | BN8: =IFERROR(Matriz_Riesgos[[#This Row],[Valor del Riesgo Residual]]-Matriz_Riesgos[[#This Row],[VRR 2]],"") -> 0 | BO8: =IFERROR(Matriz_Riesgos[[#This Row],[Frecuencia]]-Matriz_Riesgos[[#This Row],[Frecuencia Residual]],"") -> 0 | BP8: =IFERROR(Matriz_Riesgos[[#This Row],[Impacto]]-Matriz_Riesgos[[#This Row],[Impacto Residual]],"") -> 0 | BQ8: =IFERROR(Matriz_Riesgos[[#This Row],[Valor del Riesgo Inherente]]-Matriz_Riesgos[[#This Row],[Valor del Riesgo Residual]],"") -> 0
A9: 8 | B9: ROTR-RRHH-8 | C9: RRHH | E9: Otros Riesgos | F9: Contratacion | H9: Adjudicación o celebración de contratos en los que se diseñan pliegos o términos de referencia a la medida de un proponente, se omiten requisitos legales o técnicos, se alteran evaluaciones, se permite participación de oferentes no elegibles, se manipulan estudios previos o análisis de mercado. | I9: Descripción: Posibilidad de que los procesos de contratación sean direccionados, alterados o manipulados indebidamente para favorecer a un proveedor específico o afectar la libre competencia, mediante la modificación injustificada de requisitos, filtración de información privilegiada, evaluación sesgada o colusión interna. Causas: Conflictos de interés no declarados, Falta de segregación de funciones, Débil supervisión del proceso contractual, Intervención indebida de funcionarios o presion externa (politica) Falta de trazabilidad documental. Controles internos formales pero no efectivos. Efecto: Pérdidas económicas, procesos disciplinarios y penales por corrupción, interrupción de servicios críticos (salud, medicamentos, tecnología) y riesgo reputacional | J9: 3 | K9: 5 | L9: =IF((Matriz_Riesgos[[#This Row],[Frecuencia]]+Matriz_Riesgos[[#This Row],[Impacto]]-1)=-1,"",Matriz_Riesgos[[#This Row],[Frecuencia]]+Matriz_Riesgos[[#This Row],[Impacto]]-1) -> 7 | M9: =IFERROR(VLOOKUP(Matriz_Riesgos[[#This Row],[Valor del Riesgo Inherente]],t_nivel_riesgo[],2,FALSE), "") -> Riesgo Alto | N9: RRHH | O9: Todos | P9: Fraude, corrupcion, financiero, operativo, reputacional, riesgo de cumplimiento regulatorio | T9: 1. Manual de contratación actualizado. 2. Declaración obligatoria de conflicto de interés. 3. Comité evaluador con miembros independientes. 4. Transparencia del proceso. 5. Matriz de evaluación objetiva y parametrizada (criterios previamente definidos, medibles, cuantificables y no discrecionales) | X9: 1. Indicador de concentración de contratación por proveedor. 2. Auditoría contractual periódica. | AB9: 1. Nulidad contractual cuando proceda. 2. Acción de repetición (si hay responsabilidad individual). 3. Denuncia ante autoridad competente. | AG9: =IF(AND(T9="",X9="",AB9=""),"",('Otras Tablas'!$B$3*IF(W9="",0,W9)+'Otras Tablas'!$B$4*IF(AA9="",0,AA9)+'Otras Tablas'!$B$5*IF(AE9="",0,AE9))) | AH9: =IF(Matriz_Riesgos[[#This Row],[Riesgo Inherente]]="","",Matriz_Riesgos[[#This Row],[Riesgo Inherente]]) -> Adjudicación o celebración de contratos en los que se diseñan pliegos o términos de referencia a la medida de un proponente, se omiten requisitos legales o técnicos, se alteran evaluaciones, se permite participación de oferentes no elegibles, se manipulan estudios previos o análisis de mercado. | AI9: =IFERROR(IF(OR(Matriz_Riesgos[[#This Row],[Frecuencia]]="",Matriz_Riesgos[[#This Row],[Impacto]]="",Matriz_Riesgos[[#This Row],[Valor del Riesgo Inherente]]="",Matriz_Riesgos[[#This Row],[Valor del Riesgo Residual]]=""),"",IF(Matriz_Riesgos[[#This Row],[Valor del Riesgo Inherente]]=Matriz_Riesgos[[#This Row],[Valor del Riesgo Residual]],Matriz_Riesgos[[#This Row],[Frecuencia]],MIN(Matriz_Riesgos[[#This Row],[Tope F (AUX)]], Matriz_Riesgos[[#This Row],[F_base (AUX)]]+Matriz_Riesgos[[#This Row],[Inc_F (AUX)]]))),"") -> 3 | AJ9: =IFERROR(IF(OR(Matriz_Riesgos[[#This Row],[Frecuencia]]="",Matriz_Riesgos[[#This Row],[Impacto]]="",Matriz_Riesgos[[#This Row],[Valor del Riesgo Inherente]]="",Matriz_Riesgos[[#This Row],[Valor del Riesgo Residual]]=""),"",IF(Matriz_Riesgos[[#This Row],[Valor del Riesgo Inherente]]=Matriz_Riesgos[[#This Row],[Valor del Riesgo Residual]],Matriz_Riesgos[[#This Row],[Impacto]],MIN(Matriz_Riesgos[[#This Row],[Tope I (AUX)]], Matriz_Riesgos[[#This Row],[I_base (AUX)]]+Matriz_Riesgos[[#This Row],[Inc_I (AUX)]]))),"") -> 5 | AK9: =IFERROR(ROUND(MAX(1,Matriz_Riesgos[[#This Row],[Valor del Riesgo Inherente]]*(1 - Matriz_Riesgos[[#This Row],[Efectividad Total Ponderada de los Controles]])),0), "") -> 7 | AL9: =IFERROR(VLOOKUP(Matriz_Riesgos[[#This Row],[Valor del Riesgo Residual]],t_nivel_riesgo[],2,FALSE),"") -> Riesgo Alto | AM9: Evitar | AX9: =IFERROR((1-Matriz_Riesgos[[#This Row],[Efectividad Total Ponderada de los Controles]])*Matriz_Riesgos[[#This Row],[Frecuencia]],"") -> 3 | AY9: =IFERROR((1-Matriz_Riesgos[[#This Row],[Efectividad Total Ponderada de los Controles]])*Matriz_Riesgos[[#This Row],[Impacto]],"") -> 5 | AZ9: =IFERROR(Matriz_Riesgos[[#This Row],[Valor del Riesgo Residual]] + 1, "") -> 8 | BA9: =IFERROR(MAX(1, ROUNDDOWN(Matriz_Riesgos[[#This Row],[Frecuencia Residual (AUX)]],0)),"") -> 3 | BB9: =IFERROR(MAX(1, ROUNDDOWN(Matriz_Riesgos[[#This Row],[Impacto Residual (AUX)]],0)),"") -> 5 | BC9: =IF(Matriz_Riesgos[[#This Row],[Frecuencia]]="","",Matriz_Riesgos[[#This Row],[Frecuencia]]) -> 3 | BD9: =IF(Matriz_Riesgos[[#This Row],[Impacto]]="","",Matriz_Riesgos[[#This Row],[Impacto]]) -> 5 | BE9: =IF(OR(Matriz_Riesgos[[#This Row],[Tope F (AUX)]]="",Matriz_Riesgos[[#This Row],[F_base (AUX)]]=""),"",MAX(0,Matriz_Riesgos[[#This Row],[Tope F (AUX)]]-Matriz_Riesgos[[#This Row],[F_base (AUX)]])) -> 0 | BF9: =IF(OR(Matriz_Riesgos[[#This Row],[Tope I (AUX)]]="",Matriz_Riesgos[[#This Row],[I_base (AUX)]]=""),"",MAX(0,Matriz_Riesgos[[#This Row],[Tope I (AUX)]]-Matriz_Riesgos[[#This Row],[I_base (AUX)]])) -> 0 | BG9: =IF(OR(Matriz_Riesgos[[#This Row],[Suma Residual redondeada (AUX)]]="",Matriz_Riesgos[[#This Row],[F_base (AUX)]]="",Matriz_Riesgos[[#This Row],[I_base (AUX)]]=""),"",MAX(0,Matriz_Riesgos[[#This Row],[Suma Residual redondeada (AUX)]]-(Matriz_Riesgos[[#This Row],[F_base (AUX)]]+Matriz_Riesgos[[#This Row],[I_base (AUX)]]))) -> 0 | BH9: =IF(OR(Matriz_Riesgos[[#This Row],[Impacto Residual (AUX)]]="",Matriz_Riesgos[[#This Row],[Frecuencia Residual (AUX)]]=""),"",IF(MOD(Matriz_Riesgos[[#This Row],[Impacto Residual (AUX)]],1) > MOD(Matriz_Riesgos[[#This Row],[Frecuencia Residual (AUX)]],1),1,IF(MOD(Matriz_Riesgos[[#This Row],[Impacto Residual (AUX)]],1) = MOD(Matriz_Riesgos[[#This Row],[Frecuencia Residual (AUX)]],1),1,0))) -> 1 | BI9: =IF(OR(Matriz_Riesgos[[#This Row],[Resto (AUX)]]="",Matriz_Riesgos[[#This Row],[Capacidad I (AUX)]]="",Matriz_Riesgos[[#This Row],[Capacidad F (AUX)]]=""),"",IF(Matriz_Riesgos[[#This Row],[Resto (AUX)]]=0, 0,IF(Matriz_Riesgos[[#This Row],[Resto (AUX)]]=1,MIN(Matriz_Riesgos[[#This Row],[Capacidad I (AUX)]], IF(OR(Matriz_Riesgos[[#This Row],[Prefiere I (AUX)]]=1,Matriz_Riesgos[[#This Row],[Capacidad F (AUX)]]=0),1,0)),MIN(Matriz_Riesgos[[#This Row],[Capacidad I (AUX)]],IF(Matriz_Riesgos[[#This Row],[Prefiere I (AUX)]]=1,1 + IF(Matriz_Riesgos[[#This Row],[Capacidad F (AUX)]]>0,0,1),IF(Matriz_Riesgos[[#This Row],[Capacidad F (AUX)]]>0,1,2)))))) -> 0 | BJ9: =IF(OR(Matriz_Riesgos[[#This Row],[Resto (AUX)]]="",Matriz_Riesgos[[#This Row],[Capacidad F (AUX)]]="",Matriz_Riesgos[[#This Row],[Inc_I (AUX)]]=""),"",MIN(Matriz_Riesgos[[#This Row],[Capacidad F (AUX)]], MAX(0,Matriz_Riesgos[[#This Row],[Resto (AUX)]]-Matriz_Riesgos[[#This Row],[Inc_I (AUX)]]))) -> 0 | BK9: =IFERROR(MAX(ROUND(Matriz_Riesgos[[#This Row],[Frecuencia Residual (AUX)]]+Matriz_Riesgos[[#This Row],[Impacto Residual (AUX)]]-1+Matriz_Riesgos[[#This Row],[Efectividad Total Ponderada de los Controles]],0),1),"") -> 7 | BL9: =IFERROR(Matriz_Riesgos[[#This Row],[Valor del Riesgo Residual]]-Matriz_Riesgos[[#This Row],[Valor del Riesgo Residual (AUX)]],"") -> 0 | BM9: =IFERROR(Matriz_Riesgos[[#This Row],[Frecuencia Residual]]+Matriz_Riesgos[[#This Row],[Impacto Residual]]-1,"") -> 7 | BN9: =IFERROR(Matriz_Riesgos[[#This Row],[Valor del Riesgo Residual]]-Matriz_Riesgos[[#This Row],[VRR 2]],"") -> 0 | BO9: =IFERROR(Matriz_Riesgos[[#This Row],[Frecuencia]]-Matriz_Riesgos[[#This Row],[Frecuencia Residual]],"") -> 0 | BP9: =IFERROR(Matriz_Riesgos[[#This Row],[Impacto]]-Matriz_Riesgos[[#This Row],[Impacto Residual]],"") -> 0 | BQ9: =IFERROR(Matriz_Riesgos[[#This Row],[Valor del Riesgo Inherente]]-Matriz_Riesgos[[#This Row],[Valor del Riesgo Residual]],"") -> 0
A10: 9 | B10: ROTR-TESO-9 | C10: Tesoreria | E10: Otros Riesgos | F10: Pagos | H10: Desembolso de recursos cuando se modifica la cuenta bancaria sin validación robusta, se registran cuentas falsas en el sistema, existe suplantación de beneficiario o proveedor o se realizan pagos a terceros no autorizados. | I10: Descripción: Posibilidad de que se efectúen pagos de prestaciones económicas, servicios de salud o contratos a cuentas bancarias no autorizadas, suplantadas o modificadas fraudulentamente, debido a fallas en los controles de validación, actualización y confirmación de datos financieros. Causas: Debilidad en el proceso de actualización de datos financieros. Ataques de ingeniería social. Accesos indebidos al sistema. No segregación entre quien registra y quien autoriza Efecto: Pérdidas económicas, reclamaciones por no pago al beneficiario legítimo, reprocesos y suspension temporal de la planilla. | J10: 3 | K10: 5 | L10: =IF((Matriz_Riesgos[[#This Row],[Frecuencia]]+Matriz_Riesgos[[#This Row],[Impacto]]-1)=-1,"",Matriz_Riesgos[[#This Row],[Frecuencia]]+Matriz_Riesgos[[#This Row],[Impacto]]-1) -> 7 | M10: =IFERROR(VLOOKUP(Matriz_Riesgos[[#This Row],[Valor del Riesgo Inherente]],t_nivel_riesgo[],2,FALSE), "") -> Riesgo Alto | N10: Tesoreria, RRHH, Compras, Contabilidad, Pensiones | O10: Todos | P10: Fraude, financiero, operativo, legal | T10: 1. Autenticación para cambio de cuenta. 2. Confirmación directa con el beneficiario (doble canal). 3. Bloqueo automático ante cambio de cuenta cercano a fecha de pago. 4. Segregación de funciones: registro vs aprobación. 5. Registro de bitácora y trazabilidad completa. | X10: 1. Indicador de cambios de cuenta previos a fecha de pago. 2. Alertas por múltiples cambios de cuenta en corto periodo. | AB10: 1. Gestión inmediata de reversión bancaria. 2. Suspensión temporal de pagos ante alerta. 3. Investigación disciplinaria si hay intervención interna. | AG10: =IF(AND(T10="",X10="",AB10=""),"",('Otras Tablas'!$B$3*IF(W10="",0,W10)+'Otras Tablas'!$B$4*IF(AA10="",0,AA10)+'Otras Tablas'!$B$5*IF(AE10="",0,AE10))) | AH10: =IF(Matriz_Riesgos[[#This Row],[Riesgo Inherente]]="","",Matriz_Riesgos[[#This Row],[Riesgo Inherente]]) -> Desembolso de recursos cuando se modifica la cuenta bancaria sin validación robusta, se registran cuentas falsas en el sistema, existe suplantación de beneficiario o proveedor o se realizan pagos a terceros no autorizados. | AI10: =IFERROR(IF(OR(Matriz_Riesgos[[#This Row],[Frecuencia]]="",Matriz_Riesgos[[#This Row],[Impacto]]="",Matriz_Riesgos[[#This Row],[Valor del Riesgo Inherente]]="",Matriz_Riesgos[[#This Row],[Valor del Riesgo Residual]]=""),"",IF(Matriz_Riesgos[[#This Row],[Valor del Riesgo Inherente]]=Matriz_Riesgos[[#This Row],[Valor del Riesgo Residual]],Matriz_Riesgos[[#This Row],[Frecuencia]],MIN(Matriz_Riesgos[[#This Row],[Tope F (AUX)]], Matriz_Riesgos[[#This Row],[F_base (AUX)]]+Matriz_Riesgos[[#This Row],[Inc_F (AUX)]]))),"") -> 3 | AJ10: =IFERROR(IF(OR(Matriz_Riesgos[[#This Row],[Frecuencia]]="",Matriz_Riesgos[[#This Row],[Impacto]]="",Matriz_Riesgos[[#This Row],[Valor del Riesgo Inherente]]="",Matriz_Riesgos[[#This Row],[Valor del Riesgo Residual]]=""),"",IF(Matriz_Riesgos[[#This Row],[Valor del Riesgo Inherente]]=Matriz_Riesgos[[#This Row],[Valor del Riesgo Residual]],Matriz_Riesgos[[#This Row],[Impacto]],MIN(Matriz_Riesgos[[#This Row],[Tope I (AUX)]], Matriz_Riesgos[[#This Row],[I_base (AUX)]]+Matriz_Riesgos[[#This Row],[Inc_I (AUX)]]))),"") -> 5 | AK10: =IFERROR(ROUND(MAX(1,Matriz_Riesgos[[#This Row],[Valor del Riesgo Inherente]]*(1 - Matriz_Riesgos[[#This Row],[Efectividad Total Ponderada de los Controles]])),0), "") -> 7 | AL10: =IFERROR(VLOOKUP(Matriz_Riesgos[[#This Row],[Valor del Riesgo Residual]],t_nivel_riesgo[],2,FALSE),"") -> Riesgo Alto | AM10: Evitar | AX10: =IFERROR((1-Matriz_Riesgos[[#This Row],[Efectividad Total Ponderada de los Controles]])*Matriz_Riesgos[[#This Row],[Frecuencia]],"") -> 3 | AY10: =IFERROR((1-Matriz_Riesgos[[#This Row],[Efectividad Total Ponderada de los Controles]])*Matriz_Riesgos[[#This Row],[Impacto]],"") -> 5 | AZ10: =IFERROR(Matriz_Riesgos[[#This Row],[Valor del Riesgo Residual]] + 1, "") -> 8 | BA10: =IFERROR(MAX(1, ROUNDDOWN(Matriz_Riesgos[[#This Row],[Frecuencia Residual (AUX)]],0)),"") -> 3 | BB10: =IFERROR(MAX(1, ROUNDDOWN(Matriz_Riesgos[[#This Row],[Impacto Residual (AUX)]],0)),"") -> 5 | BC10: =IF(Matriz_Riesgos[[#This Row],[Frecuencia]]="","",Matriz_Riesgos[[#This Row],[Frecuencia]]) -> 3 | BD10: =IF(Matriz_Riesgos[[#This Row],[Impacto]]="","",Matriz_Riesgos[[#This Row],[Impacto]]) -> 5 | BE10: =IF(OR(Matriz_Riesgos[[#This Row],[Tope F (AUX)]]="",Matriz_Riesgos[[#This Row],[F_base (AUX)]]=""),"",MAX(0,Matriz_Riesgos[[#This Row],[Tope F (AUX)]]-Matriz_Riesgos[[#This Row],[F_base (AUX)]])) -> 0 | BF10: =IF(OR(Matriz_Riesgos[[#This Row],[Tope I (AUX)]]="",Matriz_Riesgos[[#This Row],[I_base (AUX)]]=""),"",MAX(0,Matriz_Riesgos[[#This Row],[Tope I (AUX)]]-Matriz_Riesgos[[#This Row],[I_base (AUX)]])) -> 0 | BG10: =IF(OR(Matriz_Riesgos[[#This Row],[Suma Residual redondeada (AUX)]]="",Matriz_Riesgos[[#This Row],[F_base (AUX)]]="",Matriz_Riesgos[[#This Row],[I_base (AUX)]]=""),"",MAX(0,Matriz_Riesgos[[#This Row],[Suma Residual redondeada (AUX)]]-(Matriz_Riesgos[[#This Row],[F_base (AUX)]]+Matriz_Riesgos[[#This Row],[I_base (AUX)]]))) -> 0 | BH10: =IF(OR(Matriz_Riesgos[[#This Row],[Impacto Residual (AUX)]]="",Matriz_Riesgos[[#This Row],[Frecuencia Residual (AUX)]]=""),"",IF(MOD(Matriz_Riesgos[[#This Row],[Impacto Residual (AUX)]],1) > MOD(Matriz_Riesgos[[#This Row],[Frecuencia Residual (AUX)]],1),1,IF(MOD(Matriz_Riesgos[[#This Row],[Impacto Residual (AUX)]],1) = MOD(Matriz_Riesgos[[#This Row],[Frecuencia Residual (AUX)]],1),1,0))) -> 1 | BI10: =IF(OR(Matriz_Riesgos[[#This Row],[Resto (AUX)]]="",Matriz_Riesgos[[#This Row],[Capacidad I (AUX)]]="",Matriz_Riesgos[[#This Row],[Capacidad F (AUX)]]=""),"",IF(Matriz_Riesgos[[#This Row],[Resto (AUX)]]=0, 0,IF(Matriz_Riesgos[[#This Row],[Resto (AUX)]]=1,MIN(Matriz_Riesgos[[#This Row],[Capacidad I (AUX)]], IF(OR(Matriz_Riesgos[[#This Row],[Prefiere I (AUX)]]=1,Matriz_Riesgos[[#This Row],[Capacidad F (AUX)]]=0),1,0)),MIN(Matriz_Riesgos[[#This Row],[Capacidad I (AUX)]],IF(Matriz_Riesgos[[#This Row],[Prefiere I (AUX)]]=1,1 + IF(Matriz_Riesgos[[#This Row],[Capacidad F (AUX)]]>0,0,1),IF(Matriz_Riesgos[[#This Row],[Capacidad F (AUX)]]>0,1,2)))))) -> 0 | BJ10: =IF(OR(Matriz_Riesgos[[#This Row],[Resto (AUX)]]="",Matriz_Riesgos[[#This Row],[Capacidad F (AUX)]]="",Matriz_Riesgos[[#This Row],[Inc_I (AUX)]]=""),"",MIN(Matriz_Riesgos[[#This Row],[Capacidad F (AUX)]], MAX(0,Matriz_Riesgos[[#This Row],[Resto (AUX)]]-Matriz_Riesgos[[#This Row],[Inc_I (AUX)]]))) -> 0 | BK10: =IFERROR(MAX(ROUND(Matriz_Riesgos[[#This Row],[Frecuencia Residual (AUX)]]+Matriz_Riesgos[[#This Row],[Impacto Residual (AUX)]]-1+Matriz_Riesgos[[#This Row],[Efectividad Total Ponderada de los Controles]],0),1),"") -> 7 | BL10: =IFERROR(Matriz_Riesgos[[#This Row],[Valor del Riesgo Residual]]-Matriz_Riesgos[[#This Row],[Valor del Riesgo Residual (AUX)]],"") -> 0 | BM10: =IFERROR(Matriz_Riesgos[[#This Row],[Frecuencia Residual]]+Matriz_Riesgos[[#This Row],[Impacto Residual]]-1,"") -> 7 | BN10: =IFERROR(Matriz_Riesgos[[#This Row],[Valor del Riesgo Residual]]-Matriz_Riesgos[[#This Row],[VRR 2]],"") -> 0 | BO10: =IFERROR(Matriz_Riesgos[[#This Row],[Frecuencia]]-Matriz_Riesgos[[#This Row],[Frecuencia Residual]],"") -> 0 | BP10: =IFERROR(Matriz_Riesgos[[#This Row],[Impacto]]-Matriz_Riesgos[[#This Row],[Impacto Residual]],"") -> 0 | BQ10: =IFERROR(Matriz_Riesgos[[#This Row],[Valor del Riesgo Inherente]]-Matriz_Riesgos[[#This Row],[Valor del Riesgo Residual]],"") -> 0
A11: 10 | B11: ROTR-PENS-10 | C11: Pensiones | E11: Otros Riesgos | F11: Pagos de prestaciones Economicas | H11: Reconocimiento o pago de pension por viudez o ascendencia a quien no acredita vínculo válido, pensión de orfandad sin cumplir requisitos de edad o dependencia o representantes que cobran sin legitimación. | I11: Descripción: Posibilidad de que se reconozcan o paguen prestaciones económicas a personas que no cumplen los requisitos legales para ostentar la calidad de beneficiarios, mediante suplantación, falsedad documental, ocultamiento de información o interpretación indebida de la normativa Causas: Debilidad en verificación de estado civil, Aceptación de documentos sin autenticación robusta, Falta de cruces con bases oficiales (registro civil, defunciones). Colusión interna Efecto: Pérdidas económicas, afectación de reservas técnicas y distorcion de sus proyecciones financieras, procesos judiciales de terceros afectados, daño reputacional. | J11: 3 | K11: 5 | L11: =IF((Matriz_Riesgos[[#This Row],[Frecuencia]]+Matriz_Riesgos[[#This Row],[Impacto]]-1)=-1,"",Matriz_Riesgos[[#This Row],[Frecuencia]]+Matriz_Riesgos[[#This Row],[Impacto]]-1) -> 7 | M11: =IFERROR(VLOOKUP(Matriz_Riesgos[[#This Row],[Valor del Riesgo Inherente]],t_nivel_riesgo[],2,FALSE), "") -> Riesgo Alto | N11: Gerencia de IVM | O11: IVM | P11: Fraude, financiero, reputacional, operativo, actuarial | T11: 1. Validación obligatoria contra registro civil y bases oficiales. 2. Verificación documental con herramientas antifraude. 3. Revisión cruzada de beneficiarios previos. | X11: 1. Cruce con bases de fallecidos y cambios de estado civil. 2. Alertas por múltiples beneficiarios en mismo núcleo | AB11: 1. Acción de repetición. 2. Denuncia penal por fraude documental. | AG11: =IF(AND(T11="",X11="",AB11=""),"",('Otras Tablas'!$B$3*IF(W11="",0,W11)+'Otras Tablas'!$B$4*IF(AA11="",0,AA11)+'Otras Tablas'!$B$5*IF(AE11="",0,AE11))) | AH11: =IF(Matriz_Riesgos[[#This Row],[Riesgo Inherente]]="","",Matriz_Riesgos[[#This Row],[Riesgo Inherente]]) -> Reconocimiento o pago de pension por viudez o ascendencia a quien no acredita vínculo válido, pensión de orfandad sin cumplir requisitos de edad o dependencia o representantes que cobran sin legitimación. | AI11: =IFERROR(IF(OR(Matriz_Riesgos[[#This Row],[Frecuencia]]="",Matriz_Riesgos[[#This Row],[Impacto]]="",Matriz_Riesgos[[#This Row],[Valor del Riesgo Inherente]]="",Matriz_Riesgos[[#This Row],[Valor del Riesgo Residual]]=""),"",IF(Matriz_Riesgos[[#This Row],[Valor del Riesgo Inherente]]=Matriz_Riesgos[[#This Row],[Valor del Riesgo Residual]],Matriz_Riesgos[[#This Row],[Frecuencia]],MIN(Matriz_Riesgos[[#This Row],[Tope F (AUX)]], Matriz_Riesgos[[#This Row],[F_base (AUX)]]+Matriz_Riesgos[[#This Row],[Inc_F (AUX)]]))),"") -> 3 | AJ11: =IFERROR(IF(OR(Matriz_Riesgos[[#This Row],[Frecuencia]]="",Matriz_Riesgos[[#This Row],[Impacto]]="",Matriz_Riesgos[[#This Row],[Valor del Riesgo Inherente]]="",Matriz_Riesgos[[#This Row],[Valor del Riesgo Residual]]=""),"",IF(Matriz_Riesgos[[#This Row],[Valor del Riesgo Inherente]]=Matriz_Riesgos[[#This Row],[Valor del Riesgo Residual]],Matriz_Riesgos[[#This Row],[Impacto]],MIN(Matriz_Riesgos[[#This Row],[Tope I (AUX)]], Matriz_Riesgos[[#This Row],[I_base (AUX)]]+Matriz_Riesgos[[#This Row],[Inc_I (AUX)]]))),"") -> 5 | AK11: =IFERROR(ROUND(MAX(1,Matriz_Riesgos[[#This Row],[Valor del Riesgo Inherente]]*(1 - Matriz_Riesgos[[#This Row],[Efectividad Total Ponderada de los Controles]])),0), "") -> 7 | AL11: =IFERROR(VLOOKUP(Matriz_Riesgos[[#This Row],[Valor del Riesgo Residual]],t_nivel_riesgo[],2,FALSE),"") -> Riesgo Alto | AM11: Evitar | AX11: =IFERROR((1-Matriz_Riesgos[[#This Row],[Efectividad Total Ponderada de los Controles]])*Matriz_Riesgos[[#This Row],[Frecuencia]],"") -> 3 | AY11: =IFERROR((1-Matriz_Riesgos[[#This Row],[Efectividad Total Ponderada de los Controles]])*Matriz_Riesgos[[#This Row],[Impacto]],"") -> 5 | AZ11: =IFERROR(Matriz_Riesgos[[#This Row],[Valor del Riesgo Residual]] + 1, "") -> 8 | BA11: =IFERROR(MAX(1, ROUNDDOWN(Matriz_Riesgos[[#This Row],[Frecuencia Residual (AUX)]],0)),"") -> 3 | BB11: =IFERROR(MAX(1, ROUNDDOWN(Matriz_Riesgos[[#This Row],[Impacto Residual (AUX)]],0)),"") -> 5 | BC11: =IF(Matriz_Riesgos[[#This Row],[Frecuencia]]="","",Matriz_Riesgos[[#This Row],[Frecuencia]]) -> 3 | BD11: =IF(Matriz_Riesgos[[#This Row],[Impacto]]="","",Matriz_Riesgos[[#This Row],[Impacto]]) -> 5 | BE11: =IF(OR(Matriz_Riesgos[[#This Row],[Tope F (AUX)]]="",Matriz_Riesgos[[#This Row],[F_base (AUX)]]=""),"",MAX(0,Matriz_Riesgos[[#This Row],[Tope F (AUX)]]-Matriz_Riesgos[[#This Row],[F_base (AUX)]])) -> 0 | BF11: =IF(OR(Matriz_Riesgos[[#This Row],[Tope I (AUX)]]="",Matriz_Riesgos[[#This Row],[I_base (AUX)]]=""),"",MAX(0,Matriz_Riesgos[[#This Row],[Tope I (AUX)]]-Matriz_Riesgos[[#This Row],[I_base (AUX)]])) -> 0 | BG11: =IF(OR(Matriz_Riesgos[[#This Row],[Suma Residual redondeada (AUX)]]="",Matriz_Riesgos[[#This Row],[F_base (AUX)]]="",Matriz_Riesgos[[#This Row],[I_base (AUX)]]=""),"",MAX(0,Matriz_Riesgos[[#This Row],[Suma Residual redondeada (AUX)]]-(Matriz_Riesgos[[#This Row],[F_base (AUX)]]+Matriz_Riesgos[[#This Row],[I_base (AUX)]]))) -> 0 | BH11: =IF(OR(Matriz_Riesgos[[#This Row],[Impacto Residual (AUX)]]="",Matriz_Riesgos[[#This Row],[Frecuencia Residual (AUX)]]=""),"",IF(MOD(Matriz_Riesgos[[#This Row],[Impacto Residual (AUX)]],1) > MOD(Matriz_Riesgos[[#This Row],[Frecuencia Residual (AUX)]],1),1,IF(MOD(Matriz_Riesgos[[#This Row],[Impacto Residual (AUX)]],1) = MOD(Matriz_Riesgos[[#This Row],[Frecuencia Residual (AUX)]],1),1,0))) -> 1 | BI11: =IF(OR(Matriz_Riesgos[[#This Row],[Resto (AUX)]]="",Matriz_Riesgos[[#This Row],[Capacidad I (AUX)]]="",Matriz_Riesgos[[#This Row],[Capacidad F (AUX)]]=""),"",IF(Matriz_Riesgos[[#This Row],[Resto (AUX)]]=0, 0,IF(Matriz_Riesgos[[#This Row],[Resto (AUX)]]=1,MIN(Matriz_Riesgos[[#This Row],[Capacidad I (AUX)]], IF(OR(Matriz_Riesgos[[#This Row],[Prefiere I (AUX)]]=1,Matriz_Riesgos[[#This Row],[Capacidad F (AUX)]]=0),1,0)),MIN(Matriz_Riesgos[[#This Row],[Capacidad I (AUX)]],IF(Matriz_Riesgos[[#This Row],[Prefiere I (AUX)]]=1,1 + IF(Matriz_Riesgos[[#This Row],[Capacidad F (AUX)]]>0,0,1),IF(Matriz_Riesgos[[#This Row],[Capacidad F (AUX)]]>0,1,2)))))) -> 0 | BJ11: =IF(OR(Matriz_Riesgos[[#This Row],[Resto (AUX)]]="",Matriz_Riesgos[[#This Row],[Capacidad F (AUX)]]="",Matriz_Riesgos[[#This Row],[Inc_I (AUX)]]=""),"",MIN(Matriz_Riesgos[[#This Row],[Capacidad F (AUX)]], MAX(0,Matriz_Riesgos[[#This Row],[Resto (AUX)]]-Matriz_Riesgos[[#This Row],[Inc_I (AUX)]]))) -> 0 | BK11: =IFERROR(MAX(ROUND(Matriz_Riesgos[[#This Row],[Frecuencia Residual (AUX)]]+Matriz_Riesgos[[#This Row],[Impacto Residual (AUX)]]-1+Matriz_Riesgos[[#This Row],[Efectividad Total Ponderada de los Controles]],0),1),"") -> 7 | BL11: =IFERROR(Matriz_Riesgos[[#This Row],[Valor del Riesgo Residual]]-Matriz_Riesgos[[#This Row],[Valor del Riesgo Residual (AUX)]],"") -> 0 | BM11: =IFERROR(Matriz_Riesgos[[#This Row],[Frecuencia Residual]]+Matriz_Riesgos[[#This Row],[Impacto Residual]]-1,"") -> 7 | BN11: =IFERROR(Matriz_Riesgos[[#This Row],[Valor del Riesgo Residual]]-Matriz_Riesgos[[#This Row],[VRR 2]],"") -> 0 | BO11: =IFERROR(Matriz_Riesgos[[#This Row],[Frecuencia]]-Matriz_Riesgos[[#This Row],[Frecuencia Residual]],"") -> 0 | BP11: =IFERROR(Matriz_Riesgos[[#This Row],[Impacto]]-Matriz_Riesgos[[#This Row],[Impacto Residual]],"") -> 0 | BQ11: =IFERROR(Matriz_Riesgos[[#This Row],[Valor del Riesgo Inherente]]-Matriz_Riesgos[[#This Row],[Valor del Riesgo Residual]],"") -> 0
A12: 11 | B12: ROTR-TESO-11 | C12: Tesoreria | E12: Otros Riesgos | F12: Transferencias Bancarias | H12: Transferencias a zonas de alto riesgo | I12: Descripción: Autorizacion de Transferencias a zonas de alto riesgo Causas: Falta de control para identificar zonas de alto riesgo o paraisos fiscales (compras a empresas extranjeras con cuentas en esos paises) Efecto: Pérdidas económicas / Sanciones legales x incumplimiento normativo / LAFT | J12: 2 | K12: 5 | L12: =IF((Matriz_Riesgos[[#This Row],[Frecuencia]]+Matriz_Riesgos[[#This Row],[Impacto]]-1)=-1,"",Matriz_Riesgos[[#This Row],[Frecuencia]]+Matriz_Riesgos[[#This Row],[Impacto]]-1) -> 6 | M12: =IFERROR(VLOOKUP(Matriz_Riesgos[[#This Row],[Valor del Riesgo Inherente]],t_nivel_riesgo[],2,FALSE), "") -> Riesgo Alto | N12: Tesoreria | P12: Fraude/LAFT | T12: Segmentacion geografica | AG12: =IF(AND(T12="",X12="",AB12=""),"",('Otras Tablas'!$B$3*IF(W12="",0,W12)+'Otras Tablas'!$B$4*IF(AA12="",0,AA12)+'Otras Tablas'!$B$5*IF(AE12="",0,AE12))) | AH12: =IF(Matriz_Riesgos[[#This Row],[Riesgo Inherente]]="","",Matriz_Riesgos[[#This Row],[Riesgo Inherente]]) -> Transferencias a zonas de alto riesgo | AI12: =IFERROR(IF(OR(Matriz_Riesgos[[#This Row],[Frecuencia]]="",Matriz_Riesgos[[#This Row],[Impacto]]="",Matriz_Riesgos[[#This Row],[Valor del Riesgo Inherente]]="",Matriz_Riesgos[[#This Row],[Valor del Riesgo Residual]]=""),"",IF(Matriz_Riesgos[[#This Row],[Valor del Riesgo Inherente]]=Matriz_Riesgos[[#This Row],[Valor del Riesgo Residual]],Matriz_Riesgos[[#This Row],[Frecuencia]],MIN(Matriz_Riesgos[[#This Row],[Tope F (AUX)]], Matriz_Riesgos[[#This Row],[F_base (AUX)]]+Matriz_Riesgos[[#This Row],[Inc_F (AUX)]]))),"") -> 2 | AJ12: =IFERROR(IF(OR(Matriz_Riesgos[[#This Row],[Frecuencia]]="",Matriz_Riesgos[[#This Row],[Impacto]]="",Matriz_Riesgos[[#This Row],[Valor del Riesgo Inherente]]="",Matriz_Riesgos[[#This Row],[Valor del Riesgo Residual]]=""),"",IF(Matriz_Riesgos[[#This Row],[Valor del Riesgo Inherente]]=Matriz_Riesgos[[#This Row],[Valor del Riesgo Residual]],Matriz_Riesgos[[#This Row],[Impacto]],MIN(Matriz_Riesgos[[#This Row],[Tope I (AUX)]], Matriz_Riesgos[[#This Row],[I_base (AUX)]]+Matriz_Riesgos[[#This Row],[Inc_I (AUX)]]))),"") -> 5 | AK12: =IFERROR(ROUND(MAX(1,Matriz_Riesgos[[#This Row],[Valor del Riesgo Inherente]]*(1 - Matriz_Riesgos[[#This Row],[Efectividad Total Ponderada de los Controles]])),0), "") -> 6 | AL12: =IFERROR(VLOOKUP(Matriz_Riesgos[[#This Row],[Valor del Riesgo Residual]],t_nivel_riesgo[],2,FALSE),"") -> Riesgo Alto | AM12: Evitar | AX12: =IFERROR((1-Matriz_Riesgos[[#This Row],[Efectividad Total Ponderada de los Controles]])*Matriz_Riesgos[[#This Row],[Frecuencia]],"") -> 2 | AY12: =IFERROR((1-Matriz_Riesgos[[#This Row],[Efectividad Total Ponderada de los Controles]])*Matriz_Riesgos[[#This Row],[Impacto]],"") -> 5 | AZ12: =IFERROR(Matriz_Riesgos[[#This Row],[Valor del Riesgo Residual]] + 1, "") -> 7 | BA12: =IFERROR(MAX(1, ROUNDDOWN(Matriz_Riesgos[[#This Row],[Frecuencia Residual (AUX)]],0)),"") -> 2 | BB12: =IFERROR(MAX(1, ROUNDDOWN(Matriz_Riesgos[[#This Row],[Impacto Residual (AUX)]],0)),"") -> 5 | BC12: =IF(Matriz_Riesgos[[#This Row],[Frecuencia]]="","",Matriz_Riesgos[[#This Row],[Frecuencia]]) -> 2 | BD12: =IF(Matriz_Riesgos[[#This Row],[Impacto]]="","",Matriz_Riesgos[[#This Row],[Impacto]]) -> 5 | BE12: =IF(OR(Matriz_Riesgos[[#This Row],[Tope F (AUX)]]="",Matriz_Riesgos[[#This Row],[F_base (AUX)]]=""),"",MAX(0,Matriz_Riesgos[[#This Row],[Tope F (AUX)]]-Matriz_Riesgos[[#This Row],[F_base (AUX)]])) -> 0 | BF12: =IF(OR(Matriz_Riesgos[[#This Row],[Tope I (AUX)]]="",Matriz_Riesgos[[#This Row],[I_base (AUX)]]=""),"",MAX(0,Matriz_Riesgos[[#This Row],[Tope I (AUX)]]-Matriz_Riesgos[[#This Row],[I_base (AUX)]])) -> 0 | BG12: =IF(OR(Matriz_Riesgos[[#This Row],[Suma Residual redondeada (AUX)]]="",Matriz_Riesgos[[#This Row],[F_base (AUX)]]="",Matriz_Riesgos[[#This Row],[I_base (AUX)]]=""),"",MAX(0,Matriz_Riesgos[[#This Row],[Suma Residual redondeada (AUX)]]-(Matriz_Riesgos[[#This Row],[F_base (AUX)]]+Matriz_Riesgos[[#This Row],[I_base (AUX)]]))) -> 0 | BH12: =IF(OR(Matriz_Riesgos[[#This Row],[Impacto Residual (AUX)]]="",Matriz_Riesgos[[#This Row],[Frecuencia Residual (AUX)]]=""),"",IF(MOD(Matriz_Riesgos[[#This Row],[Impacto Residual (AUX)]],1) > MOD(Matriz_Riesgos[[#This Row],[Frecuencia Residual (AUX)]],1),1,IF(MOD(Matriz_Riesgos[[#This Row],[Impacto Residual (AUX)]],1) = MOD(Matriz_Riesgos[[#This Row],[Frecuencia Residual (AUX)]],1),1,0))) -> 1 | BI12: =IF(OR(Matriz_Riesgos[[#This Row],[Resto (AUX)]]="",Matriz_Riesgos[[#This Row],[Capacidad I (AUX)]]="",Matriz_Riesgos[[#This Row],[Capacidad F (AUX)]]=""),"",IF(Matriz_Riesgos[[#This Row],[Resto (AUX)]]=0, 0,IF(Matriz_Riesgos[[#This Row],[Resto (AUX)]]=1,MIN(Matriz_Riesgos[[#This Row],[Capacidad I (AUX)]], IF(OR(Matriz_Riesgos[[#This Row],[Prefiere I (AUX)]]=1,Matriz_Riesgos[[#This Row],[Capacidad F (AUX)]]=0),1,0)),MIN(Matriz_Riesgos[[#This Row],[Capacidad I (AUX)]],IF(Matriz_Riesgos[[#This Row],[Prefiere I (AUX)]]=1,1 + IF(Matriz_Riesgos[[#This Row],[Capacidad F (AUX)]]>0,0,1),IF(Matriz_Riesgos[[#This Row],[Capacidad F (AUX)]]>0,1,2)))))) -> 0 | BJ12: =IF(OR(Matriz_Riesgos[[#This Row],[Resto (AUX)]]="",Matriz_Riesgos[[#This Row],[Capacidad F (AUX)]]="",Matriz_Riesgos[[#This Row],[Inc_I (AUX)]]=""),"",MIN(Matriz_Riesgos[[#This Row],[Capacidad F (AUX)]], MAX(0,Matriz_Riesgos[[#This Row],[Resto (AUX)]]-Matriz_Riesgos[[#This Row],[Inc_I (AUX)]]))) -> 0 | BK12: =IFERROR(MAX(ROUND(Matriz_Riesgos[[#This Row],[Frecuencia Residual (AUX)]]+Matriz_Riesgos[[#This Row],[Impacto Residual (AUX)]]-1+Matriz_Riesgos[[#This Row],[Efectividad Total Ponderada de los Controles]],0),1),"") -> 6 | BL12: =IFERROR(Matriz_Riesgos[[#This Row],[Valor del Riesgo Residual]]-Matriz_Riesgos[[#This Row],[Valor del Riesgo Residual (AUX)]],"") -> 0 | BM12: =IFERROR(Matriz_Riesgos[[#This Row],[Frecuencia Residual]]+Matriz_Riesgos[[#This Row],[Impacto Residual]]-1,"") -> 6 | BN12: =IFERROR(Matriz_Riesgos[[#This Row],[Valor del Riesgo Residual]]-Matriz_Riesgos[[#This Row],[VRR 2]],"") -> 0 | BO12: =IFERROR(Matriz_Riesgos[[#This Row],[Frecuencia]]-Matriz_Riesgos[[#This Row],[Frecuencia Residual]],"") -> 0 | BP12: =IFERROR(Matriz_Riesgos[[#This Row],[Impacto]]-Matriz_Riesgos[[#This Row],[Impacto Residual]],"") -> 0 | BQ12: =IFERROR(Matriz_Riesgos[[#This Row],[Valor del Riesgo Inherente]]-Matriz_Riesgos[[#This Row],[Valor del Riesgo Residual]],"") -> 0
A13: 12 | B13: ROTR-PATRONAL-12 | C13: Patronal | E13: Otros Riesgos | F13: Sujecion Patronal | H13: Empresas afiliadas que no tiene operaciones reales, no cuenta con infraestructura, empleados o actividad verificable, declara planillas ficticias o presenta aportes mínimos previos a reconocimiento pensional o incapacidad. | I13: Descripción: Posibilidad de que se registren, afilien o mantengan como empleadores activos empresas que no desarrollan una actividad económica real o verificable, constituidas con fines de simulación laboral, o acceso indebido a prestaciones del sistema de seguridad social. Causas: Falta de verificación de existencia y actividad económica (Debilidad en inspección), Falta de cruce con bases tributarias o mercantiles, Uso de testaferros o empresas fachada. Colusión interna. Efecto: Pérdidas economicas (Pago indebido de incapacidades, Cobertura en riesgos laborales sin actividad real)/Afectación en reservas técnicas/Sanciones legales x incumplimiento normativo / LAFT (Uso de empresas fachada para dar apariencia de legalidad) | J13: 3 | K13: 5 | L13: =IF((Matriz_Riesgos[[#This Row],[Frecuencia]]+Matriz_Riesgos[[#This Row],[Impacto]]-1)=-1,"",Matriz_Riesgos[[#This Row],[Frecuencia]]+Matriz_Riesgos[[#This Row],[Impacto]]-1) -> 7 | M13: =IFERROR(VLOOKUP(Matriz_Riesgos[[#This Row],[Valor del Riesgo Inherente]],t_nivel_riesgo[],2,FALSE), "") -> Riesgo Alto | N13: Control Patronal, RP, IVM | P13: Financiero, actuarial, operativo, Fraude, LAFT, reputacional | T13: 1. Validación contra registro mercantil y la SAR 2. Verificación de actividad económica declarada. 3. Análisis de coherencia entre actividad y número de trabajadores. | X13: 1. Cruce con bases fiscales. 2. Identificación de múltiples empresas con mismo representante legal. 3. Indicador de empresas con: Mínimo tiempo de afiliación previo a siniestro. | AB13: 1. uspensión de afiliación. 2. Denuncia por fraude. 3. Recuperación de recursos. | AG13: =IF(AND(T13="",X13="",AB13=""),"",('Otras Tablas'!$B$3*IF(W13="",0,W13)+'Otras Tablas'!$B$4*IF(AA13="",0,AA13)+'Otras Tablas'!$B$5*IF(AE13="",0,AE13))) | AH13: =IF(Matriz_Riesgos[[#This Row],[Riesgo Inherente]]="","",Matriz_Riesgos[[#This Row],[Riesgo Inherente]]) -> Empresas afiliadas que no tiene operaciones reales, no cuenta con infraestructura, empleados o actividad verificable, declara planillas ficticias o presenta aportes mínimos previos a reconocimiento pensional o incapacidad. | AI13: =IFERROR(IF(OR(Matriz_Riesgos[[#This Row],[Frecuencia]]="",Matriz_Riesgos[[#This Row],[Impacto]]="",Matriz_Riesgos[[#This Row],[Valor del Riesgo Inherente]]="",Matriz_Riesgos[[#This Row],[Valor del Riesgo Residual]]=""),"",IF(Matriz_Riesgos[[#This Row],[Valor del Riesgo Inherente]]=Matriz_Riesgos[[#This Row],[Valor del Riesgo Residual]],Matriz_Riesgos[[#This Row],[Frecuencia]],MIN(Matriz_Riesgos[[#This Row],[Tope F (AUX)]], Matriz_Riesgos[[#This Row],[F_base (AUX)]]+Matriz_Riesgos[[#This Row],[Inc_F (AUX)]]))),"") -> 3 | AJ13: =IFERROR(IF(OR(Matriz_Riesgos[[#This Row],[Frecuencia]]="",Matriz_Riesgos[[#This Row],[Impacto]]="",Matriz_Riesgos[[#This Row],[Valor del Riesgo Inherente]]="",Matriz_Riesgos[[#This Row],[Valor del Riesgo Residual]]=""),"",IF(Matriz_Riesgos[[#This Row],[Valor del Riesgo Inherente]]=Matriz_Riesgos[[#This Row],[Valor del Riesgo Residual]],Matriz_Riesgos[[#This Row],[Impacto]],MIN(Matriz_Riesgos[[#This Row],[Tope I (AUX)]], Matriz_Riesgos[[#This Row],[I_base (AUX)]]+Matriz_Riesgos[[#This Row],[Inc_I (AUX)]]))),"") -> 5 | AK13: =IFERROR(ROUND(MAX(1,Matriz_Riesgos[[#This Row],[Valor del Riesgo Inherente]]*(1 - Matriz_Riesgos[[#This Row],[Efectividad Total Ponderada de los Controles]])),0), "") -> 7 | AL13: =IFERROR(VLOOKUP(Matriz_Riesgos[[#This Row],[Valor del Riesgo Residual]],t_nivel_riesgo[],2,FALSE),"") -> Riesgo Alto | AM13: Evitar | AX13: =IFERROR((1-Matriz_Riesgos[[#This Row],[Efectividad Total Ponderada de los Controles]])*Matriz_Riesgos[[#This Row],[Frecuencia]],"") -> 3 | AY13: =IFERROR((1-Matriz_Riesgos[[#This Row],[Efectividad Total Ponderada de los Controles]])*Matriz_Riesgos[[#This Row],[Impacto]],"") -> 5 | AZ13: =IFERROR(Matriz_Riesgos[[#This Row],[Valor del Riesgo Residual]] + 1, "") -> 8 | BA13: =IFERROR(MAX(1, ROUNDDOWN(Matriz_Riesgos[[#This Row],[Frecuencia Residual (AUX)]],0)),"") -> 3 | BB13: =IFERROR(MAX(1, ROUNDDOWN(Matriz_Riesgos[[#This Row],[Impacto Residual (AUX)]],0)),"") -> 5 | BC13: =IF(Matriz_Riesgos[[#This Row],[Frecuencia]]="","",Matriz_Riesgos[[#This Row],[Frecuencia]]) -> 3 | BD13: =IF(Matriz_Riesgos[[#This Row],[Impacto]]="","",Matriz_Riesgos[[#This Row],[Impacto]]) -> 5 | BE13: =IF(OR(Matriz_Riesgos[[#This Row],[Tope F (AUX)]]="",Matriz_Riesgos[[#This Row],[F_base (AUX)]]=""),"",MAX(0,Matriz_Riesgos[[#This Row],[Tope F (AUX)]]-Matriz_Riesgos[[#This Row],[F_base (AUX)]])) -> 0 | BF13: =IF(OR(Matriz_Riesgos[[#This Row],[Tope I (AUX)]]="",Matriz_Riesgos[[#This Row],[I_base (AUX)]]=""),"",MAX(0,Matriz_Riesgos[[#This Row],[Tope I (AUX)]]-Matriz_Riesgos[[#This Row],[I_base (AUX)]])) -> 0 | BG13: =IF(OR(Matriz_Riesgos[[#This Row],[Suma Residual redondeada (AUX)]]="",Matriz_Riesgos[[#This Row],[F_base (AUX)]]="",Matriz_Riesgos[[#This Row],[I_base (AUX)]]=""),"",MAX(0,Matriz_Riesgos[[#This Row],[Suma Residual redondeada (AUX)]]-(Matriz_Riesgos[[#This Row],[F_base (AUX)]]+Matriz_Riesgos[[#This Row],[I_base (AUX)]]))) -> 0 | BH13: =IF(OR(Matriz_Riesgos[[#This Row],[Impacto Residual (AUX)]]="",Matriz_Riesgos[[#This Row],[Frecuencia Residual (AUX)]]=""),"",IF(MOD(Matriz_Riesgos[[#This Row],[Impacto Residual (AUX)]],1) > MOD(Matriz_Riesgos[[#This Row],[Frecuencia Residual (AUX)]],1),1,IF(MOD(Matriz_Riesgos[[#This Row],[Impacto Residual (AUX)]],1) = MOD(Matriz_Riesgos[[#This Row],[Frecuencia Residual (AUX)]],1),1,0))) -> 1 | BI13: =IF(OR(Matriz_Riesgos[[#This Row],[Resto (AUX)]]="",Matriz_Riesgos[[#This Row],[Capacidad I (AUX)]]="",Matriz_Riesgos[[#This Row],[Capacidad F (AUX)]]=""),"",IF(Matriz_Riesgos[[#This Row],[Resto (AUX)]]=0, 0,IF(Matriz_Riesgos[[#This Row],[Resto (AUX)]]=1,MIN(Matriz_Riesgos[[#This Row],[Capacidad I (AUX)]], IF(OR(Matriz_Riesgos[[#This Row],[Prefiere I (AUX)]]=1,Matriz_Riesgos[[#This Row],[Capacidad F (AUX)]]=0),1,0)),MIN(Matriz_Riesgos[[#This Row],[Capacidad I (AUX)]],IF(Matriz_Riesgos[[#This Row],[Prefiere I (AUX)]]=1,1 + IF(Matriz_Riesgos[[#This Row],[Capacidad F (AUX)]]>0,0,1),IF(Matriz_Riesgos[[#This Row],[Capacidad F (AUX)]]>0,1,2)))))) -> 0 | BJ13: =IF(OR(Matriz_Riesgos[[#This Row],[Resto (AUX)]]="",Matriz_Riesgos[[#This Row],[Capacidad F (AUX)]]="",Matriz_Riesgos[[#This Row],[Inc_I (AUX)]]=""),"",MIN(Matriz_Riesgos[[#This Row],[Capacidad F (AUX)]], MAX(0,Matriz_Riesgos[[#This Row],[Resto (AUX)]]-Matriz_Riesgos[[#This Row],[Inc_I (AUX)]]))) -> 0 | BK13: =IFERROR(MAX(ROUND(Matriz_Riesgos[[#This Row],[Frecuencia Residual (AUX)]]+Matriz_Riesgos[[#This Row],[Impacto Residual (AUX)]]-1+Matriz_Riesgos[[#This Row],[Efectividad Total Ponderada de los Controles]],0),1),"") -> 7 | BL13: =IFERROR(Matriz_Riesgos[[#This Row],[Valor del Riesgo Residual]]-Matriz_Riesgos[[#This Row],[Valor del Riesgo Residual (AUX)]],"") -> 0 | BM13: =IFERROR(Matriz_Riesgos[[#This Row],[Frecuencia Residual]]+Matriz_Riesgos[[#This Row],[Impacto Residual]]-1,"") -> 7 | BN13: =IFERROR(Matriz_Riesgos[[#This Row],[Valor del Riesgo Residual]]-Matriz_Riesgos[[#This Row],[VRR 2]],"") -> 0 | BO13: =IFERROR(Matriz_Riesgos[[#This Row],[Frecuencia]]-Matriz_Riesgos[[#This Row],[Frecuencia Residual]],"") -> 0 | BP13: =IFERROR(Matriz_Riesgos[[#This Row],[Impacto]]-Matriz_Riesgos[[#This Row],[Impacto Residual]],"") -> 0 | BQ13: =IFERROR(Matriz_Riesgos[[#This Row],[Valor del Riesgo Inherente]]-Matriz_Riesgos[[#This Row],[Valor del Riesgo Residual]],"") -> 0
A14: 13 | B14: ROTR-IVM-13 | C14: IVM | E14: Otros Riesgos | F14: Calculo de pension | H14: Reconocimiento de prestacion economica cuando se adicionan periodos no cotizadas realmente, se duplican períodos ya contabilizados, se modifican historiales laborales en el sistema o se corrigen registros sin trazabilidad. | I14: Descripción: Posibilidad de que se manipule, registre indebidamente o altere el número de períodos o montos de cotización de un afiliado, con el fin de cumplir artificialmente los requisitos para acceder a beneficios previsionales. Causas: Debilidad en controles sobre historia laboral, Procesos manuales de corrección sin validación robusta, Certificaciones laborales falsas, Colusión interna. Efecto: Pérdidas económicas (Reconocimiento indebido de pensión), distorsión de reservas técnicas, litigios posteriores por revocatoria, sanciones legales x incumplimiento normativo. | J14: 3 | K14: 5 | L14: =IF((Matriz_Riesgos[[#This Row],[Frecuencia]]+Matriz_Riesgos[[#This Row],[Impacto]]-1)=-1,"",Matriz_Riesgos[[#This Row],[Frecuencia]]+Matriz_Riesgos[[#This Row],[Impacto]]-1) -> 7 | M14: =IFERROR(VLOOKUP(Matriz_Riesgos[[#This Row],[Valor del Riesgo Inherente]],t_nivel_riesgo[],2,FALSE), "") -> Riesgo Alto | N14: IVM | O14: IVM | P14: Fraude, operativo, legal financiero, reputacional, actuarial | T14: 1. Bloqueo de modificación directa de semanas sin trazabilidad. 2. Doble validación en correcciones de historia laboral. | X14: 1. Alertas por correcciones masivas en corto tiempo. 2. Auditoría periódica de modificaciones históricas. | AB14: 1. Acción de repetición. 2. Denuncia penal por fraude documental. | AG14: =IF(AND(T14="",X14="",AB14=""),"",('Otras Tablas'!$B$3*IF(W14="",0,W14)+'Otras Tablas'!$B$4*IF(AA14="",0,AA14)+'Otras Tablas'!$B$5*IF(AE14="",0,AE14))) | AH14: =IF(Matriz_Riesgos[[#This Row],[Riesgo Inherente]]="","",Matriz_Riesgos[[#This Row],[Riesgo Inherente]]) -> Reconocimiento de prestacion economica cuando se adicionan periodos no cotizadas realmente, se duplican períodos ya contabilizados, se modifican historiales laborales en el sistema o se corrigen registros sin trazabilidad. | AI14: =IFERROR(IF(OR(Matriz_Riesgos[[#This Row],[Frecuencia]]="",Matriz_Riesgos[[#This Row],[Impacto]]="",Matriz_Riesgos[[#This Row],[Valor del Riesgo Inherente]]="",Matriz_Riesgos[[#This Row],[Valor del Riesgo Residual]]=""),"",IF(Matriz_Riesgos[[#This Row],[Valor del Riesgo Inherente]]=Matriz_Riesgos[[#This Row],[Valor del Riesgo Residual]],Matriz_Riesgos[[#This Row],[Frecuencia]],MIN(Matriz_Riesgos[[#This Row],[Tope F (AUX)]], Matriz_Riesgos[[#This Row],[F_base (AUX)]]+Matriz_Riesgos[[#This Row],[Inc_F (AUX)]]))),"") -> 3 | AJ14: =IFERROR(IF(OR(Matriz_Riesgos[[#This Row],[Frecuencia]]="",Matriz_Riesgos[[#This Row],[Impacto]]="",Matriz_Riesgos[[#This Row],[Valor del Riesgo Inherente]]="",Matriz_Riesgos[[#This Row],[Valor del Riesgo Residual]]=""),"",IF(Matriz_Riesgos[[#This Row],[Valor del Riesgo Inherente]]=Matriz_Riesgos[[#This Row],[Valor del Riesgo Residual]],Matriz_Riesgos[[#This Row],[Impacto]],MIN(Matriz_Riesgos[[#This Row],[Tope I (AUX)]], Matriz_Riesgos[[#This Row],[I_base (AUX)]]+Matriz_Riesgos[[#This Row],[Inc_I (AUX)]]))),"") -> 5 | AK14: =IFERROR(ROUND(MAX(1,Matriz_Riesgos[[#This Row],[Valor del Riesgo Inherente]]*(1 - Matriz_Riesgos[[#This Row],[Efectividad Total Ponderada de los Controles]])),0), "") -> 7 | AL14: =IFERROR(VLOOKUP(Matriz_Riesgos[[#This Row],[Valor del Riesgo Residual]],t_nivel_riesgo[],2,FALSE),"") -> Riesgo Alto | AM14: Evitar | AX14: =IFERROR((1-Matriz_Riesgos[[#This Row],[Efectividad Total Ponderada de los Controles]])*Matriz_Riesgos[[#This Row],[Frecuencia]],"") -> 3 | AY14: =IFERROR((1-Matriz_Riesgos[[#This Row],[Efectividad Total Ponderada de los Controles]])*Matriz_Riesgos[[#This Row],[Impacto]],"") -> 5 | AZ14: =IFERROR(Matriz_Riesgos[[#This Row],[Valor del Riesgo Residual]] + 1, "") -> 8 | BA14: =IFERROR(MAX(1, ROUNDDOWN(Matriz_Riesgos[[#This Row],[Frecuencia Residual (AUX)]],0)),"") -> 3 | BB14: =IFERROR(MAX(1, ROUNDDOWN(Matriz_Riesgos[[#This Row],[Impacto Residual (AUX)]],0)),"") -> 5 | BC14: =IF(Matriz_Riesgos[[#This Row],[Frecuencia]]="","",Matriz_Riesgos[[#This Row],[Frecuencia]]) -> 3 | BD14: =IF(Matriz_Riesgos[[#This Row],[Impacto]]="","",Matriz_Riesgos[[#This Row],[Impacto]]) -> 5 | BE14: =IF(OR(Matriz_Riesgos[[#This Row],[Tope F (AUX)]]="",Matriz_Riesgos[[#This Row],[F_base (AUX)]]=""),"",MAX(0,Matriz_Riesgos[[#This Row],[Tope F (AUX)]]-Matriz_Riesgos[[#This Row],[F_base (AUX)]])) -> 0 | BF14: =IF(OR(Matriz_Riesgos[[#This Row],[Tope I (AUX)]]="",Matriz_Riesgos[[#This Row],[I_base (AUX)]]=""),"",MAX(0,Matriz_Riesgos[[#This Row],[Tope I (AUX)]]-Matriz_Riesgos[[#This Row],[I_base (AUX)]])) -> 0 | BG14: =IF(OR(Matriz_Riesgos[[#This Row],[Suma Residual redondeada (AUX)]]="",Matriz_Riesgos[[#This Row],[F_base (AUX)]]="",Matriz_Riesgos[[#This Row],[I_base (AUX)]]=""),"",MAX(0,Matriz_Riesgos[[#This Row],[Suma Residual redondeada (AUX)]]-(Matriz_Riesgos[[#This Row],[F_base (AUX)]]+Matriz_Riesgos[[#This Row],[I_base (AUX)]]))) -> 0 | BH14: =IF(OR(Matriz_Riesgos[[#This Row],[Impacto Residual (AUX)]]="",Matriz_Riesgos[[#This Row],[Frecuencia Residual (AUX)]]=""),"",IF(MOD(Matriz_Riesgos[[#This Row],[Impacto Residual (AUX)]],1) > MOD(Matriz_Riesgos[[#This Row],[Frecuencia Residual (AUX)]],1),1,IF(MOD(Matriz_Riesgos[[#This Row],[Impacto Residual (AUX)]],1) = MOD(Matriz_Riesgos[[#This Row],[Frecuencia Residual (AUX)]],1),1,0))) -> 1 | BI14: =IF(OR(Matriz_Riesgos[[#This Row],[Resto (AUX)]]="",Matriz_Riesgos[[#This Row],[Capacidad I (AUX)]]="",Matriz_Riesgos[[#This Row],[Capacidad F (AUX)]]=""),"",IF(Matriz_Riesgos[[#This Row],[Resto (AUX)]]=0, 0,IF(Matriz_Riesgos[[#This Row],[Resto (AUX)]]=1,MIN(Matriz_Riesgos[[#This Row],[Capacidad I (AUX)]], IF(OR(Matriz_Riesgos[[#This Row],[Prefiere I (AUX)]]=1,Matriz_Riesgos[[#This Row],[Capacidad F (AUX)]]=0),1,0)),MIN(Matriz_Riesgos[[#This Row],[Capacidad I (AUX)]],IF(Matriz_Riesgos[[#This Row],[Prefiere I (AUX)]]=1,1 + IF(Matriz_Riesgos[[#This Row],[Capacidad F (AUX)]]>0,0,1),IF(Matriz_Riesgos[[#This Row],[Capacidad F (AUX)]]>0,1,2)))))) -> 0 | BJ14: =IF(OR(Matriz_Riesgos[[#This Row],[Resto (AUX)]]="",Matriz_Riesgos[[#This Row],[Capacidad F (AUX)]]="",Matriz_Riesgos[[#This Row],[Inc_I (AUX)]]=""),"",MIN(Matriz_Riesgos[[#This Row],[Capacidad F (AUX)]], MAX(0,Matriz_Riesgos[[#This Row],[Resto (AUX)]]-Matriz_Riesgos[[#This Row],[Inc_I (AUX)]]))) -> 0 | BK14: =IFERROR(MAX(ROUND(Matriz_Riesgos[[#This Row],[Frecuencia Residual (AUX)]]+Matriz_Riesgos[[#This Row],[Impacto Residual (AUX)]]-1+Matriz_Riesgos[[#This Row],[Efectividad Total Ponderada de los Controles]],0),1),"") -> 7 | BL14: =IFERROR(Matriz_Riesgos[[#This Row],[Valor del Riesgo Residual]]-Matriz_Riesgos[[#This Row],[Valor del Riesgo Residual (AUX)]],"") -> 0 | BM14: =IFERROR(Matriz_Riesgos[[#This Row],[Frecuencia Residual]]+Matriz_Riesgos[[#This Row],[Impacto Residual]]-1,"") -> 7 | BN14: =IFERROR(Matriz_Riesgos[[#This Row],[Valor del Riesgo Residual]]-Matriz_Riesgos[[#This Row],[VRR 2]],"") -> 0 | BO14: =IFERROR(Matriz_Riesgos[[#This Row],[Frecuencia]]-Matriz_Riesgos[[#This Row],[Frecuencia Residual]],"") -> 0 | BP14: =IFERROR(Matriz_Riesgos[[#This Row],[Impacto]]-Matriz_Riesgos[[#This Row],[Impacto Residual]],"") -> 0 | BQ14: =IFERROR(Matriz_Riesgos[[#This Row],[Valor del Riesgo Inherente]]-Matriz_Riesgos[[#This Row],[Valor del Riesgo Residual]],"") -> 0
A15: 14 | B15: ROTR-RRHH-14 | C15: RRHH | E15: Otros Riesgos | F15: Planilla | H15: Pago de planilla o desembolso de salarios, a empleados inexistentes dentro del IHSS (empleados fantasma) o a cuentas bancarias controladas por tercerros | I15: Descripción: Posibilidad de que funcionarios o empleados con acceso a los sistemas de gestión humana y nómina creen, modifiquen o mantengan registros de empleados inexistentes o retirados, con el fin de generar pagos salariales y prestaciones económicas indebidas. Causas: Falta de segregación de funciones entre creación, modificación y pago de nómina, Debilidades en los controles de vinculación y retiro de personal, Deficiencias en la validación de cuentas bancarias y documentos de identidad, Controles insuficientes en accesos y perfiles del sistema, Cultura ética débil o ausencia de monitoreo antifraude ( Efecto: Pérdidas económicas / LAFT / | J15: 2 | K15: 5 | L15: =IF((Matriz_Riesgos[[#This Row],[Frecuencia]]+Matriz_Riesgos[[#This Row],[Impacto]]-1)=-1,"",Matriz_Riesgos[[#This Row],[Frecuencia]]+Matriz_Riesgos[[#This Row],[Impacto]]-1) -> 6 | M15: =IFERROR(VLOOKUP(Matriz_Riesgos[[#This Row],[Valor del Riesgo Inherente]],t_nivel_riesgo[],2,FALSE), "") -> Riesgo Alto | N15: RRHH | O15: Todos | P15: Fraude/LAFT/operativo/abuso de autoridad | X15: Cruces de informacion RRHH y financiera | AG15: =IF(AND(T15="",X15="",AB15=""),"",('Otras Tablas'!$B$3*IF(W15="",0,W15)+'Otras Tablas'!$B$4*IF(AA15="",0,AA15)+'Otras Tablas'!$B$5*IF(AE15="",0,AE15))) | AH15: =IF(Matriz_Riesgos[[#This Row],[Riesgo Inherente]]="","",Matriz_Riesgos[[#This Row],[Riesgo Inherente]]) -> Pago de planilla o desembolso de salarios, a empleados inexistentes dentro del IHSS (empleados fantasma) o a cuentas bancarias controladas por tercerros | AI15: =IFERROR(IF(OR(Matriz_Riesgos[[#This Row],[Frecuencia]]="",Matriz_Riesgos[[#This Row],[Impacto]]="",Matriz_Riesgos[[#This Row],[Valor del Riesgo Inherente]]="",Matriz_Riesgos[[#This Row],[Valor del Riesgo Residual]]=""),"",IF(Matriz_Riesgos[[#This Row],[Valor del Riesgo Inherente]]=Matriz_Riesgos[[#This Row],[Valor del Riesgo Residual]],Matriz_Riesgos[[#This Row],[Frecuencia]],MIN(Matriz_Riesgos[[#This Row],[Tope F (AUX)]], Matriz_Riesgos[[#This Row],[F_base (AUX)]]+Matriz_Riesgos[[#This Row],[Inc_F (AUX)]]))),"") -> 2 | AJ15: =IFERROR(IF(OR(Matriz_Riesgos[[#This Row],[Frecuencia]]="",Matriz_Riesgos[[#This Row],[Impacto]]="",Matriz_Riesgos[[#This Row],[Valor del Riesgo Inherente]]="",Matriz_Riesgos[[#This Row],[Valor del Riesgo Residual]]=""),"",IF(Matriz_Riesgos[[#This Row],[Valor del Riesgo Inherente]]=Matriz_Riesgos[[#This Row],[Valor del Riesgo Residual]],Matriz_Riesgos[[#This Row],[Impacto]],MIN(Matriz_Riesgos[[#This Row],[Tope I (AUX)]], Matriz_Riesgos[[#This Row],[I_base (AUX)]]+Matriz_Riesgos[[#This Row],[Inc_I (AUX)]]))),"") -> 5 | AK15: =IFERROR(ROUND(MAX(1,Matriz_Riesgos[[#This Row],[Valor del Riesgo Inherente]]*(1 - Matriz_Riesgos[[#This Row],[Efectividad Total Ponderada de los Controles]])),0), "") -> 6 | AL15: =IFERROR(VLOOKUP(Matriz_Riesgos[[#This Row],[Valor del Riesgo Residual]],t_nivel_riesgo[],2,FALSE),"") -> Riesgo Alto | AM15: Evitar | AX15: =IFERROR((1-Matriz_Riesgos[[#This Row],[Efectividad Total Ponderada de los Controles]])*Matriz_Riesgos[[#This Row],[Frecuencia]],"") -> 2 | AY15: =IFERROR((1-Matriz_Riesgos[[#This Row],[Efectividad Total Ponderada de los Controles]])*Matriz_Riesgos[[#This Row],[Impacto]],"") -> 5 | AZ15: =IFERROR(Matriz_Riesgos[[#This Row],[Valor del Riesgo Residual]] + 1, "") -> 7 | BA15: =IFERROR(MAX(1, ROUNDDOWN(Matriz_Riesgos[[#This Row],[Frecuencia Residual (AUX)]],0)),"") -> 2 | BB15: =IFERROR(MAX(1, ROUNDDOWN(Matriz_Riesgos[[#This Row],[Impacto Residual (AUX)]],0)),"") -> 5 | BC15: =IF(Matriz_Riesgos[[#This Row],[Frecuencia]]="","",Matriz_Riesgos[[#This Row],[Frecuencia]]) -> 2 | BD15: =IF(Matriz_Riesgos[[#This Row],[Impacto]]="","",Matriz_Riesgos[[#This Row],[Impacto]]) -> 5 | BE15: =IF(OR(Matriz_Riesgos[[#This Row],[Tope F (AUX)]]="",Matriz_Riesgos[[#This Row],[F_base (AUX)]]=""),"",MAX(0,Matriz_Riesgos[[#This Row],[Tope F (AUX)]]-Matriz_Riesgos[[#This Row],[F_base (AUX)]])) -> 0 | BF15: =IF(OR(Matriz_Riesgos[[#This Row],[Tope I (AUX)]]="",Matriz_Riesgos[[#This Row],[I_base (AUX)]]=""),"",MAX(0,Matriz_Riesgos[[#This Row],[Tope I (AUX)]]-Matriz_Riesgos[[#This Row],[I_base (AUX)]])) -> 0 | BG15: =IF(OR(Matriz_Riesgos[[#This Row],[Suma Residual redondeada (AUX)]]="",Matriz_Riesgos[[#This Row],[F_base (AUX)]]="",Matriz_Riesgos[[#This Row],[I_base (AUX)]]=""),"",MAX(0,Matriz_Riesgos[[#This Row],[Suma Residual redondeada (AUX)]]-(Matriz_Riesgos[[#This Row],[F_base (AUX)]]+Matriz_Riesgos[[#This Row],[I_base (AUX)]]))) -> 0 | BH15: =IF(OR(Matriz_Riesgos[[#This Row],[Impacto Residual (AUX)]]="",Matriz_Riesgos[[#This Row],[Frecuencia Residual (AUX)]]=""),"",IF(MOD(Matriz_Riesgos[[#This Row],[Impacto Residual (AUX)]],1) > MOD(Matriz_Riesgos[[#This Row],[Frecuencia Residual (AUX)]],1),1,IF(MOD(Matriz_Riesgos[[#This Row],[Impacto Residual (AUX)]],1) = MOD(Matriz_Riesgos[[#This Row],[Frecuencia Residual (AUX)]],1),1,0))) -> 1 | BI15: =IF(OR(Matriz_Riesgos[[#This Row],[Resto (AUX)]]="",Matriz_Riesgos[[#This Row],[Capacidad I (AUX)]]="",Matriz_Riesgos[[#This Row],[Capacidad F (AUX)]]=""),"",IF(Matriz_Riesgos[[#This Row],[Resto (AUX)]]=0, 0,IF(Matriz_Riesgos[[#This Row],[Resto (AUX)]]=1,MIN(Matriz_Riesgos[[#This Row],[Capacidad I (AUX)]], IF(OR(Matriz_Riesgos[[#This Row],[Prefiere I (AUX)]]=1,Matriz_Riesgos[[#This Row],[Capacidad F (AUX)]]=0),1,0)),MIN(Matriz_Riesgos[[#This Row],[Capacidad I (AUX)]],IF(Matriz_Riesgos[[#This Row],[Prefiere I (AUX)]]=1,1 + IF(Matriz_Riesgos[[#This Row],[Capacidad F (AUX)]]>0,0,1),IF(Matriz_Riesgos[[#This Row],[Capacidad F (AUX)]]>0,1,2)))))) -> 0 | BJ15: =IF(OR(Matriz_Riesgos[[#This Row],[Resto (AUX)]]="",Matriz_Riesgos[[#This Row],[Capacidad F (AUX)]]="",Matriz_Riesgos[[#This Row],[Inc_I (AUX)]]=""),"",MIN(Matriz_Riesgos[[#This Row],[Capacidad F (AUX)]], MAX(0,Matriz_Riesgos[[#This Row],[Resto (AUX)]]-Matriz_Riesgos[[#This Row],[Inc_I (AUX)]]))) -> 0 | BK15: =IFERROR(MAX(ROUND(Matriz_Riesgos[[#This Row],[Frecuencia Residual (AUX)]]+Matriz_Riesgos[[#This Row],[Impacto Residual (AUX)]]-1+Matriz_Riesgos[[#This Row],[Efectividad Total Ponderada de los Controles]],0),1),"") -> 6 | BL15: =IFERROR(Matriz_Riesgos[[#This Row],[Valor del Riesgo Residual]]-Matriz_Riesgos[[#This Row],[Valor del Riesgo Residual (AUX)]],"") -> 0 | BM15: =IFERROR(Matriz_Riesgos[[#This Row],[Frecuencia Residual]]+Matriz_Riesgos[[#This Row],[Impacto Residual]]-1,"") -> 6 | BN15: =IFERROR(Matriz_Riesgos[[#This Row],[Valor del Riesgo Residual]]-Matriz_Riesgos[[#This Row],[VRR 2]],"") -> 0 | BO15: =IFERROR(Matriz_Riesgos[[#This Row],[Frecuencia]]-Matriz_Riesgos[[#This Row],[Frecuencia Residual]],"") -> 0 | BP15: =IFERROR(Matriz_Riesgos[[#This Row],[Impacto]]-Matriz_Riesgos[[#This Row],[Impacto Residual]],"") -> 0 | BQ15: =IFERROR(Matriz_Riesgos[[#This Row],[Valor del Riesgo Inherente]]-Matriz_Riesgos[[#This Row],[Valor del Riesgo Residual]],"") -> 0 | BR15: 1. Cuentas bancarias repetidas en diferentes empleados 2. Empleados sin expediente físico completo 3. Falta de registro biométrico o control de asistencia 4. Variaciones presupuestarias sin justificación
A16: 15 | B16: ROTR-RRHH-15 | C16: RRHH | E16: Otros Riesgos | F16: Gestion Salaial | H16: Aplicación de incrementos salariales sin respaldo presupuestario ni aprobación formal conforme a normativa interna | I16: Descripción: Posibilidad de que funcionarios con facultades en la administración de personal aprueben o ejecuten incrementos salariales, bonificaciones o ajustes remunerativos sin cumplir los procedimientos, autorizaciones o disposiciones presupuestarias establecidas, con el fin de beneficiar indebidamente a empleados o desviar recursos institucionales. Causas: Falta de segregación de funciones, Debilidad en controles de aprobación por jerarquias, Accesos excesivos al sistema de planillas, Ausencia de auditoría periódica, Cultura organizacional permisiva Efecto: Pérdidas económicas, daño reputacional, sanciones por incumplimiento normativo | J16: 3 | K16: 4 | L16: =IF((Matriz_Riesgos[[#This Row],[Frecuencia]]+Matriz_Riesgos[[#This Row],[Impacto]]-1)=-1,"",Matriz_Riesgos[[#This Row],[Frecuencia]]+Matriz_Riesgos[[#This Row],[Impacto]]-1) -> 6 | M16: =IFERROR(VLOOKUP(Matriz_Riesgos[[#This Row],[Valor del Riesgo Inherente]],t_nivel_riesgo[],2,FALSE), "") -> Riesgo Alto | N16: RRHH | O16: Todos | P16: Fraude, Corrupcion, operativo, financiero | T16: 1. Politica formalizada de incrementos salariales 2.- Segregacion de Funciones 3.- Aprobaciones jerarquicas/cero dependencia de un unico aprobador 4.- parametrizacion del sistema de planillas 5.- Control presupuestario previo 6.- Manual de funciones actualizado | X16: 1.- Conciliacion mensual entre planilla pagada y presupuesto 2.- Bitacora del sistema de modificaciones salariales 3. Revision semestral (por lo menos) por parte de Auditoria Interna a las actas de aprobacion, soporte presupuestario y expedientes laborales, asi como de incrementos salariales extraordinarios 4. Generacion de sistema de alertas para incrementos salariales multiples en un mismo año | AB16: 1.- Suspension inmediata de incremento irregular 2. Investigacion administrativa formal 3. Recuperacion de valores pagados indebidamente 4. Fortalecimiento de los controles vulnerados 5.- Informe a las autoridades competentes en caso de indicios suficiente de delito. | AG16: =IF(AND(T16="",X16="",AB16=""),"",('Otras Tablas'!$B$3*IF(W16="",0,W16)+'Otras Tablas'!$B$4*IF(AA16="",0,AA16)+'Otras Tablas'!$B$5*IF(AE16="",0,AE16))) | AH16: =IF(Matriz_Riesgos[[#This Row],[Riesgo Inherente]]="","",Matriz_Riesgos[[#This Row],[Riesgo Inherente]]) -> Aplicación de incrementos salariales sin respaldo presupuestario ni aprobación formal conforme a normativa interna | AI16: =IFERROR(IF(OR(Matriz_Riesgos[[#This Row],[Frecuencia]]="",Matriz_Riesgos[[#This Row],[Impacto]]="",Matriz_Riesgos[[#This Row],[Valor del Riesgo Inherente]]="",Matriz_Riesgos[[#This Row],[Valor del Riesgo Residual]]=""),"",IF(Matriz_Riesgos[[#This Row],[Valor del Riesgo Inherente]]=Matriz_Riesgos[[#This Row],[Valor del Riesgo Residual]],Matriz_Riesgos[[#This Row],[Frecuencia]],MIN(Matriz_Riesgos[[#This Row],[Tope F (AUX)]], Matriz_Riesgos[[#This Row],[F_base (AUX)]]+Matriz_Riesgos[[#This Row],[Inc_F (AUX)]]))),"") -> 3 | AJ16: =IFERROR(IF(OR(Matriz_Riesgos[[#This Row],[Frecuencia]]="",Matriz_Riesgos[[#This Row],[Impacto]]="",Matriz_Riesgos[[#This Row],[Valor del Riesgo Inherente]]="",Matriz_Riesgos[[#This Row],[Valor del Riesgo Residual]]=""),"",IF(Matriz_Riesgos[[#This Row],[Valor del Riesgo Inherente]]=Matriz_Riesgos[[#This Row],[Valor del Riesgo Residual]],Matriz_Riesgos[[#This Row],[Impacto]],MIN(Matriz_Riesgos[[#This Row],[Tope I (AUX)]], Matriz_Riesgos[[#This Row],[I_base (AUX)]]+Matriz_Riesgos[[#This Row],[Inc_I (AUX)]]))),"") -> 4 | AK16: =IFERROR(ROUND(MAX(1,Matriz_Riesgos[[#This Row],[Valor del Riesgo Inherente]]*(1 - Matriz_Riesgos[[#This Row],[Efectividad Total Ponderada de los Controles]])),0), "") -> 6 | AL16: =IFERROR(VLOOKUP(Matriz_Riesgos[[#This Row],[Valor del Riesgo Residual]],t_nivel_riesgo[],2,FALSE),"") -> Riesgo Alto | AM16: Evitar | AX16: =IFERROR((1-Matriz_Riesgos[[#This Row],[Efectividad Total Ponderada de los Controles]])*Matriz_Riesgos[[#This Row],[Frecuencia]],"") -> 3 | AY16: =IFERROR((1-Matriz_Riesgos[[#This Row],[Efectividad Total Ponderada de los Controles]])*Matriz_Riesgos[[#This Row],[Impacto]],"") -> 4 | AZ16: =IFERROR(Matriz_Riesgos[[#This Row],[Valor del Riesgo Residual]] + 1, "") -> 7 | BA16: =IFERROR(MAX(1, ROUNDDOWN(Matriz_Riesgos[[#This Row],[Frecuencia Residual (AUX)]],0)),"") -> 3 | BB16: =IFERROR(MAX(1, ROUNDDOWN(Matriz_Riesgos[[#This Row],[Impacto Residual (AUX)]],0)),"") -> 4 | BC16: =IF(Matriz_Riesgos[[#This Row],[Frecuencia]]="","",Matriz_Riesgos[[#This Row],[Frecuencia]]) -> 3 | BD16: =IF(Matriz_Riesgos[[#This Row],[Impacto]]="","",Matriz_Riesgos[[#This Row],[Impacto]]) -> 4 | BE16: =IF(OR(Matriz_Riesgos[[#This Row],[Tope F (AUX)]]="",Matriz_Riesgos[[#This Row],[F_base (AUX)]]=""),"",MAX(0,Matriz_Riesgos[[#This Row],[Tope F (AUX)]]-Matriz_Riesgos[[#This Row],[F_base (AUX)]])) -> 0 | BF16: =IF(OR(Matriz_Riesgos[[#This Row],[Tope I (AUX)]]="",Matriz_Riesgos[[#This Row],[I_base (AUX)]]=""),"",MAX(0,Matriz_Riesgos[[#This Row],[Tope I (AUX)]]-Matriz_Riesgos[[#This Row],[I_base (AUX)]])) -> 0 | BG16: =IF(OR(Matriz_Riesgos[[#This Row],[Suma Residual redondeada (AUX)]]="",Matriz_Riesgos[[#This Row],[F_base (AUX)]]="",Matriz_Riesgos[[#This Row],[I_base (AUX)]]=""),"",MAX(0,Matriz_Riesgos[[#This Row],[Suma Residual redondeada (AUX)]]-(Matriz_Riesgos[[#This Row],[F_base (AUX)]]+Matriz_Riesgos[[#This Row],[I_base (AUX)]]))) -> 0 | BH16: =IF(OR(Matriz_Riesgos[[#This Row],[Impacto Residual (AUX)]]="",Matriz_Riesgos[[#This Row],[Frecuencia Residual (AUX)]]=""),"",IF(MOD(Matriz_Riesgos[[#This Row],[Impacto Residual (AUX)]],1) > MOD(Matriz_Riesgos[[#This Row],[Frecuencia Residual (AUX)]],1),1,IF(MOD(Matriz_Riesgos[[#This Row],[Impacto Residual (AUX)]],1) = MOD(Matriz_Riesgos[[#This Row],[Frecuencia Residual (AUX)]],1),1,0))) -> 1 | BI16: =IF(OR(Matriz_Riesgos[[#This Row],[Resto (AUX)]]="",Matriz_Riesgos[[#This Row],[Capacidad I (AUX)]]="",Matriz_Riesgos[[#This Row],[Capacidad F (AUX)]]=""),"",IF(Matriz_Riesgos[[#This Row],[Resto (AUX)]]=0, 0,IF(Matriz_Riesgos[[#This Row],[Resto (AUX)]]=1,MIN(Matriz_Riesgos[[#This Row],[Capacidad I (AUX)]], IF(OR(Matriz_Riesgos[[#This Row],[Prefiere I (AUX)]]=1,Matriz_Riesgos[[#This Row],[Capacidad F (AUX)]]=0),1,0)),MIN(Matriz_Riesgos[[#This Row],[Capacidad I (AUX)]],IF(Matriz_Riesgos[[#This Row],[Prefiere I (AUX)]]=1,1 + IF(Matriz_Riesgos[[#This Row],[Capacidad F (AUX)]]>0,0,1),IF(Matriz_Riesgos[[#This Row],[Capacidad F (AUX)]]>0,1,2)))))) -> 0 | BJ16: =IF(OR(Matriz_Riesgos[[#This Row],[Resto (AUX)]]="",Matriz_Riesgos[[#This Row],[Capacidad F (AUX)]]="",Matriz_Riesgos[[#This Row],[Inc_I (AUX)]]=""),"",MIN(Matriz_Riesgos[[#This Row],[Capacidad F (AUX)]], MAX(0,Matriz_Riesgos[[#This Row],[Resto (AUX)]]-Matriz_Riesgos[[#This Row],[Inc_I (AUX)]]))) -> 0 | BK16: =IFERROR(MAX(ROUND(Matriz_Riesgos[[#This Row],[Frecuencia Residual (AUX)]]+Matriz_Riesgos[[#This Row],[Impacto Residual (AUX)]]-1+Matriz_Riesgos[[#This Row],[Efectividad Total Ponderada de los Controles]],0),1),"") -> 6 | BL16: =IFERROR(Matriz_Riesgos[[#This Row],[Valor del Riesgo Residual]]-Matriz_Riesgos[[#This Row],[Valor del Riesgo Residual (AUX)]],"") -> 0 | BM16: =IFERROR(Matriz_Riesgos[[#This Row],[Frecuencia Residual]]+Matriz_Riesgos[[#This Row],[Impacto Residual]]-1,"") -> 6 | BN16: =IFERROR(Matriz_Riesgos[[#This Row],[Valor del Riesgo Residual]]-Matriz_Riesgos[[#This Row],[VRR 2]],"") -> 0 | BO16: =IFERROR(Matriz_Riesgos[[#This Row],[Frecuencia]]-Matriz_Riesgos[[#This Row],[Frecuencia Residual]],"") -> 0 | BP16: =IFERROR(Matriz_Riesgos[[#This Row],[Impacto]]-Matriz_Riesgos[[#This Row],[Impacto Residual]],"") -> 0 | BQ16: =IFERROR(Matriz_Riesgos[[#This Row],[Valor del Riesgo Inherente]]-Matriz_Riesgos[[#This Row],[Valor del Riesgo Residual]],"") -> 0 | BR16: 1. Incrementos salariales fuera del período anual autorizado 2. Ajustes manuales en sistema sin acta de aprobación 3. Variaciones presupuestarias no justificadas 4. Empleados con aumentos reiterados 5. Modificaciones salariales realizadas por el mismo usuario del sistema, fuera del proceso autorizado
A17: 16 | B17: ROTR-RRHH-16 | C17: RRHH | E17: Otros Riesgos | F17: Contratacion | H17: Adjudicación de contratos incumpliendo requisitos de transparencia, competencia y aprobación interna. | I17: Descripción: Posibilidad de que funcionarios manipulen o direccionen procesos de contratación institucional, omitiendo o alterando los procedimientos internos establecidos, con el fin de favorecer a determinados proveedores, lo que podría generar actos de corrupción, sobrevaloración contractual y eventual utilización del contrato como mecanismo para desviar o legitimar recursos de origen ilícito. Causas: Concentración de poder en un solo funcionario, Falta de comité evaluador independiente, Debilidad en el proceso operativo y en la supervision falta de debida diligencia con el proveedor Conflictos de interés no declarados Efecto: Pérdidas perdidas económicas x contrataciones excesivas o con remuneracion superior a lo permitido o presupuestado | J17: 2 | K17: 5 | L17: =IF((Matriz_Riesgos[[#This Row],[Frecuencia]]+Matriz_Riesgos[[#This Row],[Impacto]]-1)=-1,"",Matriz_Riesgos[[#This Row],[Frecuencia]]+Matriz_Riesgos[[#This Row],[Impacto]]-1) -> 6 | M17: =IFERROR(VLOOKUP(Matriz_Riesgos[[#This Row],[Valor del Riesgo Inherente]],t_nivel_riesgo[],2,FALSE), "") -> Riesgo Alto | N17: RRHH/MAI | O17: Todos | P17: Fraude/Corrupcion/Reputacional/legal/LAFT | T17: Comité de selección de RRHH | AG17: =IF(AND(T17="",X17="",AB17=""),"",('Otras Tablas'!$B$3*IF(W17="",0,W17)+'Otras Tablas'!$B$4*IF(AA17="",0,AA17)+'Otras Tablas'!$B$5*IF(AE17="",0,AE17))) | AH17: =IF(Matriz_Riesgos[[#This Row],[Riesgo Inherente]]="","",Matriz_Riesgos[[#This Row],[Riesgo Inherente]]) -> Adjudicación de contratos incumpliendo requisitos de transparencia, competencia y aprobación interna. | AI17: =IFERROR(IF(OR(Matriz_Riesgos[[#This Row],[Frecuencia]]="",Matriz_Riesgos[[#This Row],[Impacto]]="",Matriz_Riesgos[[#This Row],[Valor del Riesgo Inherente]]="",Matriz_Riesgos[[#This Row],[Valor del Riesgo Residual]]=""),"",IF(Matriz_Riesgos[[#This Row],[Valor del Riesgo Inherente]]=Matriz_Riesgos[[#This Row],[Valor del Riesgo Residual]],Matriz_Riesgos[[#This Row],[Frecuencia]],MIN(Matriz_Riesgos[[#This Row],[Tope F (AUX)]], Matriz_Riesgos[[#This Row],[F_base (AUX)]]+Matriz_Riesgos[[#This Row],[Inc_F (AUX)]]))),"") -> 2 | AJ17: =IFERROR(IF(OR(Matriz_Riesgos[[#This Row],[Frecuencia]]="",Matriz_Riesgos[[#This Row],[Impacto]]="",Matriz_Riesgos[[#This Row],[Valor del Riesgo Inherente]]="",Matriz_Riesgos[[#This Row],[Valor del Riesgo Residual]]=""),"",IF(Matriz_Riesgos[[#This Row],[Valor del Riesgo Inherente]]=Matriz_Riesgos[[#This Row],[Valor del Riesgo Residual]],Matriz_Riesgos[[#This Row],[Impacto]],MIN(Matriz_Riesgos[[#This Row],[Tope I (AUX)]], Matriz_Riesgos[[#This Row],[I_base (AUX)]]+Matriz_Riesgos[[#This Row],[Inc_I (AUX)]]))),"") -> 5 | AK17: =IFERROR(ROUND(MAX(1,Matriz_Riesgos[[#This Row],[Valor del Riesgo Inherente]]*(1 - Matriz_Riesgos[[#This Row],[Efectividad Total Ponderada de los Controles]])),0), "") -> 6 | AL17: =IFERROR(VLOOKUP(Matriz_Riesgos[[#This Row],[Valor del Riesgo Residual]],t_nivel_riesgo[],2,FALSE),"") -> Riesgo Alto | AM17: Evitar | AX17: =IFERROR((1-Matriz_Riesgos[[#This Row],[Efectividad Total Ponderada de los Controles]])*Matriz_Riesgos[[#This Row],[Frecuencia]],"") -> 2 | AY17: =IFERROR((1-Matriz_Riesgos[[#This Row],[Efectividad Total Ponderada de los Controles]])*Matriz_Riesgos[[#This Row],[Impacto]],"") -> 5 | AZ17: =IFERROR(Matriz_Riesgos[[#This Row],[Valor del Riesgo Residual]] + 1, "") -> 7 | BA17: =IFERROR(MAX(1, ROUNDDOWN(Matriz_Riesgos[[#This Row],[Frecuencia Residual (AUX)]],0)),"") -> 2 | BB17: =IFERROR(MAX(1, ROUNDDOWN(Matriz_Riesgos[[#This Row],[Impacto Residual (AUX)]],0)),"") -> 5 | BC17: =IF(Matriz_Riesgos[[#This Row],[Frecuencia]]="","",Matriz_Riesgos[[#This Row],[Frecuencia]]) -> 2 | BD17: =IF(Matriz_Riesgos[[#This Row],[Impacto]]="","",Matriz_Riesgos[[#This Row],[Impacto]]) -> 5 | BE17: =IF(OR(Matriz_Riesgos[[#This Row],[Tope F (AUX)]]="",Matriz_Riesgos[[#This Row],[F_base (AUX)]]=""),"",MAX(0,Matriz_Riesgos[[#This Row],[Tope F (AUX)]]-Matriz_Riesgos[[#This Row],[F_base (AUX)]])) -> 0 | BF17: =IF(OR(Matriz_Riesgos[[#This Row],[Tope I (AUX)]]="",Matriz_Riesgos[[#This Row],[I_base (AUX)]]=""),"",MAX(0,Matriz_Riesgos[[#This Row],[Tope I (AUX)]]-Matriz_Riesgos[[#This Row],[I_base (AUX)]])) -> 0 | BG17: =IF(OR(Matriz_Riesgos[[#This Row],[Suma Residual redondeada (AUX)]]="",Matriz_Riesgos[[#This Row],[F_base (AUX)]]="",Matriz_Riesgos[[#This Row],[I_base (AUX)]]=""),"",MAX(0,Matriz_Riesgos[[#This Row],[Suma Residual redondeada (AUX)]]-(Matriz_Riesgos[[#This Row],[F_base (AUX)]]+Matriz_Riesgos[[#This Row],[I_base (AUX)]]))) -> 0 | BH17: =IF(OR(Matriz_Riesgos[[#This Row],[Impacto Residual (AUX)]]="",Matriz_Riesgos[[#This Row],[Frecuencia Residual (AUX)]]=""),"",IF(MOD(Matriz_Riesgos[[#This Row],[Impacto Residual (AUX)]],1) > MOD(Matriz_Riesgos[[#This Row],[Frecuencia Residual (AUX)]],1),1,IF(MOD(Matriz_Riesgos[[#This Row],[Impacto Residual (AUX)]],1) = MOD(Matriz_Riesgos[[#This Row],[Frecuencia Residual (AUX)]],1),1,0))) -> 1 | BI17: =IF(OR(Matriz_Riesgos[[#This Row],[Resto (AUX)]]="",Matriz_Riesgos[[#This Row],[Capacidad I (AUX)]]="",Matriz_Riesgos[[#This Row],[Capacidad F (AUX)]]=""),"",IF(Matriz_Riesgos[[#This Row],[Resto (AUX)]]=0, 0,IF(Matriz_Riesgos[[#This Row],[Resto (AUX)]]=1,MIN(Matriz_Riesgos[[#This Row],[Capacidad I (AUX)]], IF(OR(Matriz_Riesgos[[#This Row],[Prefiere I (AUX)]]=1,Matriz_Riesgos[[#This Row],[Capacidad F (AUX)]]=0),1,0)),MIN(Matriz_Riesgos[[#This Row],[Capacidad I (AUX)]],IF(Matriz_Riesgos[[#This Row],[Prefiere I (AUX)]]=1,1 + IF(Matriz_Riesgos[[#This Row],[Capacidad F (AUX)]]>0,0,1),IF(Matriz_Riesgos[[#This Row],[Capacidad F (AUX)]]>0,1,2)))))) -> 0 | BJ17: =IF(OR(Matriz_Riesgos[[#This Row],[Resto (AUX)]]="",Matriz_Riesgos[[#This Row],[Capacidad F (AUX)]]="",Matriz_Riesgos[[#This Row],[Inc_I (AUX)]]=""),"",MIN(Matriz_Riesgos[[#This Row],[Capacidad F (AUX)]], MAX(0,Matriz_Riesgos[[#This Row],[Resto (AUX)]]-Matriz_Riesgos[[#This Row],[Inc_I (AUX)]]))) -> 0 | BK17: =IFERROR(MAX(ROUND(Matriz_Riesgos[[#This Row],[Frecuencia Residual (AUX)]]+Matriz_Riesgos[[#This Row],[Impacto Residual (AUX)]]-1+Matriz_Riesgos[[#This Row],[Efectividad Total Ponderada de los Controles]],0),1),"") -> 6 | BL17: =IFERROR(Matriz_Riesgos[[#This Row],[Valor del Riesgo Residual]]-Matriz_Riesgos[[#This Row],[Valor del Riesgo Residual (AUX)]],"") -> 0 | BM17: =IFERROR(Matriz_Riesgos[[#This Row],[Frecuencia Residual]]+Matriz_Riesgos[[#This Row],[Impacto Residual]]-1,"") -> 6 | BN17: =IFERROR(Matriz_Riesgos[[#This Row],[Valor del Riesgo Residual]]-Matriz_Riesgos[[#This Row],[VRR 2]],"") -> 0 | BO17: =IFERROR(Matriz_Riesgos[[#This Row],[Frecuencia]]-Matriz_Riesgos[[#This Row],[Frecuencia Residual]],"") -> 0 | BP17: =IFERROR(Matriz_Riesgos[[#This Row],[Impacto]]-Matriz_Riesgos[[#This Row],[Impacto Residual]],"") -> 0 | BQ17: =IFERROR(Matriz_Riesgos[[#This Row],[Valor del Riesgo Inherente]]-Matriz_Riesgos[[#This Row],[Valor del Riesgo Residual]],"") -> 0 | BR17: 1. Pliegos de condiciones con requisitos restrictivos o direccionados 2. Único oferente recurrente 3. Proveedores recién constituidos que ganan contratos relevantes 4. Fraccionamiento de contratos para evitar procesos formales 5. Modificaciones contractuales frecuentes que incrementan el valor 6. Relación personal entre funcionario y proveedor
A18: 17 | B18: ROTR-PATRONALCOMP-17 | C18: Patronal/compras | E18: Otros Riesgos | F18: Identificacion de Proveedores | H18: Adjudicación y contratación con proveedor inexistente, ficticio, inhabilitado o sin capacidad real para prestar el servicio. | I18: Descripción: Posibilidad de que el IHSS celebre procesos de contratación con proveedores que no cuenten con respaldo documental completo, existencia legal verificada o capacidad técnica y financiera comprobada, debido a deficiencias en los procedimientos de debida diligencia y control documental, lo cual puede facilitar actos de corrupción, fraude o simulación contractual. Causas: Ausencia de procedimiento formal de debida diligencia a proveedores, Falta de checklist obligatorio documental, Sistemas no integrados de registro de proveedores Negligencia en revisión documental. Colusión interna, Falta de validación con registros públicos, Alta carga operativa en unidad de compras, Procesos de emergencia o compras directas, sin suficiente respaldo o justificacion Efecto: Pérdida directa de recursos institucionales, procesos penales por fraude o corrupción, señalamientos mediáticos, Pérdida de confianza pública, interrupcion de servicios | J18: 4 | K18: 5 | L18: =IF((Matriz_Riesgos[[#This Row],[Frecuencia]]+Matriz_Riesgos[[#This Row],[Impacto]]-1)=-1,"",Matriz_Riesgos[[#This Row],[Frecuencia]]+Matriz_Riesgos[[#This Row],[Impacto]]-1) -> 8 | M18: =IFERROR(VLOOKUP(Matriz_Riesgos[[#This Row],[Valor del Riesgo Inherente]],t_nivel_riesgo[],2,FALSE), "") -> Riesgo Intolerable | N18: Compras/Control Patronal/GAYF/Auditoria Interna/Asesoria legal | O18: Todos | P18: Fraude/LAFT/Reputacional/legal | T18: 1. Procedimiento formal de debida diligencia a proveedores. 2. Checklist obligatorio de requisitos legales y financieros 3. Cláusulas contractuales anticorrupción. 4. Registro unico institucional de proveedores 5. Segregacion de funciones claramente definidas. | X18: 1. Auditoria periodica de expedientes contractuales. 2. Verificación aleatoria de existencia física 3. Monitoreo de proveedores recien creados 4. Revisión posterior a pagos relevantes | AB18: 1. Suspension inmediata del contrato, ante hechos concretos 2. Recuperación de pagos indebidos 3. Denuncia ante el ministerio Publico 4. Inhabilitación del proveedor. 5. Sancion disciplinaria a funcionario o empleados responsables del o los procesos 6. Revisión integral de contratos adjudicados por el mismo evaluador | AG18: =IF(AND(T18="",X18="",AB18=""),"",('Otras Tablas'!$B$3*IF(W18="",0,W18)+'Otras Tablas'!$B$4*IF(AA18="",0,AA18)+'Otras Tablas'!$B$5*IF(AE18="",0,AE18))) | AH18: =IF(Matriz_Riesgos[[#This Row],[Riesgo Inherente]]="","",Matriz_Riesgos[[#This Row],[Riesgo Inherente]]) -> Adjudicación y contratación con proveedor inexistente, ficticio, inhabilitado o sin capacidad real para prestar el servicio. | AI18: =IFERROR(IF(OR(Matriz_Riesgos[[#This Row],[Frecuencia]]="",Matriz_Riesgos[[#This Row],[Impacto]]="",Matriz_Riesgos[[#This Row],[Valor del Riesgo Inherente]]="",Matriz_Riesgos[[#This Row],[Valor del Riesgo Residual]]=""),"",IF(Matriz_Riesgos[[#This Row],[Valor del Riesgo Inherente]]=Matriz_Riesgos[[#This Row],[Valor del Riesgo Residual]],Matriz_Riesgos[[#This Row],[Frecuencia]],MIN(Matriz_Riesgos[[#This Row],[Tope F (AUX)]], Matriz_Riesgos[[#This Row],[F_base (AUX)]]+Matriz_Riesgos[[#This Row],[Inc_F (AUX)]]))),"") -> 4 | AJ18: =IFERROR(IF(OR(Matriz_Riesgos[[#This Row],[Frecuencia]]="",Matriz_Riesgos[[#This Row],[Impacto]]="",Matriz_Riesgos[[#This Row],[Valor del Riesgo Inherente]]="",Matriz_Riesgos[[#This Row],[Valor del Riesgo Residual]]=""),"",IF(Matriz_Riesgos[[#This Row],[Valor del Riesgo Inherente]]=Matriz_Riesgos[[#This Row],[Valor del Riesgo Residual]],Matriz_Riesgos[[#This Row],[Impacto]],MIN(Matriz_Riesgos[[#This Row],[Tope I (AUX)]], Matriz_Riesgos[[#This Row],[I_base (AUX)]]+Matriz_Riesgos[[#This Row],[Inc_I (AUX)]]))),"") -> 5 | AK18: =IFERROR(ROUND(MAX(1,Matriz_Riesgos[[#This Row],[Valor del Riesgo Inherente]]*(1 - Matriz_Riesgos[[#This Row],[Efectividad Total Ponderada de los Controles]])),0), "") -> 8 | AL18: =IFERROR(VLOOKUP(Matriz_Riesgos[[#This Row],[Valor del Riesgo Residual]],t_nivel_riesgo[],2,FALSE),"") -> Riesgo Intolerable | AM18: Evitar | AX18: =IFERROR((1-Matriz_Riesgos[[#This Row],[Efectividad Total Ponderada de los Controles]])*Matriz_Riesgos[[#This Row],[Frecuencia]],"") -> 4 | AY18: =IFERROR((1-Matriz_Riesgos[[#This Row],[Efectividad Total Ponderada de los Controles]])*Matriz_Riesgos[[#This Row],[Impacto]],"") -> 5 | AZ18: =IFERROR(Matriz_Riesgos[[#This Row],[Valor del Riesgo Residual]] + 1, "") -> 9 | BA18: =IFERROR(MAX(1, ROUNDDOWN(Matriz_Riesgos[[#This Row],[Frecuencia Residual (AUX)]],0)),"") -> 4 | BB18: =IFERROR(MAX(1, ROUNDDOWN(Matriz_Riesgos[[#This Row],[Impacto Residual (AUX)]],0)),"") -> 5 | BC18: =IF(Matriz_Riesgos[[#This Row],[Frecuencia]]="","",Matriz_Riesgos[[#This Row],[Frecuencia]]) -> 4 | BD18: =IF(Matriz_Riesgos[[#This Row],[Impacto]]="","",Matriz_Riesgos[[#This Row],[Impacto]]) -> 5 | BE18: =IF(OR(Matriz_Riesgos[[#This Row],[Tope F (AUX)]]="",Matriz_Riesgos[[#This Row],[F_base (AUX)]]=""),"",MAX(0,Matriz_Riesgos[[#This Row],[Tope F (AUX)]]-Matriz_Riesgos[[#This Row],[F_base (AUX)]])) -> 0 | BF18: =IF(OR(Matriz_Riesgos[[#This Row],[Tope I (AUX)]]="",Matriz_Riesgos[[#This Row],[I_base (AUX)]]=""),"",MAX(0,Matriz_Riesgos[[#This Row],[Tope I (AUX)]]-Matriz_Riesgos[[#This Row],[I_base (AUX)]])) -> 0 | BG18: =IF(OR(Matriz_Riesgos[[#This Row],[Suma Residual redondeada (AUX)]]="",Matriz_Riesgos[[#This Row],[F_base (AUX)]]="",Matriz_Riesgos[[#This Row],[I_base (AUX)]]=""),"",MAX(0,Matriz_Riesgos[[#This Row],[Suma Residual redondeada (AUX)]]-(Matriz_Riesgos[[#This Row],[F_base (AUX)]]+Matriz_Riesgos[[#This Row],[I_base (AUX)]]))) -> 0 | BH18: =IF(OR(Matriz_Riesgos[[#This Row],[Impacto Residual (AUX)]]="",Matriz_Riesgos[[#This Row],[Frecuencia Residual (AUX)]]=""),"",IF(MOD(Matriz_Riesgos[[#This Row],[Impacto Residual (AUX)]],1) > MOD(Matriz_Riesgos[[#This Row],[Frecuencia Residual (AUX)]],1),1,IF(MOD(Matriz_Riesgos[[#This Row],[Impacto Residual (AUX)]],1) = MOD(Matriz_Riesgos[[#This Row],[Frecuencia Residual (AUX)]],1),1,0))) -> 1 | BI18: =IF(OR(Matriz_Riesgos[[#This Row],[Resto (AUX)]]="",Matriz_Riesgos[[#This Row],[Capacidad I (AUX)]]="",Matriz_Riesgos[[#This Row],[Capacidad F (AUX)]]=""),"",IF(Matriz_Riesgos[[#This Row],[Resto (AUX)]]=0, 0,IF(Matriz_Riesgos[[#This Row],[Resto (AUX)]]=1,MIN(Matriz_Riesgos[[#This Row],[Capacidad I (AUX)]], IF(OR(Matriz_Riesgos[[#This Row],[Prefiere I (AUX)]]=1,Matriz_Riesgos[[#This Row],[Capacidad F (AUX)]]=0),1,0)),MIN(Matriz_Riesgos[[#This Row],[Capacidad I (AUX)]],IF(Matriz_Riesgos[[#This Row],[Prefiere I (AUX)]]=1,1 + IF(Matriz_Riesgos[[#This Row],[Capacidad F (AUX)]]>0,0,1),IF(Matriz_Riesgos[[#This Row],[Capacidad F (AUX)]]>0,1,2)))))) -> 0 | BJ18: =IF(OR(Matriz_Riesgos[[#This Row],[Resto (AUX)]]="",Matriz_Riesgos[[#This Row],[Capacidad F (AUX)]]="",Matriz_Riesgos[[#This Row],[Inc_I (AUX)]]=""),"",MIN(Matriz_Riesgos[[#This Row],[Capacidad F (AUX)]], MAX(0,Matriz_Riesgos[[#This Row],[Resto (AUX)]]-Matriz_Riesgos[[#This Row],[Inc_I (AUX)]]))) -> 0 | BK18: =IFERROR(MAX(ROUND(Matriz_Riesgos[[#This Row],[Frecuencia Residual (AUX)]]+Matriz_Riesgos[[#This Row],[Impacto Residual (AUX)]]-1+Matriz_Riesgos[[#This Row],[Efectividad Total Ponderada de los Controles]],0),1),"") -> 8 | BL18: =IFERROR(Matriz_Riesgos[[#This Row],[Valor del Riesgo Residual]]-Matriz_Riesgos[[#This Row],[Valor del Riesgo Residual (AUX)]],"") -> 0 | BM18: =IFERROR(Matriz_Riesgos[[#This Row],[Frecuencia Residual]]+Matriz_Riesgos[[#This Row],[Impacto Residual]]-1,"") -> 8 | BN18: =IFERROR(Matriz_Riesgos[[#This Row],[Valor del Riesgo Residual]]-Matriz_Riesgos[[#This Row],[VRR 2]],"") -> 0 | BO18: =IFERROR(Matriz_Riesgos[[#This Row],[Frecuencia]]-Matriz_Riesgos[[#This Row],[Frecuencia Residual]],"") -> 0 | BP18: =IFERROR(Matriz_Riesgos[[#This Row],[Impacto]]-Matriz_Riesgos[[#This Row],[Impacto Residual]],"") -> 0 | BQ18: =IFERROR(Matriz_Riesgos[[#This Row],[Valor del Riesgo Inherente]]-Matriz_Riesgos[[#This Row],[Valor del Riesgo Residual]],"") -> 0
A19: 18 | B19: ROTR-COMPRAS-18 | C19: Compras | E19: Otros Riesgos | F19: Ejecucion Contractual | H19: Riesgo de pago indebido a proveedores por bienes o servicios no recibidos o no ejecutados | I19: Descripción: Posibilidad de que el IHSS realice pagos a proveedores por bienes no entregados, servicios no ejecutados, servicios médicos no prestados o prestaciones sobrevaloradas, como consecuencia de debilidades en los controles de recepción, validación, supervisión contractual o posibles actos de colusión entre funcionarios y terceros. Causas: Debilidad en la segregación de funciones, Ausencia de controles físicos de recepción. Colusión entre funcionario y proveedor. Deficiente administración contractual. Cultura organizacional débil en control interno. Presión por ejecución presupuestaria. Efecto: Pérdidas económicas/riesgo reputacional/Interrupcion en prestacion de servicios medicos/sanciones administrativas y penales | J19: 3 | K19: 5 | L19: =IF((Matriz_Riesgos[[#This Row],[Frecuencia]]+Matriz_Riesgos[[#This Row],[Impacto]]-1)=-1,"",Matriz_Riesgos[[#This Row],[Frecuencia]]+Matriz_Riesgos[[#This Row],[Impacto]]-1) -> 7 | M19: =IFERROR(VLOOKUP(Matriz_Riesgos[[#This Row],[Valor del Riesgo Inherente]],t_nivel_riesgo[],2,FALSE), "") -> Riesgo Alto | N19: MAI/Compras/GAYF/Auditoria | O19: Todos | P19: Fraude/Corrupcion/legal, operativo, reputacional, incumplimiento normativo, LAFT | T19: 1. politica formal de contratacion y pagos 2. Segregacion de funciones obligatoria (incluye solicitud, aprobacion, recepcion, contabilizacion y pago) 3.- parametrizacion en el sistema de forma que no hayan pagos que ya hayan sido ejecutados 4. Registro y debida diligencia del proveedor 5. Acta formal de Recepcion 6.- Declaracion anual de conflicto de interes 7.- Limites de autorizacion escalonadas por orden jerarquico y por montos 8.- Incorporacion en los contratos de clausulas anticorrupcion y penalidades contractuales (Terminacion anticipada, penalizacion por incumplimiento, obligacion de devolucion d epagos indebidos, entre otros) | X19: 1.- Conciliacion periodica de inventario fisico vrs sistema 2.- Auditorias internas, programadas y sorpresivas 3.- Cruces automatizados de facturacion (identificacion de facturas duplicadas, pagos fraccionados, concentracion excesiva de un proveedor) 4. Indicadores de alerta (incremento inusual de pagos, variacion significativa de precios, modificaciones contractuales frecuentes) 5. Canal de denucnias confidencial, como mecanismo anonimo para reportar irregularidades | AB19: 1.- Suspension inmediata del pago del proveedor 2. Investigacion administrativa formal (Auditoria) 3.- Terminacion anticipada del contrato por incumplimiento 4. Recuperacion de fondos 5.- Denuncia ante autoridades competentes 6.- Inclusion en lista de proveedores inhabilitados | AG19: =IF(AND(T19="",X19="",AB19=""),"",('Otras Tablas'!$B$3*IF(W19="",0,W19)+'Otras Tablas'!$B$4*IF(AA19="",0,AA19)+'Otras Tablas'!$B$5*IF(AE19="",0,AE19))) | AH19: =IF(Matriz_Riesgos[[#This Row],[Riesgo Inherente]]="","",Matriz_Riesgos[[#This Row],[Riesgo Inherente]]) -> Riesgo de pago indebido a proveedores por bienes o servicios no recibidos o no ejecutados | AI19: =IFERROR(IF(OR(Matriz_Riesgos[[#This Row],[Frecuencia]]="",Matriz_Riesgos[[#This Row],[Impacto]]="",Matriz_Riesgos[[#This Row],[Valor del Riesgo Inherente]]="",Matriz_Riesgos[[#This Row],[Valor del Riesgo Residual]]=""),"",IF(Matriz_Riesgos[[#This Row],[Valor del Riesgo Inherente]]=Matriz_Riesgos[[#This Row],[Valor del Riesgo Residual]],Matriz_Riesgos[[#This Row],[Frecuencia]],MIN(Matriz_Riesgos[[#This Row],[Tope F (AUX)]], Matriz_Riesgos[[#This Row],[F_base (AUX)]]+Matriz_Riesgos[[#This Row],[Inc_F (AUX)]]))),"") -> 3 | AJ19: =IFERROR(IF(OR(Matriz_Riesgos[[#This Row],[Frecuencia]]="",Matriz_Riesgos[[#This Row],[Impacto]]="",Matriz_Riesgos[[#This Row],[Valor del Riesgo Inherente]]="",Matriz_Riesgos[[#This Row],[Valor del Riesgo Residual]]=""),"",IF(Matriz_Riesgos[[#This Row],[Valor del Riesgo Inherente]]=Matriz_Riesgos[[#This Row],[Valor del Riesgo Residual]],Matriz_Riesgos[[#This Row],[Impacto]],MIN(Matriz_Riesgos[[#This Row],[Tope I (AUX)]], Matriz_Riesgos[[#This Row],[I_base (AUX)]]+Matriz_Riesgos[[#This Row],[Inc_I (AUX)]]))),"") -> 5 | AK19: =IFERROR(ROUND(MAX(1,Matriz_Riesgos[[#This Row],[Valor del Riesgo Inherente]]*(1 - Matriz_Riesgos[[#This Row],[Efectividad Total Ponderada de los Controles]])),0), "") -> 7 | AL19: =IFERROR(VLOOKUP(Matriz_Riesgos[[#This Row],[Valor del Riesgo Residual]],t_nivel_riesgo[],2,FALSE),"") -> Riesgo Alto | AM19: Evitar | AX19: =IFERROR((1-Matriz_Riesgos[[#This Row],[Efectividad Total Ponderada de los Controles]])*Matriz_Riesgos[[#This Row],[Frecuencia]],"") -> 3 | AY19: =IFERROR((1-Matriz_Riesgos[[#This Row],[Efectividad Total Ponderada de los Controles]])*Matriz_Riesgos[[#This Row],[Impacto]],"") -> 5 | AZ19: =IFERROR(Matriz_Riesgos[[#This Row],[Valor del Riesgo Residual]] + 1, "") -> 8 | BA19: =IFERROR(MAX(1, ROUNDDOWN(Matriz_Riesgos[[#This Row],[Frecuencia Residual (AUX)]],0)),"") -> 3 | BB19: =IFERROR(MAX(1, ROUNDDOWN(Matriz_Riesgos[[#This Row],[Impacto Residual (AUX)]],0)),"") -> 5 | BC19: =IF(Matriz_Riesgos[[#This Row],[Frecuencia]]="","",Matriz_Riesgos[[#This Row],[Frecuencia]]) -> 3 | BD19: =IF(Matriz_Riesgos[[#This Row],[Impacto]]="","",Matriz_Riesgos[[#This Row],[Impacto]]) -> 5 | BE19: =IF(OR(Matriz_Riesgos[[#This Row],[Tope F (AUX)]]="",Matriz_Riesgos[[#This Row],[F_base (AUX)]]=""),"",MAX(0,Matriz_Riesgos[[#This Row],[Tope F (AUX)]]-Matriz_Riesgos[[#This Row],[F_base (AUX)]])) -> 0 | BF19: =IF(OR(Matriz_Riesgos[[#This Row],[Tope I (AUX)]]="",Matriz_Riesgos[[#This Row],[I_base (AUX)]]=""),"",MAX(0,Matriz_Riesgos[[#This Row],[Tope I (AUX)]]-Matriz_Riesgos[[#This Row],[I_base (AUX)]])) -> 0 | BG19: =IF(OR(Matriz_Riesgos[[#This Row],[Suma Residual redondeada (AUX)]]="",Matriz_Riesgos[[#This Row],[F_base (AUX)]]="",Matriz_Riesgos[[#This Row],[I_base (AUX)]]=""),"",MAX(0,Matriz_Riesgos[[#This Row],[Suma Residual redondeada (AUX)]]-(Matriz_Riesgos[[#This Row],[F_base (AUX)]]+Matriz_Riesgos[[#This Row],[I_base (AUX)]]))) -> 0 | BH19: =IF(OR(Matriz_Riesgos[[#This Row],[Impacto Residual (AUX)]]="",Matriz_Riesgos[[#This Row],[Frecuencia Residual (AUX)]]=""),"",IF(MOD(Matriz_Riesgos[[#This Row],[Impacto Residual (AUX)]],1) > MOD(Matriz_Riesgos[[#This Row],[Frecuencia Residual (AUX)]],1),1,IF(MOD(Matriz_Riesgos[[#This Row],[Impacto Residual (AUX)]],1) = MOD(Matriz_Riesgos[[#This Row],[Frecuencia Residual (AUX)]],1),1,0))) -> 1 | BI19: =IF(OR(Matriz_Riesgos[[#This Row],[Resto (AUX)]]="",Matriz_Riesgos[[#This Row],[Capacidad I (AUX)]]="",Matriz_Riesgos[[#This Row],[Capacidad F (AUX)]]=""),"",IF(Matriz_Riesgos[[#This Row],[Resto (AUX)]]=0, 0,IF(Matriz_Riesgos[[#This Row],[Resto (AUX)]]=1,MIN(Matriz_Riesgos[[#This Row],[Capacidad I (AUX)]], IF(OR(Matriz_Riesgos[[#This Row],[Prefiere I (AUX)]]=1,Matriz_Riesgos[[#This Row],[Capacidad F (AUX)]]=0),1,0)),MIN(Matriz_Riesgos[[#This Row],[Capacidad I (AUX)]],IF(Matriz_Riesgos[[#This Row],[Prefiere I (AUX)]]=1,1 + IF(Matriz_Riesgos[[#This Row],[Capacidad F (AUX)]]>0,0,1),IF(Matriz_Riesgos[[#This Row],[Capacidad F (AUX)]]>0,1,2)))))) -> 0 | BJ19: =IF(OR(Matriz_Riesgos[[#This Row],[Resto (AUX)]]="",Matriz_Riesgos[[#This Row],[Capacidad F (AUX)]]="",Matriz_Riesgos[[#This Row],[Inc_I (AUX)]]=""),"",MIN(Matriz_Riesgos[[#This Row],[Capacidad F (AUX)]], MAX(0,Matriz_Riesgos[[#This Row],[Resto (AUX)]]-Matriz_Riesgos[[#This Row],[Inc_I (AUX)]]))) -> 0 | BK19: =IFERROR(MAX(ROUND(Matriz_Riesgos[[#This Row],[Frecuencia Residual (AUX)]]+Matriz_Riesgos[[#This Row],[Impacto Residual (AUX)]]-1+Matriz_Riesgos[[#This Row],[Efectividad Total Ponderada de los Controles]],0),1),"") -> 7 | BL19: =IFERROR(Matriz_Riesgos[[#This Row],[Valor del Riesgo Residual]]-Matriz_Riesgos[[#This Row],[Valor del Riesgo Residual (AUX)]],"") -> 0 | BM19: =IFERROR(Matriz_Riesgos[[#This Row],[Frecuencia Residual]]+Matriz_Riesgos[[#This Row],[Impacto Residual]]-1,"") -> 7 | BN19: =IFERROR(Matriz_Riesgos[[#This Row],[Valor del Riesgo Residual]]-Matriz_Riesgos[[#This Row],[VRR 2]],"") -> 0 | BO19: =IFERROR(Matriz_Riesgos[[#This Row],[Frecuencia]]-Matriz_Riesgos[[#This Row],[Frecuencia Residual]],"") -> 0 | BP19: =IFERROR(Matriz_Riesgos[[#This Row],[Impacto]]-Matriz_Riesgos[[#This Row],[Impacto Residual]],"") -> 0 | BQ19: =IFERROR(Matriz_Riesgos[[#This Row],[Valor del Riesgo Inherente]]-Matriz_Riesgos[[#This Row],[Valor del Riesgo Residual]],"") -> 0 | BR19: 1. Facturación recurrente con conceptos ambiguos. 2. Pagos urgentes fuera de programación normal. 3. proveedores vinculados a funcionarios 4. Órdenes de compra posteriores a la factura 5. Concentración excesiva en un solo proveedor. 6. Diferencia entre inventario fisico vrs sistema
A20: 19 | B20: ROTR-RRHHTESORERI-19 | C20: RRHH/Tesoreria | E20: Otros Riesgos | F20: Pago Planilla | H20: Riesgo de pagos indebidos a través de planilla a una misma cuenta bancaria | I20: Descripción: Posibilidad de que se procesen pagos de salarios, beneficios o prestaciones laborales a múltiples empleados utilizando una misma cuenta bancaria, como resultado de la creación de empleados ficticios, manipulación indebida de datos bancarios, colusión interna o debilidades en los controles de validación y actualización de información en el sistema de planillas. Causas: 1. Ausencia de controles automáticos que detecten cuentas duplicadas. 2. Debilidad en la segregación de funciones en RRHH. 3. Accesos inadecuados al sistema de nómina 4. Colusión entre personal de RRHH y Tesorería o terceros Efecto: Pérdidas económicas/riesgo reputacional | J20: 4 | K20: 4 | L20: =IF((Matriz_Riesgos[[#This Row],[Frecuencia]]+Matriz_Riesgos[[#This Row],[Impacto]]-1)=-1,"",Matriz_Riesgos[[#This Row],[Frecuencia]]+Matriz_Riesgos[[#This Row],[Impacto]]-1) -> 7 | M20: =IFERROR(VLOOKUP(Matriz_Riesgos[[#This Row],[Valor del Riesgo Inherente]],t_nivel_riesgo[],2,FALSE), "") -> Riesgo Alto | N20: RRHH, Tesoreria, GTIC | O20: Todos | P20: Fraude/Corrupcion/Operativo/Reputacional/Informatico | T20: 1. Segregacion de funciones en planilla 2. Validación automática de cuentas bancarias duplicadas 3. Control de accesos 4. Políticas de actualización con soporte documental | X20: 1. Reportes de cuentas duplicadas 2. Conciliaciones de planilla vs pagos 3. Auditorías internas 4. Monitoreo de cambios en datos maestros | AB20: 1. Bloqueo de pagos 2. Investigación interna 3. Recuperación de fondos 4. Proceso de sanciones disciplinarias | AG20: =IF(AND(T20="",X20="",AB20=""),"",('Otras Tablas'!$B$3*IF(W20="",0,W20)+'Otras Tablas'!$B$4*IF(AA20="",0,AA20)+'Otras Tablas'!$B$5*IF(AE20="",0,AE20))) | AH20: =IF(Matriz_Riesgos[[#This Row],[Riesgo Inherente]]="","",Matriz_Riesgos[[#This Row],[Riesgo Inherente]]) -> Riesgo de pagos indebidos a través de planilla a una misma cuenta bancaria | AI20: =IFERROR(IF(OR(Matriz_Riesgos[[#This Row],[Frecuencia]]="",Matriz_Riesgos[[#This Row],[Impacto]]="",Matriz_Riesgos[[#This Row],[Valor del Riesgo Inherente]]="",Matriz_Riesgos[[#This Row],[Valor del Riesgo Residual]]=""),"",IF(Matriz_Riesgos[[#This Row],[Valor del Riesgo Inherente]]=Matriz_Riesgos[[#This Row],[Valor del Riesgo Residual]],Matriz_Riesgos[[#This Row],[Frecuencia]],MIN(Matriz_Riesgos[[#This Row],[Tope F (AUX)]], Matriz_Riesgos[[#This Row],[F_base (AUX)]]+Matriz_Riesgos[[#This Row],[Inc_F (AUX)]]))),"") -> 4 | AJ20: =IFERROR(IF(OR(Matriz_Riesgos[[#This Row],[Frecuencia]]="",Matriz_Riesgos[[#This Row],[Impacto]]="",Matriz_Riesgos[[#This Row],[Valor del Riesgo Inherente]]="",Matriz_Riesgos[[#This Row],[Valor del Riesgo Residual]]=""),"",IF(Matriz_Riesgos[[#This Row],[Valor del Riesgo Inherente]]=Matriz_Riesgos[[#This Row],[Valor del Riesgo Residual]],Matriz_Riesgos[[#This Row],[Impacto]],MIN(Matriz_Riesgos[[#This Row],[Tope I (AUX)]], Matriz_Riesgos[[#This Row],[I_base (AUX)]]+Matriz_Riesgos[[#This Row],[Inc_I (AUX)]]))),"") -> 4 | AK20: =IFERROR(ROUND(MAX(1,Matriz_Riesgos[[#This Row],[Valor del Riesgo Inherente]]*(1 - Matriz_Riesgos[[#This Row],[Efectividad Total Ponderada de los Controles]])),0), "") -> 7 | AL20: =IFERROR(VLOOKUP(Matriz_Riesgos[[#This Row],[Valor del Riesgo Residual]],t_nivel_riesgo[],2,FALSE),"") -> Riesgo Alto | AM20: Evitar | AX20: =IFERROR((1-Matriz_Riesgos[[#This Row],[Efectividad Total Ponderada de los Controles]])*Matriz_Riesgos[[#This Row],[Frecuencia]],"") -> 4 | AY20: =IFERROR((1-Matriz_Riesgos[[#This Row],[Efectividad Total Ponderada de los Controles]])*Matriz_Riesgos[[#This Row],[Impacto]],"") -> 4 | AZ20: =IFERROR(Matriz_Riesgos[[#This Row],[Valor del Riesgo Residual]] + 1, "") -> 8 | BA20: =IFERROR(MAX(1, ROUNDDOWN(Matriz_Riesgos[[#This Row],[Frecuencia Residual (AUX)]],0)),"") -> 4 | BB20: =IFERROR(MAX(1, ROUNDDOWN(Matriz_Riesgos[[#This Row],[Impacto Residual (AUX)]],0)),"") -> 4 | BC20: =IF(Matriz_Riesgos[[#This Row],[Frecuencia]]="","",Matriz_Riesgos[[#This Row],[Frecuencia]]) -> 4 | BD20: =IF(Matriz_Riesgos[[#This Row],[Impacto]]="","",Matriz_Riesgos[[#This Row],[Impacto]]) -> 4 | BE20: =IF(OR(Matriz_Riesgos[[#This Row],[Tope F (AUX)]]="",Matriz_Riesgos[[#This Row],[F_base (AUX)]]=""),"",MAX(0,Matriz_Riesgos[[#This Row],[Tope F (AUX)]]-Matriz_Riesgos[[#This Row],[F_base (AUX)]])) -> 0 | BF20: =IF(OR(Matriz_Riesgos[[#This Row],[Tope I (AUX)]]="",Matriz_Riesgos[[#This Row],[I_base (AUX)]]=""),"",MAX(0,Matriz_Riesgos[[#This Row],[Tope I (AUX)]]-Matriz_Riesgos[[#This Row],[I_base (AUX)]])) -> 0 | BG20: =IF(OR(Matriz_Riesgos[[#This Row],[Suma Residual redondeada (AUX)]]="",Matriz_Riesgos[[#This Row],[F_base (AUX)]]="",Matriz_Riesgos[[#This Row],[I_base (AUX)]]=""),"",MAX(0,Matriz_Riesgos[[#This Row],[Suma Residual redondeada (AUX)]]-(Matriz_Riesgos[[#This Row],[F_base (AUX)]]+Matriz_Riesgos[[#This Row],[I_base (AUX)]]))) -> 0 | BH20: =IF(OR(Matriz_Riesgos[[#This Row],[Impacto Residual (AUX)]]="",Matriz_Riesgos[[#This Row],[Frecuencia Residual (AUX)]]=""),"",IF(MOD(Matriz_Riesgos[[#This Row],[Impacto Residual (AUX)]],1) > MOD(Matriz_Riesgos[[#This Row],[Frecuencia Residual (AUX)]],1),1,IF(MOD(Matriz_Riesgos[[#This Row],[Impacto Residual (AUX)]],1) = MOD(Matriz_Riesgos[[#This Row],[Frecuencia Residual (AUX)]],1),1,0))) -> 1 | BI20: =IF(OR(Matriz_Riesgos[[#This Row],[Resto (AUX)]]="",Matriz_Riesgos[[#This Row],[Capacidad I (AUX)]]="",Matriz_Riesgos[[#This Row],[Capacidad F (AUX)]]=""),"",IF(Matriz_Riesgos[[#This Row],[Resto (AUX)]]=0, 0,IF(Matriz_Riesgos[[#This Row],[Resto (AUX)]]=1,MIN(Matriz_Riesgos[[#This Row],[Capacidad I (AUX)]], IF(OR(Matriz_Riesgos[[#This Row],[Prefiere I (AUX)]]=1,Matriz_Riesgos[[#This Row],[Capacidad F (AUX)]]=0),1,0)),MIN(Matriz_Riesgos[[#This Row],[Capacidad I (AUX)]],IF(Matriz_Riesgos[[#This Row],[Prefiere I (AUX)]]=1,1 + IF(Matriz_Riesgos[[#This Row],[Capacidad F (AUX)]]>0,0,1),IF(Matriz_Riesgos[[#This Row],[Capacidad F (AUX)]]>0,1,2)))))) -> 0 | BJ20: =IF(OR(Matriz_Riesgos[[#This Row],[Resto (AUX)]]="",Matriz_Riesgos[[#This Row],[Capacidad F (AUX)]]="",Matriz_Riesgos[[#This Row],[Inc_I (AUX)]]=""),"",MIN(Matriz_Riesgos[[#This Row],[Capacidad F (AUX)]], MAX(0,Matriz_Riesgos[[#This Row],[Resto (AUX)]]-Matriz_Riesgos[[#This Row],[Inc_I (AUX)]]))) -> 0 | BK20: =IFERROR(MAX(ROUND(Matriz_Riesgos[[#This Row],[Frecuencia Residual (AUX)]]+Matriz_Riesgos[[#This Row],[Impacto Residual (AUX)]]-1+Matriz_Riesgos[[#This Row],[Efectividad Total Ponderada de los Controles]],0),1),"") -> 7 | BL20: =IFERROR(Matriz_Riesgos[[#This Row],[Valor del Riesgo Residual]]-Matriz_Riesgos[[#This Row],[Valor del Riesgo Residual (AUX)]],"") -> 0 | BM20: =IFERROR(Matriz_Riesgos[[#This Row],[Frecuencia Residual]]+Matriz_Riesgos[[#This Row],[Impacto Residual]]-1,"") -> 7 | BN20: =IFERROR(Matriz_Riesgos[[#This Row],[Valor del Riesgo Residual]]-Matriz_Riesgos[[#This Row],[VRR 2]],"") -> 0 | BO20: =IFERROR(Matriz_Riesgos[[#This Row],[Frecuencia]]-Matriz_Riesgos[[#This Row],[Frecuencia Residual]],"") -> 0 | BP20: =IFERROR(Matriz_Riesgos[[#This Row],[Impacto]]-Matriz_Riesgos[[#This Row],[Impacto Residual]],"") -> 0 | BQ20: =IFERROR(Matriz_Riesgos[[#This Row],[Valor del Riesgo Inherente]]-Matriz_Riesgos[[#This Row],[Valor del Riesgo Residual]],"") -> 0 | BR20: 1.- Cuentas bancarias asignadas a mas de un empleado 2. Cuentas bancarias modificadas poco antes de pago de planilla 3. Conciliacion bancaria (planilla) no concuerda con presupuesto autorizado 4. Empleados sin registro biometrico de asistencia laboral 5. Empleados con expediente incompleto o inexistente 6. Tiempo de deteccion de casos
A21: 20 | B21: ROTR-COMPRASTESOR-20 | C21: Compras/Tesoreria/GAYF | E21: Otros Riesgos | F21: Pago a Proveedores | H21: Pagos indebidos por ejecución anticipada sin soporte o incumpliendo condiciones contractuales | I21: Descripción: Posibilidad de realizar pagos a proveedores o terceros de manera anticipada o con inusual prontitud, sin contar con el debido respaldo documental o sin el cumplimiento de las condiciones contractuales establecidas, como consecuencia de colusión interna, presiones indebidas de funcionarios o exigencias de proveedores Causas: Debilidades en la verificación de cumplimiento contractual, Falta de segregación de funciones en el ciclo de pagos Presión interna para agilizar pagos Ausencia de controles en la validación documental Colusión entre empleados y proveedores Manipulación de urgencias operativas Prácticas corruptas (sobornos o incentivos) Efecto: Pérdidas económicas/riesgo reputacional/riego legal x incumplimiento contractual/materializacion de actos de corrupcion/Debilitamiento del Control Interno | J21: 3 | K21: 5 | L21: =IF((Matriz_Riesgos[[#This Row],[Frecuencia]]+Matriz_Riesgos[[#This Row],[Impacto]]-1)=-1,"",Matriz_Riesgos[[#This Row],[Frecuencia]]+Matriz_Riesgos[[#This Row],[Impacto]]-1) -> 7 | M21: =IFERROR(VLOOKUP(Matriz_Riesgos[[#This Row],[Valor del Riesgo Inherente]],t_nivel_riesgo[],2,FALSE), "") -> Riesgo Alto | N21: Compras, Tesoreria, GAYF | O21: Todos | P21: Fraude/Corrupcion/Legal/Reputacional/Operativo | T21: 1. Políticas claras de pagos (no anticipos sin autorización formal) 2. Segregación de funciones (solicitud, validación, aprobación y pago) 3. Registro y control de excepciones debidamente autorizadas 4. valuación y debida diligencia de proveedores | X21: 1. Auditorías periódicas al proceso 2. Revisión de pagos anticipados o fuera de término 3. Reportes de pagos urgentes o excepcionales 4. Cruce entre pagos realizados y cumplimiento contractual 5. Monitoreo de patrones de pago por proveedor (frecuencias de pago (¿Hay proveedores con pagos demasiado frecuentes?), montos de pago (Pagos fraccionados (muchos pagos pequeños), Promedio de pago por proveedor, Pagos por encima del promedio histórico), Concentracion (Proveedores que concentran alto volumen de pagos), Oportunidad del pago (Comparación de pagos vs condiciones contractuales) y variaciones (Cambios bruscos en montos o frecuencia, Incrementos injustificados) | AB21: 1. Suspensión de pagos irregulares 2. Recuperación de recursos pagados indebidamente 3. Investigación interna 4. Aplicación de sanciones disciplinarias 5. Ajustes en procesos y fortalecimiento de controles | AG21: =IF(AND(T21="",X21="",AB21=""),"",('Otras Tablas'!$B$3*IF(W21="",0,W21)+'Otras Tablas'!$B$4*IF(AA21="",0,AA21)+'Otras Tablas'!$B$5*IF(AE21="",0,AE21))) | AH21: =IF(Matriz_Riesgos[[#This Row],[Riesgo Inherente]]="","",Matriz_Riesgos[[#This Row],[Riesgo Inherente]]) -> Pagos indebidos por ejecución anticipada sin soporte o incumpliendo condiciones contractuales | AI21: =IFERROR(IF(OR(Matriz_Riesgos[[#This Row],[Frecuencia]]="",Matriz_Riesgos[[#This Row],[Impacto]]="",Matriz_Riesgos[[#This Row],[Valor del Riesgo Inherente]]="",Matriz_Riesgos[[#This Row],[Valor del Riesgo Residual]]=""),"",IF(Matriz_Riesgos[[#This Row],[Valor del Riesgo Inherente]]=Matriz_Riesgos[[#This Row],[Valor del Riesgo Residual]],Matriz_Riesgos[[#This Row],[Frecuencia]],MIN(Matriz_Riesgos[[#This Row],[Tope F (AUX)]], Matriz_Riesgos[[#This Row],[F_base (AUX)]]+Matriz_Riesgos[[#This Row],[Inc_F (AUX)]]))),"") -> 3 | AJ21: =IFERROR(IF(OR(Matriz_Riesgos[[#This Row],[Frecuencia]]="",Matriz_Riesgos[[#This Row],[Impacto]]="",Matriz_Riesgos[[#This Row],[Valor del Riesgo Inherente]]="",Matriz_Riesgos[[#This Row],[Valor del Riesgo Residual]]=""),"",IF(Matriz_Riesgos[[#This Row],[Valor del Riesgo Inherente]]=Matriz_Riesgos[[#This Row],[Valor del Riesgo Residual]],Matriz_Riesgos[[#This Row],[Impacto]],MIN(Matriz_Riesgos[[#This Row],[Tope I (AUX)]], Matriz_Riesgos[[#This Row],[I_base (AUX)]]+Matriz_Riesgos[[#This Row],[Inc_I (AUX)]]))),"") -> 5 | AK21: =IFERROR(ROUND(MAX(1,Matriz_Riesgos[[#This Row],[Valor del Riesgo Inherente]]*(1 - Matriz_Riesgos[[#This Row],[Efectividad Total Ponderada de los Controles]])),0), "") -> 7 | AL21: =IFERROR(VLOOKUP(Matriz_Riesgos[[#This Row],[Valor del Riesgo Residual]],t_nivel_riesgo[],2,FALSE),"") -> Riesgo Alto | AM21: Evitar | AX21: =IFERROR((1-Matriz_Riesgos[[#This Row],[Efectividad Total Ponderada de los Controles]])*Matriz_Riesgos[[#This Row],[Frecuencia]],"") -> 3 | AY21: =IFERROR((1-Matriz_Riesgos[[#This Row],[Efectividad Total Ponderada de los Controles]])*Matriz_Riesgos[[#This Row],[Impacto]],"") -> 5 | AZ21: =IFERROR(Matriz_Riesgos[[#This Row],[Valor del Riesgo Residual]] + 1, "") -> 8 | BA21: =IFERROR(MAX(1, ROUNDDOWN(Matriz_Riesgos[[#This Row],[Frecuencia Residual (AUX)]],0)),"") -> 3 | BB21: =IFERROR(MAX(1, ROUNDDOWN(Matriz_Riesgos[[#This Row],[Impacto Residual (AUX)]],0)),"") -> 5 | BC21: =IF(Matriz_Riesgos[[#This Row],[Frecuencia]]="","",Matriz_Riesgos[[#This Row],[Frecuencia]]) -> 3 | BD21: =IF(Matriz_Riesgos[[#This Row],[Impacto]]="","",Matriz_Riesgos[[#This Row],[Impacto]]) -> 5 | BE21: =IF(OR(Matriz_Riesgos[[#This Row],[Tope F (AUX)]]="",Matriz_Riesgos[[#This Row],[F_base (AUX)]]=""),"",MAX(0,Matriz_Riesgos[[#This Row],[Tope F (AUX)]]-Matriz_Riesgos[[#This Row],[F_base (AUX)]])) -> 0 | BF21: =IF(OR(Matriz_Riesgos[[#This Row],[Tope I (AUX)]]="",Matriz_Riesgos[[#This Row],[I_base (AUX)]]=""),"",MAX(0,Matriz_Riesgos[[#This Row],[Tope I (AUX)]]-Matriz_Riesgos[[#This Row],[I_base (AUX)]])) -> 0 | BG21: =IF(OR(Matriz_Riesgos[[#This Row],[Suma Residual redondeada (AUX)]]="",Matriz_Riesgos[[#This Row],[F_base (AUX)]]="",Matriz_Riesgos[[#This Row],[I_base (AUX)]]=""),"",MAX(0,Matriz_Riesgos[[#This Row],[Suma Residual redondeada (AUX)]]-(Matriz_Riesgos[[#This Row],[F_base (AUX)]]+Matriz_Riesgos[[#This Row],[I_base (AUX)]]))) -> 0 | BH21: =IF(OR(Matriz_Riesgos[[#This Row],[Impacto Residual (AUX)]]="",Matriz_Riesgos[[#This Row],[Frecuencia Residual (AUX)]]=""),"",IF(MOD(Matriz_Riesgos[[#This Row],[Impacto Residual (AUX)]],1) > MOD(Matriz_Riesgos[[#This Row],[Frecuencia Residual (AUX)]],1),1,IF(MOD(Matriz_Riesgos[[#This Row],[Impacto Residual (AUX)]],1) = MOD(Matriz_Riesgos[[#This Row],[Frecuencia Residual (AUX)]],1),1,0))) -> 1 | BI21: =IF(OR(Matriz_Riesgos[[#This Row],[Resto (AUX)]]="",Matriz_Riesgos[[#This Row],[Capacidad I (AUX)]]="",Matriz_Riesgos[[#This Row],[Capacidad F (AUX)]]=""),"",IF(Matriz_Riesgos[[#This Row],[Resto (AUX)]]=0, 0,IF(Matriz_Riesgos[[#This Row],[Resto (AUX)]]=1,MIN(Matriz_Riesgos[[#This Row],[Capacidad I (AUX)]], IF(OR(Matriz_Riesgos[[#This Row],[Prefiere I (AUX)]]=1,Matriz_Riesgos[[#This Row],[Capacidad F (AUX)]]=0),1,0)),MIN(Matriz_Riesgos[[#This Row],[Capacidad I (AUX)]],IF(Matriz_Riesgos[[#This Row],[Prefiere I (AUX)]]=1,1 + IF(Matriz_Riesgos[[#This Row],[Capacidad F (AUX)]]>0,0,1),IF(Matriz_Riesgos[[#This Row],[Capacidad F (AUX)]]>0,1,2)))))) -> 0 | BJ21: =IF(OR(Matriz_Riesgos[[#This Row],[Resto (AUX)]]="",Matriz_Riesgos[[#This Row],[Capacidad F (AUX)]]="",Matriz_Riesgos[[#This Row],[Inc_I (AUX)]]=""),"",MIN(Matriz_Riesgos[[#This Row],[Capacidad F (AUX)]], MAX(0,Matriz_Riesgos[[#This Row],[Resto (AUX)]]-Matriz_Riesgos[[#This Row],[Inc_I (AUX)]]))) -> 0 | BK21: =IFERROR(MAX(ROUND(Matriz_Riesgos[[#This Row],[Frecuencia Residual (AUX)]]+Matriz_Riesgos[[#This Row],[Impacto Residual (AUX)]]-1+Matriz_Riesgos[[#This Row],[Efectividad Total Ponderada de los Controles]],0),1),"") -> 7 | BL21: =IFERROR(Matriz_Riesgos[[#This Row],[Valor del Riesgo Residual]]-Matriz_Riesgos[[#This Row],[Valor del Riesgo Residual (AUX)]],"") -> 0 | BM21: =IFERROR(Matriz_Riesgos[[#This Row],[Frecuencia Residual]]+Matriz_Riesgos[[#This Row],[Impacto Residual]]-1,"") -> 7 | BN21: =IFERROR(Matriz_Riesgos[[#This Row],[Valor del Riesgo Residual]]-Matriz_Riesgos[[#This Row],[VRR 2]],"") -> 0 | BO21: =IFERROR(Matriz_Riesgos[[#This Row],[Frecuencia]]-Matriz_Riesgos[[#This Row],[Frecuencia Residual]],"") -> 0 | BP21: =IFERROR(Matriz_Riesgos[[#This Row],[Impacto]]-Matriz_Riesgos[[#This Row],[Impacto Residual]],"") -> 0 | BQ21: =IFERROR(Matriz_Riesgos[[#This Row],[Valor del Riesgo Inherente]]-Matriz_Riesgos[[#This Row],[Valor del Riesgo Residual]],"") -> 0 | BR21: 1. Pagos realizados antes de la recepción de bienes o servicios (pago sin orden de compra bloquear) 2. Aprobaciones de pago fuera del flujo normal 3. Pagos urgentes sin justificación válida 4. Proveedores que insisten en pagos anticipados 5. Aumento repentino en pagos a un proveedor específico (mas de 3 alerta) 6. Modificaciones contractuales no formalizadas 7. Intervención inusual de altos cargos para autorizar pagos 8. numero de hallazgos de auditoria (KRI) 9. Pagos en días no habituales (festivos, fines de semana)
A22: 21 | B22: ROTR-COMPRASGAYF-21 | C22: Compras/GAYF | E22: Otros Riesgos | F22: Compras | H22: Fraccionamiento recurrente de compras | I22: Descripción: Posibilidad de que se autoricen compras de bienes y/o servicios sin cumplir con las exigencias normativas internas y externas en cuanto a tipo de bien, servicio y montos establecidos, debido a debilidades en los controles, discrecionalidad en la aprobación y falta de supervisióncidos Causas: Desconocimiento de normativas, Abuso de autoridad, Falta de ética o conflictos de interés, Procedimientos no estandarizados, Ausencia de controles de validación previa, Falta de segregación de funciones, Sistemas sin restricciones automáticas por montos, Ausencia de trazabilidad digital Presión por urgencias operativas (ej. insumos médicos), Influencias externas o colusión con proveedores. Efecto: Pérdidas económicas (Sobrecostos, pagos indebidos)/riesgo reputacional (Pérdida de confianza institucional)/riego legal (Sanciones por incumplimiento normativo)/operativo (Ineficiencia en adquisiciones)/social (Afectación en calidad de servicios de salud) | J22: 2 | K22: 5 | L22: =IF((Matriz_Riesgos[[#This Row],[Frecuencia]]+Matriz_Riesgos[[#This Row],[Impacto]]-1)=-1,"",Matriz_Riesgos[[#This Row],[Frecuencia]]+Matriz_Riesgos[[#This Row],[Impacto]]-1) -> 6 | M22: =IFERROR(VLOOKUP(Matriz_Riesgos[[#This Row],[Valor del Riesgo Inherente]],t_nivel_riesgo[],2,FALSE), "") -> Riesgo Alto | N22: Compras | O22: Todos | P22: Fraude/Corrupcion/LAFT | T22: 1. Políticas y manuales de contratación formalmente aprobados 2. Definición de niveles de autorización por montos 3. Segregación de funciones (solicitud, evaluación, aprobación) 4. Registro de proveedores validados | X22: 1. Auditorías periódicas a procesos de compras 2. Revisión de cumplimiento de topes y procesos (Ley) 3. Monitoreo de excepciones | AB22: 1. Procesos disciplinarios 2. Ajustes a procedimientos 3. Reporte a entes de control | AG22: =IF(AND(T22="",X22="",AB22=""),"",('Otras Tablas'!$B$3*IF(W22="",0,W22)+'Otras Tablas'!$B$4*IF(AA22="",0,AA22)+'Otras Tablas'!$B$5*IF(AE22="",0,AE22))) | AH22: =IF(Matriz_Riesgos[[#This Row],[Riesgo Inherente]]="","",Matriz_Riesgos[[#This Row],[Riesgo Inherente]]) -> Fraccionamiento recurrente de compras | AI22: =IFERROR(IF(OR(Matriz_Riesgos[[#This Row],[Frecuencia]]="",Matriz_Riesgos[[#This Row],[Impacto]]="",Matriz_Riesgos[[#This Row],[Valor del Riesgo Inherente]]="",Matriz_Riesgos[[#This Row],[Valor del Riesgo Residual]]=""),"",IF(Matriz_Riesgos[[#This Row],[Valor del Riesgo Inherente]]=Matriz_Riesgos[[#This Row],[Valor del Riesgo Residual]],Matriz_Riesgos[[#This Row],[Frecuencia]],MIN(Matriz_Riesgos[[#This Row],[Tope F (AUX)]], Matriz_Riesgos[[#This Row],[F_base (AUX)]]+Matriz_Riesgos[[#This Row],[Inc_F (AUX)]]))),"") -> 2 | AJ22: =IFERROR(IF(OR(Matriz_Riesgos[[#This Row],[Frecuencia]]="",Matriz_Riesgos[[#This Row],[Impacto]]="",Matriz_Riesgos[[#This Row],[Valor del Riesgo Inherente]]="",Matriz_Riesgos[[#This Row],[Valor del Riesgo Residual]]=""),"",IF(Matriz_Riesgos[[#This Row],[Valor del Riesgo Inherente]]=Matriz_Riesgos[[#This Row],[Valor del Riesgo Residual]],Matriz_Riesgos[[#This Row],[Impacto]],MIN(Matriz_Riesgos[[#This Row],[Tope I (AUX)]], Matriz_Riesgos[[#This Row],[I_base (AUX)]]+Matriz_Riesgos[[#This Row],[Inc_I (AUX)]]))),"") -> 5 | AK22: =IFERROR(ROUND(MAX(1,Matriz_Riesgos[[#This Row],[Valor del Riesgo Inherente]]*(1 - Matriz_Riesgos[[#This Row],[Efectividad Total Ponderada de los Controles]])),0), "") -> 6 | AL22: =IFERROR(VLOOKUP(Matriz_Riesgos[[#This Row],[Valor del Riesgo Residual]],t_nivel_riesgo[],2,FALSE),"") -> Riesgo Alto | AM22: Evitar | AN22: 1. Implementar controles automáticos por montos en sistema 2. Fortalecer segregación de funciones 3. Capacitación en normativa de contratación y prevencion de riesgos 4. Implementar analítica de datos para detectar anomalías | AX22: =IFERROR((1-Matriz_Riesgos[[#This Row],[Efectividad Total Ponderada de los Controles]])*Matriz_Riesgos[[#This Row],[Frecuencia]],"") -> 2 | AY22: =IFERROR((1-Matriz_Riesgos[[#This Row],[Efectividad Total Ponderada de los Controles]])*Matriz_Riesgos[[#This Row],[Impacto]],"") -> 5 | AZ22: =IFERROR(Matriz_Riesgos[[#This Row],[Valor del Riesgo Residual]] + 1, "") -> 7 | BA22: =IFERROR(MAX(1, ROUNDDOWN(Matriz_Riesgos[[#This Row],[Frecuencia Residual (AUX)]],0)),"") -> 2 | BB22: =IFERROR(MAX(1, ROUNDDOWN(Matriz_Riesgos[[#This Row],[Impacto Residual (AUX)]],0)),"") -> 5 | BC22: =IF(Matriz_Riesgos[[#This Row],[Frecuencia]]="","",Matriz_Riesgos[[#This Row],[Frecuencia]]) -> 2 | BD22: =IF(Matriz_Riesgos[[#This Row],[Impacto]]="","",Matriz_Riesgos[[#This Row],[Impacto]]) -> 5 | BE22: =IF(OR(Matriz_Riesgos[[#This Row],[Tope F (AUX)]]="",Matriz_Riesgos[[#This Row],[F_base (AUX)]]=""),"",MAX(0,Matriz_Riesgos[[#This Row],[Tope F (AUX)]]-Matriz_Riesgos[[#This Row],[F_base (AUX)]])) -> 0 | BF22: =IF(OR(Matriz_Riesgos[[#This Row],[Tope I (AUX)]]="",Matriz_Riesgos[[#This Row],[I_base (AUX)]]=""),"",MAX(0,Matriz_Riesgos[[#This Row],[Tope I (AUX)]]-Matriz_Riesgos[[#This Row],[I_base (AUX)]])) -> 0 | BG22: =IF(OR(Matriz_Riesgos[[#This Row],[Suma Residual redondeada (AUX)]]="",Matriz_Riesgos[[#This Row],[F_base (AUX)]]="",Matriz_Riesgos[[#This Row],[I_base (AUX)]]=""),"",MAX(0,Matriz_Riesgos[[#This Row],[Suma Residual redondeada (AUX)]]-(Matriz_Riesgos[[#This Row],[F_base (AUX)]]+Matriz_Riesgos[[#This Row],[I_base (AUX)]]))) -> 0 | BH22: =IF(OR(Matriz_Riesgos[[#This Row],[Impacto Residual (AUX)]]="",Matriz_Riesgos[[#This Row],[Frecuencia Residual (AUX)]]=""),"",IF(MOD(Matriz_Riesgos[[#This Row],[Impacto Residual (AUX)]],1) > MOD(Matriz_Riesgos[[#This Row],[Frecuencia Residual (AUX)]],1),1,IF(MOD(Matriz_Riesgos[[#This Row],[Impacto Residual (AUX)]],1) = MOD(Matriz_Riesgos[[#This Row],[Frecuencia Residual (AUX)]],1),1,0))) -> 1 | BI22: =IF(OR(Matriz_Riesgos[[#This Row],[Resto (AUX)]]="",Matriz_Riesgos[[#This Row],[Capacidad I (AUX)]]="",Matriz_Riesgos[[#This Row],[Capacidad F (AUX)]]=""),"",IF(Matriz_Riesgos[[#This Row],[Resto (AUX)]]=0, 0,IF(Matriz_Riesgos[[#This Row],[Resto (AUX)]]=1,MIN(Matriz_Riesgos[[#This Row],[Capacidad I (AUX)]], IF(OR(Matriz_Riesgos[[#This Row],[Prefiere I (AUX)]]=1,Matriz_Riesgos[[#This Row],[Capacidad F (AUX)]]=0),1,0)),MIN(Matriz_Riesgos[[#This Row],[Capacidad I (AUX)]],IF(Matriz_Riesgos[[#This Row],[Prefiere I (AUX)]]=1,1 + IF(Matriz_Riesgos[[#This Row],[Capacidad F (AUX)]]>0,0,1),IF(Matriz_Riesgos[[#This Row],[Capacidad F (AUX)]]>0,1,2)))))) -> 0 | BJ22: =IF(OR(Matriz_Riesgos[[#This Row],[Resto (AUX)]]="",Matriz_Riesgos[[#This Row],[Capacidad F (AUX)]]="",Matriz_Riesgos[[#This Row],[Inc_I (AUX)]]=""),"",MIN(Matriz_Riesgos[[#This Row],[Capacidad F (AUX)]], MAX(0,Matriz_Riesgos[[#This Row],[Resto (AUX)]]-Matriz_Riesgos[[#This Row],[Inc_I (AUX)]]))) -> 0 | BK22: =IFERROR(MAX(ROUND(Matriz_Riesgos[[#This Row],[Frecuencia Residual (AUX)]]+Matriz_Riesgos[[#This Row],[Impacto Residual (AUX)]]-1+Matriz_Riesgos[[#This Row],[Efectividad Total Ponderada de los Controles]],0),1),"") -> 6 | BL22: =IFERROR(Matriz_Riesgos[[#This Row],[Valor del Riesgo Residual]]-Matriz_Riesgos[[#This Row],[Valor del Riesgo Residual (AUX)]],"") -> 0 | BM22: =IFERROR(Matriz_Riesgos[[#This Row],[Frecuencia Residual]]+Matriz_Riesgos[[#This Row],[Impacto Residual]]-1,"") -> 6 | BN22: =IFERROR(Matriz_Riesgos[[#This Row],[Valor del Riesgo Residual]]-Matriz_Riesgos[[#This Row],[VRR 2]],"") -> 0 | BO22: =IFERROR(Matriz_Riesgos[[#This Row],[Frecuencia]]-Matriz_Riesgos[[#This Row],[Frecuencia Residual]],"") -> 0 | BP22: =IFERROR(Matriz_Riesgos[[#This Row],[Impacto]]-Matriz_Riesgos[[#This Row],[Impacto Residual]],"") -> 0 | BQ22: =IFERROR(Matriz_Riesgos[[#This Row],[Valor del Riesgo Inherente]]-Matriz_Riesgos[[#This Row],[Valor del Riesgo Residual]],"") -> 0 | BR22: 1. Compras recurrentes justo por debajo de los límites de aprobación 2. Uso excesivo de contrataciones directas 3. Proveedores recurrentes sin justificación técnica 4. Falta de documentación de soporte 5. Aprobaciones fuera de horario o en tiempos inusuales 6. Fraccionamiento de compras 7. Cantidad de procesos anulados o cuestionados
